Workbook
Name mutual_fund: 'data valadiation'!$C$4

Sheet nifty 500 co list
B1: LTP (₹) | C1: 1D change % | D1: Market Cap (Cr) | E1: 52W High / Low (₹) | I1: Volume | J1: Company | L1: High | M1: Low | N1: Current Price
B2: 486.95 | C2: 8.07 | D2: 9832 | E2: 691.80/343.50 | I2: 2551655 | J2: Balrampur Chini Mills Ltd. | L2: 691.8 | M2: 343.5 | N2: 486.95
B3: 714.6 | C3: 5.6 | D3: 19023 | E3: 1,313.25/648.60 | I3: 4096631 | J3: KEC International Ltd. | L3: 1313.25 | M3: 648.6 | N3: 714.6
B4: 4014.4 | C4: 5.37 | D4: 54345 | E4: 6,133.40/1,941.05 | I4: 6327755 | J4: BSE Ltd. | L4: 6133.4 | M4: 1941.05 | N4: 4014.4
B5: 229.31 | C5: 4.57 | D5: 31797 | E5: 311.80/186.03 | I5: 10632915 | J5: NLC India Ltd. | L5: 311.8 | M5: 186.03 | N5: 229.31
B6: 684.7 | C6: 4.38 | D6: 53342 | E6: 1,576.35/606.00 | I6: 108682122 | J6: IndusInd Bank Ltd. | L6: 1576.35 | M6: 606 | N6: 684.7
B7: 549.7 | C7: 4.32 | D7: 21996 | E7: 674.30/350.00 | I7: 888471 | J7: Krishna Institute of Medical Sciences Ltd. | L7: 674.3 | M7: 350 | N7: 549.7
B8: 5436.45 | C8: 4.02 | D8: 28266 | E8: 8,480.00/2,805.55 | I8: 122692 | J8: Godfrey Phillips India Ltd. | L8: 8480 | M8: 2805.55 | N8: 5436.45
B9: 4658.4 | C9: 3.94 | D9: 51757 | E9: 5,535.85/3,622.25 | I9: 182032 | J9: Sundaram Finance Ltd. | L9: 5535.85 | M9: 3622.25 | N9: 4658.4
B10: 225.53 | C10: 3.66 | D10: 143286 | E10: 394.70/198.65 | I10: 28455086 | J10: Jio Financial Services Ltd. | L10: 394.7 | M10: 198.65 | N10: 225.53
B11: 853.45 | C11: 3.55 | D11: 135189 | E11: 2,174.10/758.00 | I11: 4826264 | J11: Adani Green Energy Ltd. | L11: 2174.1 | M11: 758 | N11: 853.45
B12: 357.65 | C12: 3.37 | D12: 23025 | E12: 484.00/261.25 | I12: 3496657 | J12: Crompton Greaves Consumer Electricals Ltd. | L12: 484 | M12: 261.25 | N12: 357.65
B13: 735.75 | C13: 3.36 | D13: 25825 | E13: 1,037.00/357.05 | I13: 1805402 | J13: Aegis Logistics Ltd. | L13: 1037 | M13: 357.05 | N13: 735.75
... B501: 522.55 | C501: -9.52 | D501: 12503 | E501: 736.30/452.00 | I501: 2913334 | J501: Indegene Ltd. | L501: 736.3 | M501: 452 | N501: 522.55

Sheet return on incides
A1: Symbol | B1: 1M | C1: 3M | D1: 1Yr | E1: 3Yr | F1: 5Yr | G1: 10Yr | Q1: mutual funds: kotak | Z1: kotak & nifty indices | AE1: nippon & nifty indices | AJ1: parag & nifty indices | AO1: quant & nifty indices
A2: Nifty 50 | B2: -3.88 | C2: -8.52 | D2: 1.09 | E2: 11.94 | F2: 17.92 | G2: 11.29 | I2: Row Labels | J2: Sum of 1M | K2: Sum of 3M | L2: Sum of 1Yr | M2: Sum of 3Yr | N2: Sum of 5Yr | O2: Sum of 10Yr | Q2: Period Invested for | R2: 1 Month | S2: 3 Month | T2: 1 Year | U2: 3 Year | V2: 5 Year | W2: 10 Year | X2: sprklines | Z2: 1 yr | AA2: 3yr | AB2: 5yr | AC2: 10yr | AD2: kotak is performing beter than these indices | AE2: 1 yr | AF2: 3yr | AG2: 5yr | AH2: 10yr | AJ2: 1 yr | AK2: 3yr | AL2: 5yr | AM2: 10yr | AO2: 1 yr | AP2: 3yr | AQ2: 5yr | AR2: 10yr
A3: Nifty 100 | B3: -4.15 | C3: -10.38 | D3: 0.49 | E3: 12.01 | F3: 17.99 | G3: 11.47 | I3: Nifty 500 | J3: -5.11 | K3: -12.91 | L3: 0.14 | M3: 13.75 | N3: 19.85 | O3: 12.24 | Q3: =HYPERLINK("#'Kotak Holdings'!A1", " Kotak returns") -> Kotak returns | R3: -0.0774 | S3: -0.1864 | T3: 0.083 | U3: 0.6441 | V3: 1.875 | W3: 3.2846 | Z3: =IF($T$3>D2,"good","not good") -> not good | AA3: =IF($U$3>E2,"good","not good") -> not good | AB3: =IF($W$3>F2,"good","not good") -> not good | AC3: =IF($V$3>G2,"good","not good") -> not good | AD3: =IF(Z3="good",A2,"") | AE3: =IF($T$4>D2,"good") -> FALSE | AF3: =IF($U$4>E2,"good") -> FALSE | AG3: =IF($V$4>F2,"good") -> FALSE | AH3: =IF($W$4>G2,"good") -> FALSE | AK3: =IF($U$5>E2,"good") -> FALSE | AL3: =IF($V$5>F2,"good") -> FALSE | AM3: =IF($W$5>G2,"good") -> FALSE | AO3: =IF($T$6>D2,"good") -> FALSE | AP3: =IF($U$6>E2,"good") -> FALSE | AQ3: =IF($V$6>F2,"good") -> FALSE | AR3: =IF($W$6>G2,"good") -> FALSE
A4: Nifty 200 | B4: -4.72 | C4: -11.7 | D4: 0.26 | E4: 13.2 | F4: 19.07 | G4: 11.87 | I4: Grand Total | J4: -5.11 | K4: -12.91 | L4: 0.14 | M4: 13.75 | N4: 19.85 | O4: 12.24 | Q4: =HYPERLINK("#'nippon holdings'!A1", "nippon returns") -> nippon returns | R4: -0.0721 | S4: -0.21 | T4: 0.0108 | U4: 0.7864 | V4: 2.9546 | W4: 4.8163 | Z4: =IF($T$3>D3,"good","not good") -> not good | AA4: =IF($U$3>E3,"good","not good") -> not good | AB4: =IF($V$3>F3,"good","not good") -> not good | AC4: =IF($V$3>G3,"good","not good") -> not good | AD4: =IF(Z4="good",A3,"") | AE4: =IF($T$4>D3,"good") -> FALSE | AF4: =IF($U$4>E3,"good") -> FALSE | AG4: =IF($V$4>F3,"good") -> FALSE | AH4: =IF($W$4>G3,"good") -> FALSE | AJ4: =IF($T$5>D3,"good") -> FALSE | AK4: =IF($U$5>E3,"good") -> FALSE | AL4: =IF($V$5>F3,"good") -> FALSE | AM4: =IF($W$5>G3,"good") -> FALSE | AO4: =IF($T$6>D3,"good") -> FALSE | AP4: =IF($U$6>E3,"good") -> FALSE | AQ4: =IF($V$6>F3,"good") -> FALSE | AR4: =IF($W$6>G3,"good") -> FALSE
A5: Nifty 500 | B5: -5.11 | C5: -12.91 | D5: 0.14 | E5: 13.75 | F5: 19.85 | G5: 12.24 | Q5: =HYPERLINK("#'parag holdings'!A1","parag parik returns") -> parag parik returns | R5: -0.0356 | S5: -0.0595 | T5: 0.1028 | U5: 0.6472 | V5: 2.0871 | W5: 3.6719 | Z5: =IF($T$3>D4,"good","not good") -> not good | AA5: =IF($U$3>E4,"good","not good") -> not good | AB5: =IF($V$3>F4,"good","not good") -> not good | AC5: =IF($V$3>G4,"good","not good") -> not good | AD5: =IF(Z5="good",A4,"") | AE5: =IF($T$4>D4,"good") -> FALSE | AF5: =IF($U$4>E4,"good") -> FALSE | AG5: =IF($V$4>F4,"good") -> FALSE | AH5: =IF($W$4>G4,"good") -> FALSE | AJ5: =IF($T$5>D4,"good") -> FALSE | AK5: =IF($U$5>E4,"good") -> FALSE | AL5: =IF($V$5>F4,"good") -> FALSE | AM5: =IF($W$5>G4,"good") -> FALSE | AO5: =IF($T$6>D4,"good") -> FALSE | AP5: =IF($U$6>E4,"good") -> FALSE | AQ5: =IF($V$6>F4,"good") -> FALSE | AR5: =IF($W$6>G4,"good") -> FALSE
A6: NIFTY TOTAL MKT | B6: -5.27 | C6: -13.3 | D6: 0.22 | E6: 14.14 | F6: 20.3 | G6: 12.46 | Q6: =HYPERLINK("#'quant holdings'!A1", "quant returns") -> quant returns | R6: -0.0587 | S6: -0.1521 | T6: -0.0988 | U6: 0.6834 | V6: 2.6856 | W6: 3.3162 | Z6: =IF($T$3>D5,"good","not good") -> not good | AA6: =IF($U$3>E5,"good","not good") -> not good | AB6: =IF($V$3>F5,"good","not good") -> not good | AC6: =IF($V$3>G5,"good","not good") -> not good | AD6: =IF(Z6="good",A5,"") | AE6: =IF($T$4>D5,"good") -> FALSE | AF6: =IF($U$4>E5,"good") -> FALSE | AG6: =IF($V$4>F5,"good") -> FALSE | AH6: =IF($W$4>G5,"good") -> FALSE | AJ6: =IF($T$5>D5,"good") -> FALSE | AK6: =IF($U$5>E5,"good") -> FALSE | AL6: =IF($V$5>F5,"good") -> FALSE | AM6: =IF($W$5>G5,"good") -> FALSE | AO6: =IF($T$6>D5,"good") -> FALSE | AP6: =IF($U$6>E5,"good") -> FALSE | AQ6: =IF($V$6>F5,"good") -> FALSE | AR6: =IF($W$6>G5,"good") -> FALSE
A7: Nifty Next 50 | B7: -5.39 | C7: -19.15 | D7: -1.53 | E7: 14.77 | F7: 19.53 | G7: 12.76 | Z7: =IF($T$3>D6,"good","not good") -> not good | AA7: =IF($U$3>E6,"good","not good") -> not good | AB7: =IF($V$3>F6,"good","not good") -> not good | AC7: =IF($V$3>G6,"good","not good") -> not good | AD7: =IF(Z7="good",A6,"") | AE7: =IF($T$4>D6,"good") -> FALSE | AF7: =IF($U$4>E6,"good") -> FALSE | AG7: =IF($V$4>F6,"good") -> FALSE | AH7: =IF($W$4>G6,"good") -> FALSE | AJ7: =IF($T$5>D6,"good") -> FALSE | AK7: =IF($U$5>E6,"good") -> FALSE | AL7: =IF($V$5>F6,"good") -> FALSE | AM7: =IF($W$5>G6,"good") -> FALSE | AO7: =IF($T$6>D6,"good") -> FALSE | AP7: =IF($U$6>E6,"good") -> FALSE | AQ7: =IF($V$6>F6,"good") -> FALSE | AR7: =IF($W$6>G6,"good") -> FALSE
A8: NIFTY Smallcap 100 | B8: -8.68 | C8: -22.31 | D8: -2.56 | E8: 15.63 | F8: 25.16 | G8: 11.39 | Z8: =IF($T$3>D7,"good","not good") -> good | AA8: =IF($U$3>E7,"good","not good") -> not good | AB8: =IF($V$3>F7,"good","not good") -> not good | AC8: =IF($V$3>G7,"good","not good") -> not good | AD8: =IF(Z8="good",A7,"") -> Nifty Next 50 | AE8: =IF($T$4>D7,"good") -> good | AF8: =IF($U$4>E7,"good") -> FALSE | AG8: =IF($V$4>F7,"good") -> FALSE | AH8: =IF($W$4>G7,"good") -> FALSE | AJ8: =IF($T$5>D7,"good") -> good | AK8: =IF($U$5>E7,"good") -> FALSE | AL8: =IF($V$5>F7,"good") -> FALSE | AM8: =IF($W$5>G7,"good") -> FALSE | AO8: =IF($T$6>D7,"good") -> good | AP8: =IF($U$6>E7,"good") -> FALSE | AQ8: =IF($V$6>F7,"good") -> FALSE | AR8: =IF($W$6>G7,"good") -> FALSE
A9: NIFTY500 MULTICAP 50:25:25 | B9: -5.93 | C9: -15.08 | D9: 0.02 | E9: 15.65 | F9: 22.54 | G9: 13.32 | Z9: =IF($T$3>D8,"good","not good") -> good | AA9: =IF($U$3>E8,"good","not good") -> not good | AB9: =IF($V$3>F8,"good","not good") -> not good | AC9: =IF($V$3>G8,"good","not good") -> not good | AD9: =IF(Z9="good",A8,"") -> NIFTY Smallcap 100 | AE9: =IF($T$4>D8,"good") -> good | AF9: =IF($U$4>E8,"good") -> FALSE | AG9: =IF($V$4>F8,"good") -> FALSE | AH9: =IF($W$4>G8,"good") -> FALSE | AJ9: =IF($T$5>D8,"good") -> good | AK9: =IF($U$5>E8,"good") -> FALSE | AL9: =IF($V$5>F8,"good") -> FALSE | AM9: =IF($W$5>G8,"good") -> FALSE | AO9: =IF($T$6>D8,"good") -> good | AP9: =IF($U$6>E8,"good") -> FALSE | AQ9: =IF($V$6>F8,"good") -> FALSE | AR9: =IF($W$6>G8,"good") -> FALSE
A10: NIFTY LargeMidcap 250 | B10: -5.55 | C10: -13.79 | D10: 0.79 | E10: 16.27 | F10: 22.12 | G10: 13.9 | Z10: =IF($T$3>D9,"good","not good") -> good | AA10: =IF($U$3>E9,"good","not good") -> not good | AB10: =IF($V$3>F9,"good","not good") -> not good | AC10: =IF($V$3>G9,"good","not good") -> not good | AD10: =IF(Z10="good",A9,"") -> NIFTY500 MULTICAP 50:25:25 | AE10: =IF($T$4>D9,"good") -> FALSE | AF10: =IF($U$4>E9,"good") -> FALSE | AG10: =IF($V$4>F9,"good") -> FALSE | AH10: =IF($W$4>G9,"good") -> FALSE | AJ10: =IF($T$5>D9,"good") -> good | AK10: =IF($U$5>E9,"good") -> FALSE | AL10: =IF($V$5>F9,"good") -> FALSE | AM10: =IF($W$5>G9,"good") -> FALSE | AO10: =IF($T$6>D9,"good") -> FALSE | AP10: =IF($U$6>E9,"good") -> FALSE | AQ10: =IF($V$6>F9,"good") -> FALSE | AR10: =IF($W$6>G9,"good") -> FALSE
A11: Nifty500 LargeMidSmall Equal-Cap Weighted | B11: -6.56 | C11: -16.65 | D11: -0.24 | E11: 16.77 | F11: 23.92 | G11: 13.81 | Z11: =IF($T$3>D10,"good","not good") -> not good | AA11: =IF($U$3>E10,"good","not good") -> not good | AB11: =IF($V$3>F10,"good","not good") -> not good | AC11: =IF($V$3>G10,"good","not good") -> not good | AD11: =IF(Z11="good",A10,"") | AE11: =IF($T$4>D10,"good") -> FALSE | AF11: =IF($U$4>E10,"good") -> FALSE | AG11: =IF($V$4>F10,"good") -> FALSE | AH11: =IF($W$4>G10,"good") -> FALSE | AJ11: =IF($T$5>D10,"good") -> FALSE | AK11: =IF($U$5>E10,"good") -> FALSE | AL11: =IF($V$5>F10,"good") -> FALSE | AM11: =IF($W$5>G10,"good") -> FALSE | AO11: =IF($T$6>D10,"good") -> FALSE | AP11: =IF($U$6>E10,"good") -> FALSE | AQ11: =IF($V$6>F10,"good") -> FALSE | AR11: =IF($W$6>G10,"good") -> FALSE
A12: NIFTY SMALLCAP 50 | B12: -8.67 | C12: -22.39 | D12: 1.99 | E12: 17.14 | F12: 25.55 | G12: 9.76 | Z12: =IF($T$3>D11,"good","not good") -> good | AA12: =IF($U$3>E11,"good","not good") -> not good | AB12: =IF($V$3>F11,"good","not good") -> not good | AC12: =IF($V$3>G11,"good","not good") -> not good | AD12: =IF(Z12="good",A11,"") -> Nifty500 LargeMidSmall Equal-Cap Weighted | AE12: =IF($T$4>D11,"good") -> good | AF12: =IF($U$4>E11,"good") -> FALSE | AG12: =IF($V$4>F11,"good") -> FALSE | AH12: =IF($W$4>G11,"good") -> FALSE | AJ12: =IF($T$5>D11,"good") -> good | AK12: =IF($U$5>E11,"good") -> FALSE | AL12: =IF($V$5>F11,"good") -> FALSE | AM12: =IF($W$5>G11,"good") -> FALSE | AO12: =IF($T$6>D11,"good") -> good | AP12: =IF($U$6>E11,"good") -> FALSE | AQ12: =IF($V$6>F11,"good") -> FALSE | AR12: =IF($W$6>G11,"good") -> FALSE
A13: Nifty smallcap 250 | B13: -8.69 | C13: -22.29 | D13: -2.66 | E13: 17.51 | F13: 27.4 | G13: 13.52 | Z13: =IF($T$3>D12,"good","not good") -> not good | AA13: =IF($U$3>E12,"good","not good") -> not good | AB13: =IF($V$3>F12,"good","not good") -> not good | AC13: =IF($V$3>G12,"good","not good") -> not good | AD13: =IF(Z13="good",A12,"") | AE13: =IF($T$4>D12,"good") -> FALSE | AF13: =IF($U$4>E12,"good") -> FALSE | AG13: =IF($V$4>F12,"good") -> FALSE | AH13: =IF($W$4>G12,"good") -> FALSE | AJ13: =IF($T$5>D12,"good") -> FALSE | AK13: =IF($U$5>E12,"good") -> FALSE | AL13: =IF($V$5>F12,"good") -> FALSE | AM13: =IF($W$5>G12,"good") -> FALSE | AO13: =IF($T$6>D12,"good") -> FALSE | AP13: =IF($U$6>E12,"good") -> FALSE | AQ13: =IF($V$6>F12,"good") -> FALSE | AR13: =IF($W$6>G12,"good") -> FALSE
A14: NIFTY MID SELECT | B14: -7.04 | C14: -16.2 | D14: 1.2 | E14: 17.53 | F14: 24.1 | G14: 15.29 | Z14: =IF($T$3>D13,"good","not good") -> good | AA14: =IF($U$3>E13,"good","not good") -> not good | AB14: =IF($V$3>F13,"good","not good") -> not good | AC14: =IF($V$3>G13,"good","not good") -> not good | AD14: =IF(Z14="good",A13,"") -> Nifty smallcap 250 | AE14: =IF($T$4>D13,"good") -> good | AF14: =IF($U$4>E13,"good") -> FALSE | AG14: =IF($V$4>F13,"good") -> FALSE | AH14: =IF($W$4>G13,"good") -> FALSE | AJ14: =IF($T$5>D13,"good") -> good | AK14: =IF($U$5>E13,"good") -> FALSE | AL14: =IF($V$5>F13,"good") -> FALSE | AM14: =IF($W$5>G13,"good") -> FALSE | AO14: =IF($T$6>D13,"good") -> good | AP14: =IF($U$6>E13,"good") -> FALSE | AQ14: =IF($V$6>F13,"good") -> FALSE | AR14: =IF($W$6>G13,"good") -> FALSE
A15: Nifty MidSmallcap 400 | B15: -7.62 | C15: -19.09 | D15: -0.49 | E15: 19.47 | F15: 26.49 | G15: 15.28 | Z15: =IF($T$3>D14,"good","not good") -> not good | AA15: =IF($U$3>E14,"good","not good") -> not good | AB15: =IF($V$3>F14,"good","not good") -> not good | AC15: =IF($V$3>G14,"good","not good") -> not good | AD15: =IF(Z15="good",A14,"") | AE15: =IF($T$4>D14,"good") -> FALSE | AF15: =IF($U$4>E14,"good") -> FALSE | AG15: =IF($V$4>F14,"good") -> FALSE | AH15: =IF($W$4>G14,"good") -> FALSE | AJ15: =IF($T$5>D14,"good") -> FALSE | AK15: =IF($U$5>E14,"good") -> FALSE | AL15: =IF($V$5>F14,"good") -> FALSE | AM15: =IF($W$5>G14,"good") -> FALSE | AO15: =IF($T$6>D14,"good") -> FALSE | AP15: =IF($U$6>E14,"good") -> FALSE | AQ15: =IF($V$6>F14,"good") -> FALSE | AR15: =IF($W$6>G14,"good") -> FALSE
A16: Nifty Midcap 150 | B16: -7.03 | C16: -17.24 | D16: 0.73 | E16: 20.35 | F16: 26.09 | G16: 16.13 | Z16: =IF($T$3>D15,"good","not good") -> good | AA16: =IF($U$3>E15,"good","not good") -> not good | AB16: =IF($V$3>F15,"good","not good") -> not good | AC16: =IF($V$3>G15,"good","not good") -> not good | AD16: =IF(Z16="good",A15,"") -> Nifty MidSmallcap 400 | AE16: =IF($T$4>D15,"good") -> good | AF16: =IF($U$4>E15,"good") -> FALSE | AG16: =IF($V$4>F15,"good") -> FALSE | AH16: =IF($W$4>G15,"good") -> FALSE | AJ16: =IF($T$5>D15,"good") -> good | AK16: =IF($U$5>E15,"good") -> FALSE | AL16: =IF($V$5>F15,"good") -> FALSE | AM16: =IF($W$5>G15,"good") -> FALSE | AO16: =IF($T$6>D15,"good") -> good | AP16: =IF($U$6>E15,"good") -> FALSE | AQ16: =IF($V$6>F15,"good") -> FALSE | AR16: =IF($W$6>G15,"good") -> FALSE
A17: NIFTY MIDCAP 100 | B17: -7.62 | C17: -18 | D17: -0.56 | E17: 20.81 | F17: 26.38 | G17: 15 | Z17: =IF($T$3>D16,"good","not good") -> not good | AA17: =IF($U$3>E16,"good","not good") -> not good | AB17: =IF($V$3>F16,"good","not good") -> not good | AC17: =IF($V$3>G16,"good","not good") -> not good | AD17: =IF(Z17="good",A16,"") | AE17: =IF($T$4>D16,"good") -> FALSE | AF17: =IF($U$4>E16,"good") -> FALSE | AG17: =IF($V$4>F16,"good") -> FALSE | AH17: =IF($W$4>G16,"good") -> FALSE | AJ17: =IF($T$5>D16,"good") -> FALSE | AK17: =IF($U$5>E16,"good") -> FALSE | AL17: =IF($V$5>F16,"good") -> FALSE | AM17: =IF($W$5>G16,"good") -> FALSE | AO17: =IF($T$6>D16,"good") -> FALSE | AP17: =IF($U$6>E16,"good") -> FALSE | AQ17: =IF($V$6>F16,"good") -> FALSE | AR17: =IF($W$6>G16,"good") -> FALSE
A18: Nifty Midcap 50 | B18: -6.52 | C18: -16.77 | D18: -1.26 | E18: 22 | F18: 28.12 | G18: 16.01 | Z18: =IF($T$3>D17,"good","not good") -> good | AA18: =IF($U$3>E17,"good","not good") -> not good | AB18: =IF($V$3>F17,"good","not good") -> not good | AC18: =IF($V$3>G17,"good","not good") -> not good | AD18: =IF(Z18="good",A17,"") -> NIFTY MIDCAP 100 | AE18: =IF($T$4>D17,"good") -> good | AF18: =IF($U$4>E17,"good") -> FALSE | AG18: =IF($V$4>F17,"good") -> FALSE | AH18: =IF($W$4>G17,"good") -> FALSE | AJ18: =IF($T$5>D17,"good") -> good | AK18: =IF($U$5>E17,"good") -> FALSE | AL18: =IF($V$5>F17,"good") -> FALSE | AM18: =IF($W$5>G17,"good") -> FALSE | AO18: =IF($T$6>D17,"good") -> good | AP18: =IF($U$6>E17,"good") -> FALSE | AQ18: =IF($V$6>F17,"good") -> FALSE | AR18: =IF($W$6>G17,"good") -> FALSE
A19: NIFTY MICROCAP250 | B19: -9.4 | C19: -22.89 | D19: 3.04 | E19: 28.3 | F19: 41.9 | G19: 19.54 | Z19: =IF($T$3>D18,"good","not good") -> good | AA19: =IF($U$3>E18,"good","not good") -> not good | AB19: =IF($V$3>F18,"good","not good") -> not good | AC19: =IF($V$3>G18,"good","not good") -> not good | AD19: =IF(Z19="good",A18,"") -> Nifty Midcap 50 | AE19: =IF($T$4>D18,"good") -> good | AF19: =IF($U$4>E18,"good") -> FALSE | AG19: =IF($V$4>F18,"good") -> FALSE | AH19: =IF($W$4>G18,"good") -> FALSE | AJ19: =IF($T$5>D18,"good") -> good | AK19: =IF($U$5>E18,"good") -> FALSE | AL19: =IF($V$5>F18,"good") -> FALSE | AM19: =IF($W$5>G18,"good") -> FALSE | AO19: =IF($T$6>D18,"good") -> good | AP19: =IF($U$6>E18,"good") -> FALSE | AQ19: =IF($V$6>F18,"good") -> FALSE | AR19: =IF($W$6>G18,"good") -> FALSE
AO23: =IF($T$6>#REF!,"good") -> #REF!
AO24: =IF($T$6>D23,"good") -> FALSE

Sheet kotak
A1: Period Invested for | B1: ₹10000 Invested on | C1: Latest Value | D1: absolute returns | E1: Annualised Returns | F1: Category Avg | G1: Rank within Category | J1: here kh is in 500 or not | P1: here kh is in 500 or not
A2: 1 Week | B2: 45719 | C2: 10182.7 | D2: 0.0183 | E2: - | F2: 0.0151 | G2: 11293 | J2: =IF('kotak holdings'!A2='nifty 500 co list'!J2:J501,TRUE,FALSE) -> FALSE | P2: =IF('kotak holdings'!G2='nifty 500 co list'!P2:P501,TRUE,FALSE) -> FALSE
A3: 1 Month | B3: 45698 | C3: 9226.4 | D3: -0.0774 | E3: - | F3: -0.0663 | G3: 28/30 | J3: =IF('kotak holdings'!A3='nifty 500 co list'!J3:J502,TRUE,FALSE) -> FALSE | P3: =IF('kotak holdings'!G3='nifty 500 co list'!P3:P502,TRUE,FALSE) -> FALSE
A4: 3 Month | B4: 45636 | C4: 8135.8 | D4: -0.1864 | E4: - | F4: -0.1761 | G4: 25/30 | J4: =IF('kotak holdings'!A4='nifty 500 co list'!J4:J503,TRUE,FALSE) -> FALSE | P4: =IF('kotak holdings'!G4='nifty 500 co list'!P4:P503,TRUE,FALSE) -> FALSE
A5: 6 Month | B5: 45545 | C5: 8348.8 | D5: -0.1651 | E5: - | F5: -0.1711 | G5: 14/30 | J5: =IF('kotak holdings'!A5='nifty 500 co list'!J5:J504,TRUE,FALSE) -> FALSE | P5: =IF('kotak holdings'!G5='nifty 500 co list'!P5:P504,TRUE,FALSE) -> FALSE
A6: YTD | B6: 45658 | C6: 8287.6 | D6: -0.1712 | E6: - | F6: -0.1532 | G6: 26/30 | J6: =IF('kotak holdings'!A6='nifty 500 co list'!J6:J505,TRUE,FALSE) -> FALSE | P6: =IF('kotak holdings'!G6='nifty 500 co list'!P6:P505,TRUE,FALSE) -> FALSE
A7: 1 Year | B7: 45358 | C7: 10829.9 | D7: 0.083 | E7: 0.0823 | F7: 0.0369 | G7: 11079 | J7: =IF('kotak holdings'!A7='nifty 500 co list'!J7:J506,TRUE,FALSE) -> FALSE | P7: =IF('kotak holdings'!G7='nifty 500 co list'!P7:P506,TRUE,FALSE) -> FALSE
A8: 2 Year | B8: 44995 | C8: 14729.6 | D8: 0.473 | E8: 0.2133 | F8: 0.2362 | G8: 22/30 | J8: =IF('kotak holdings'!A8='nifty 500 co list'!J8:J507,TRUE,FALSE) -> FALSE | P8: =IF('kotak holdings'!G8='nifty 500 co list'!P8:P507,TRUE,FALSE) -> FALSE
A9: 3 Year | B9: 44630 | C9: 16441.2 | D9: 0.6441 | E9: 0.1801 | F9: 0.1805 | G9: 46357 | J9: =IF('kotak holdings'!A9='nifty 500 co list'!J9:J508,TRUE,FALSE) -> FALSE | P9: =IF('kotak holdings'!G9='nifty 500 co list'!P9:P508,TRUE,FALSE) -> FALSE
A10: 5 Year | B10: 43899 | C10: 28750.5 | D10: 1.875 | E10: 0.2349 | F10: 0.2312 | G10: 45597 | P10: =IF('kotak holdings'!G10='nifty 500 co list'!P10:P509,TRUE,FALSE) -> FALSE
A11: 10 Year | B11: 42073 | C11: 42845.5 | D11: 3.2846 | E11: 0.1565 | F11: 0.1415 | G11: 44317 | P11: =IF('kotak holdings'!G11='nifty 500 co list'!P11:P510,TRUE,FALSE) -> FALSE
A12: Since Inception | B12: 39171 | C12: 111664 | D12: 10.1664 | E12: 0.1438 | F12: 0.1754 | G12: 25/30 | P12: =IF('kotak holdings'!G12='nifty 500 co list'!P12:P511,TRUE,FALSE) -> FALSE
P13: =IF('kotak holdings'!G13='nifty 500 co list'!P13:P512,TRUE,FALSE) -> FALSE
P14: =IF('kotak holdings'!G14='nifty 500 co list'!P14:P513,TRUE,FALSE) -> FALSE
P15: =IF('kotak holdings'!G15='nifty 500 co list'!P15:P514,TRUE,FALSE) -> FALSE
B16: Period Invested for | C16: 1 Week | D16: 1 Month | E16: 3 Month | F16: 6 Month | G16: YTD | H16: 1 Year | I16: 2 Year | J16: 3 Year | K16: 5 Year | L16: 10 Year | M16: Since Inception | P16: =IF('kotak holdings'!G16='nifty 500 co list'!P16:P515,TRUE,FALSE) -> FALSE
B17: absolute returns | C17: 0.0183 | D17: -0.0774 | E17: -0.1864 | F17: -0.1651 | G17: -0.1712 | H17: 0.083 | I17: 0.473 | J17: 0.6441 | K17: 1.875 | L17: 3.2846 | M17: 10.1664 | P17: =IF('kotak holdings'!G17='nifty 500 co list'!P17:P516,TRUE,FALSE) -> FALSE
P18: =IF('kotak holdings'!G18='nifty 500 co list'!P18:P517,TRUE,FALSE) -> FALSE
P19: =IF('kotak holdings'!G19='nifty 500 co list'!P19:P518,TRUE,FALSE) -> FALSE
P20: =IF('kotak holdings'!G20='nifty 500 co list'!P20:P519,TRUE,FALSE) -> FALSE
P21: =IF('kotak holdings'!G21='nifty 500 co list'!P21:P520,TRUE,FALSE) -> FALSE
P22: =IF('kotak holdings'!G22='nifty 500 co list'!P22:P521,TRUE,FALSE) -> FALSE
P23: =IF('kotak holdings'!G23='nifty 500 co list'!P23:P522,TRUE,FALSE) -> FALSE
P24: =IF('kotak holdings'!G24='nifty 500 co list'!P24:P523,TRUE,FALSE) -> FALSE
P25: =IF('kotak holdings'!G25='nifty 500 co list'!P25:P524,TRUE,FALSE) -> FALSE
P26: =IF('kotak holdings'!G26='nifty 500 co list'!P26:P525,TRUE,FALSE) -> FALSE
B27: Period Invested for | C27: 1 Year | D27: 3 Year | E27: 5 Year | P27: =IF('kotak holdings'!G27='nifty 500 co list'!P27:P526,TRUE,FALSE) -> FALSE
B28: kotak returns | C28: 0.0823 | D28: 0.1801 | E28: 0.2349 | P28: =IF('kotak holdings'!G28='nifty 500 co list'!P28:P527,TRUE,FALSE) -> FALSE
B29: Nifty 500 | C29: 7.32% | D29: 0.4312 | E29: 194.27% | P29: =IF('kotak holdings'!G29='nifty 500 co list'!P29:P528,TRUE,FALSE) -> FALSE
P30: =IF('kotak holdings'!G30='nifty 500 co list'!P30:P529,TRUE,FALSE) -> FALSE
P31: =IF('kotak holdings'!G31='nifty 500 co list'!P31:P530,TRUE,FALSE) -> FALSE
P32: =IF('kotak holdings'!G32='nifty 500 co list'!P32:P531,TRUE,FALSE) -> FALSE
P33: =IF('kotak holdings'!G33='nifty 500 co list'!P33:P532,TRUE,FALSE) -> FALSE
P34: =IF('kotak holdings'!G34='nifty 500 co list'!P34:P533,TRUE,FALSE) -> FALSE
P35: =IF('kotak holdings'!G35='nifty 500 co list'!P35:P534,TRUE,FALSE) -> FALSE
P36: =IF('kotak holdings'!G36='nifty 500 co list'!P36:P535,TRUE,FALSE) -> FALSE
P37: =IF('kotak holdings'!G37='nifty 500 co list'!P37:P536,TRUE,FALSE) -> FALSE
P38: =IF('kotak holdings'!G38='nifty 500 co list'!P38:P537,TRUE,FALSE) -> FALSE
P39: =IF('kotak holdings'!G39='nifty 500 co list'!P39:P538,TRUE,FALSE) -> FALSE
P40: =IF('kotak holdings'!G40='nifty 500 co list'!P40:P539,TRUE,FALSE) -> FALSE
P41: =IF('kotak holdings'!G41='nifty 500 co list'!P41:P540,TRUE,FALSE) -> FALSE
... P46: =IF('kotak holdings'!G46='nifty 500 co list'!P46:P545,TRUE,FALSE) -> FALSE
A47: 10 Year | P47: =IF('kotak holdings'!G47='nifty 500 co list'!P47:P546,TRUE,FALSE) -> FALSE
A48: 0.1565 | P48: =IF('kotak holdings'!G48='nifty 500 co list'!P48:P547,TRUE,FALSE) -> FALSE
A49: 12.24 | P49: =IF('kotak holdings'!G49='nifty 500 co list'!P49:P548,TRUE,FALSE) -> FALSE
P50: =IF('kotak holdings'!G50='nifty 500 co list'!P50:P549,TRUE,FALSE) -> FALSE
P51: =IF('kotak holdings'!G51='nifty 500 co list'!P51:P550,TRUE,FALSE) -> FALSE
P52: =IF('kotak holdings'!G52='nifty 500 co list'!P52:P551,TRUE,FALSE) -> FALSE
P53: =IF('kotak holdings'!G53='nifty 500 co list'!P53:P552,TRUE,FALSE) -> FALSE
P54: =IF('kotak holdings'!G54='nifty 500 co list'!P54:P553,TRUE,FALSE) -> FALSE
P55: =IF('kotak holdings'!G55='nifty 500 co list'!P55:P554,TRUE,FALSE) -> FALSE
P56: =IF('kotak holdings'!G56='nifty 500 co list'!P56:P555,TRUE,FALSE) -> FALSE
P57: =IF('kotak holdings'!G57='nifty 500 co list'!P57:P556,TRUE,FALSE) -> FALSE
P58: =IF('kotak holdings'!G58='nifty 500 co list'!P58:P557,TRUE,FALSE) -> FALSE
P59: =IF('kotak holdings'!G59='nifty 500 co list'!P59:P558,TRUE,FALSE) -> FALSE
P60: =IF('kotak holdings'!G60='nifty 500 co list'!P60:P559,TRUE,FALSE) -> FALSE
P61: =IF('kotak holdings'!G61='nifty 500 co list'!P61:P560,TRUE,FALSE) -> FALSE
... P515: =IF('kotak holdings'!G515='nifty 500 co list'!P515:P1014,TRUE,FALSE) -> TRUE

Sheet data valadiation
A1: Sector | C1: sectors | E1: Period Invested for
A2: Abrasives & bearings | C2: Coal | E2: =HYPERLINK("#'Kotak Holdings'!A1", " Kotak returns") -> Kotak returns
A3: Advertising & media agencies | C3: Mutual Fund | E3: =HYPERLINK("#'nippon holdings'!A1", "nippon returns") -> nippon returns
A4: Aerospace & defense | C4: Kotak returns | E4: =HYPERLINK("#'parag holdings'!A1","parag parik returns") -> parag parik returns
A5: Airline | C5: =IF(MATCH(C4,E2:E5,0)="Kotak Returns", (HYPERLINK("#'Kotak Holdings'!A1", "Go to Kotak")), IF(MATCH(C4,E2:E5,0)="Nippon Returns", (HYPERLINK("#'Nippon Holdings'!A1", "Go to Nippon")), IF(MATCH(C4,E2:E5,0)="Parag Returns",( HYPERLINK("#'Parag Holdings'!A1", "Go to Parag")), IF(MATCH(C4,E2:E5,0)="Quant Returns",( HYPERLINK("#'Quant Holdings'!A1", "Go to Quant")), "nil")))) -> nil | E5: =HYPERLINK("#'quant holdings'!A1", "quant returns") -> quant returns
A6: Amusement parks/ other recreation
A7: Animal feed
A8: Asset management company
A9: Auto ancillaries
A10: Auto components & equipments
A11: Auto dealer
A12: Breweries & distilleries
A13: Business process outsourcing (bpo)/ knowledge process outsourcing (kpo)
A14: Cables - electricals
A15: Cement & cement products
A16: Civil construction
A17: Coal
... A100: Tyres & allied

Sheet nippon
A1: Period Invested for | B1: ₹10000 Invested on | C1: Latest Value | D1: Absolute Returns | E1: Annualised Returns | F1: Category Avg | G1: Rank within Category
A2: 1 Week | B2: 45719 | C2: 10379.7 | D2: 0.038 | E2: - | F2: 0.0363 | G2: 14/32
A3: 1 Month | B3: 45698 | C3: 9278.9 | D3: -0.0721 | E3: - | F3: -0.0786 | G3: 12024
A4: 3 Month | B4: 45636 | C4: 7899.6 | D4: -0.21 | E4: - | F4: -0.2055 | G4: 17/31
A5: 6 Month | B5: 45545 | C5: 7970.7 | D5: -0.2029 | E5: - | F5: -0.194 | G5: 20/30
A6: YTD | B6: 45658 | C6: 8183.3 | D6: -0.1817 | E6: - | F6: -0.177 | G6: 11658
A7: 1 Year | B7: 45358 | C7: 10108 | D7: 0.0108 | E7: 0.0107 | F7: 0.017 | G7: 14/29
A8: 2 Year | B8: 44995 | C8: 15506 | D8: 0.5506 | E8: 0.2449 | F8: 0.2217 | G8: 46204
A9: 3 Year | B9: 44630 | C9: 17864.1 | D9: 0.7864 | E9: 0.2132 | F9: 0.1695 | G9: 45717
A10: 5 Year | B10: 43899 | C10: 39546.3 | D10: 2.9546 | E10: 0.3161 | F10: 0.268 | G10: 44986
A11: 10 Year | B11: 42073 | C11: 58163.2 | D11: 4.8163 | E11: 0.1923 | F11: 0.1499 | G11: 42005
A12: Since Inception | B12: 40437 | C12: 143909.7 | D12: 13.391 | E12: 0.202 | F12: 0.1585 | G12: 11232

Sheet parag parik
A1: Period Invested for | B1: ₹10000 Invested on | C1: Latest Value | D1: Absolute Returns | E1: Annualised Returns | F1: Category Avg | G1: Rank within Category
A2: 1 Week | B2: 45719 | C2: 10110.9 | D2: 0.0111 | E2: - | F2: 0.0152 | G2: 37/39
A3: 1 Month | B3: 45698 | C3: 9644.1 | D3: -0.0356 | E3: - | F3: -0.0595 | G3: 14305
A4: 3 Month | B4: 45636 | C4: 9404.7 | D4: -0.0595 | E4: - | F4: -0.147 | G4: 14246
A5: 6 Month | B5: 45545 | C5: 9752.8 | D5: -0.0247 | E5: - | F5: -0.1458 | G5: 14246
A6: YTD | B6: 45658 | C6: 9518.7 | D6: -0.0481 | E6: - | F6: -0.1181 | G6: 14246
A7: 1 Year | B7: 45358 | C7: 11028.3 | D7: 0.1028 | E7: 0.1028 | F7: 0.0101 | G7: 13912
A8: 2 Year | B8: 44995 | C8: 15723.5 | D8: 0.5723 | E8: 0.2547 | F8: 0.1857 | G8: 12479
A9: 3 Year | B9: 44630 | C9: 16471.9 | D9: 0.6472 | E9: 0.1814 | F9: 0.1335 | G9: 47209
A10: 5 Year | B10: 43899 | C10: 30870.6 | D10: 2.0871 | E10: 0.253 | F10: 0.1821 | G10: 44986
A11: 10 Year | B11: 42073 | C11: 46719.5 | D11: 3.6719 | E11: 0.1667 | F11: 0.1193 | G11: 43497
A12: Since Inception | B12: 41418 | C12: 77095.1 | D12: 6.7095 | E12: 0.1891 | F12: 0.1387 | G12: 14336

Sheet quant
B1: Period Invested for | C1: ₹10000 Invested on | D1: Latest Value | E1: Absolute Returns | F1: Annualised Returns | G1: Category Avg | H1: Rank within Category | K1: initial investment | L1: final value | M1: absolute return | N1: CAGR
A2: 7 | B2: 1 Week | C2: 45719 | D2: 10316.6 | E2: 0.0317 | F2: - | G2: 0.0151 | H2: 10959 | K2: 10000 | L2: =(1+E2/100)*10000 -> 10003.17 | M2: =((L2-10000)/10000)*100 -> 0.0317 | N2: =((L2/10000)^(1/A2)-1)*100 -> 0.0045279563
A3: 30 | B3: 1 Month | C3: 45698 | D3: 9413.4 | E3: -0.0587 | F3: - | G3: -0.0663 | H3: 11049 | K3: 10000 | L3: =(1+E3/100)*10000 -> 9994.13 | M3: =((L3-10000)/10000)*100 -> -0.0587 | N3: =((L3/10000)^(1/A3)-1)*100 -> -0.001957222
A4: 90 | B4: 3 Month | C4: 45636 | D4: 8479 | E4: -0.1521 | F4: - | G4: -0.1761 | H4: 11018 | K4: 10000 | L4: =(1+E4/100)*10000 -> 9984.79 | M4: =((L4-10000)/10000)*100 -> -0.1521 | N4: =((L4/10000)^(1/A4)-1)*100 -> -0.0016912722
A5: 180 | B5: 6 Month | C5: 45545 | D5: 7914 | E5: -0.2086 | F5: - | G5: -0.1711 | H5: 29/30 | K5: 10000 | L5: =(1+E5/100)*10000 -> 9979.14 | M5: =((L5-10000)/10000)*100 -> -0.2086 | N5: =((L5/10000)^(1/A5)-1)*100 -> -0.0011600926
B6: YTD | C6: 45658 | D6: 8657 | E6: -0.1343 | F6: - | G6: -0.1532 | H6: 11018 | K6: 10000 | L6: =(1+E6/100)*10000 -> 9986.57 | M6: =((L6-10000)/10000)*100 -> -0.1343 | N6: =((L6/10000)^(1/A6)-1)*100 -> #DIV/0!
A7: 365 | B7: 1 Year | C7: 45358 | D7: 9011.5 | E7: -0.0988 | F7: -0.0981 | G7: 0.0369 | H7: 30/30 | K7: 10000 | L7: =(1+E7/100)*10000 -> 9990.12 | M7: =((L7-10000)/10000)*100 -> -0.0988 | N7: =((L7/10000)^(1/A7)-1)*100 -> -0.00027081837
A8: 730 | B8: 2 Year | C8: 44995 | D8: 14756.6 | E8: 0.4757 | F8: 0.2144 | G8: 0.2362 | H8: 20/30 | K8: 10000 | L8: =(1+E8/100)*10000 -> 10047.57 | M8: =((L8-10000)/10000)*100 -> 0.4757 | N8: =((L8/10000)^(1/A8)-1)*100 -> 0.00065010091
A9: 1095 | B9: 3 Year | C9: 44630 | D9: 16833.5 | E9: 0.6834 | F9: 0.1894 | G9: 0.1805 | H9: 46327 | K9: 10000 | L9: =(1+E9/100)*10000 -> 10068.34 | M9: =((L9-10000)/10000)*100 -> 0.6834 | N9: =((L9/10000)^(1/A9)-1)*100 -> 0.00062198861
A10: 1825 | B10: 5 Year | C10: 43899 | D10: 36856.4 | E10: 2.6856 | F10: 0.2977 | G10: 0.2312 | H10: 45292 | K10: 10000 | L10: =(1+E10/100)*10000 -> 10268.56 | M10: =((L10-10000)/10000)*100 -> 2.6856 | N10: =((L10/10000)^(1/A10)-1)*100 -> 0.0014521589
A11: 3650 | B11: 10 Year | C11: 42073 | D11: 43161.6 | E11: 3.3162 | F11: 0.1573 | G11: 0.1415 | H11: 44287 | K11: 10000 | L11: =(1+E11/100)*10000 -> 10331.62 | M11: =((L11-10000)/10000)*100 -> 3.3162 | N11: =((L11/10000)^(1/A11)-1)*100 -> 0.00089381229
B12: Since Inception | C12: 36971 | D12: 192516.1 | E12: 18.2516 | F12: 0.1312 | G12: 0.1754 | H12: 27/30 | K12: 10000 | L12: =(1+E12/100)*10000 -> 11825.16 | M12: =((L12-10000)/10000)*100 -> 18.2516 | N12: =Q13=((L12/10000)^(1/A12)-1)*100 -> #DIV/0!

Sheet kotak holdings
A1: Stock Invested in | B1: Sector | C1: Value(Mn) | D1: % of Total Holdings | E1: 1M Change | F1: 1Y Highest Holding | G1: 1Y Lowest Holding | H1: Quantity | I1: 1M Change in Qty | J1: Column1
A2: Bharat Electronics Ltd. | B2: Aerospace & defense | C2: 9536.8 | D2: 0.0194 | E2: 0.0014 | F2: 3.62% (May 2024) | G2: 1.77% (Sep 2024) | H2: 3.26 Cr | I2: 0
A3: Schaeffler India Ltd. | B3: Auto components & equipments | C3: 9929.6 | D3: 0.0202 | E3: 0.0016 | F3: 3.54% (Jun 2024) | G3: 1.86% (Dec 2024) | H3: 28.98 L | I3: 0
A4: Exide Industries Ltd. | B4: Auto components & equipments | C4: 8396 | D4: 0.0171 | E4: -0.0005 | F4: 2.58% (Jun 2024) | G4: 1.71% (Jan 2025) | H4: 2.24 Cr | I4: 0
A5: Minda Industries Ltd. | B5: Auto components & equipments | C5: 5961.4 | D5: 0.0121 | E5: -0.0004 | F5: 1.27% (Nov 2024) | G5: 0.56% (Feb 2024) | H5: 63.04 L | I5: 0
A6: WABCO India Ltd. | B6: Auto components & equipments | C6: 3964.8 | D6: 0.0081 | E6: -0.0001 | F6: 1.02% (Oct 2024) | G6: 0.4% (Apr 2024) | H6: 3.59 L | I6: 0
A7: Sundram Fasteners Ltd. | B7: Auto components & equipments | C7: 2881.7 | D7: 0.0059 | E7: 0.0004 | F7: 0.76% (Jun 2024) | G7: 0.55% (Dec 2024) | H7: 27.60 L | I7: 0
A8: Motherson Sumi Systems Ltd. | B8: Auto components & equipments | C8: 1680.6 | D8: 0.0034 | E8: -0.0058 | F8: 2.42% (Jul 2024) | G8: 0.34% (Jan 2025) | H8: 1.19 Cr | I8: -1.94 Cr
A9: KEI Industries Ltd. | B9: Cables - electricals | C9: 6662.7 | D9: 0.0136 | E9: 0.0035 | F9: 1.36% (Jan 2025) | G9: 0% (Feb 2024) | H9: 16.56 L | I9: 4.45 L
A10: Polycab India Limited | B10: Cables - electricals | C10: 5956.3 | D10: 0.0121 | E10: -0.0014 | F10: 1.38% (Nov 2024) | G10: 0% (Feb 2024) | H10: 9.86 L | I10: 0
A11: Bharat Forge Ltd. | B11: Castings & forgings | C11: 7119.4 | D11: 0.0145 | E11: 0.0003 | F11: 2.81% (May 2024) | G11: 1.42% (Dec 2024) | H11: 58.16 L | I11: 0
A12: J.K. Cement Ltd. | B12: Cement & cement products | C12: 12322.6 | D12: 0.0251 | E12: 0.0029 | F12: 2.63% (Feb 2024) | G12: 1.99% (May 2024) | H12: 25.49 L | I12: -0.14 L
A13: The Ramco Cements Ltd. | B13: Cement & cement products | C13: 6344.4 | D13: 0.0129 | E13: 0.0003 | F13: 1.35% (Nov 2024) | G13: 0.93% (May 2024) | H13: 69.15 L | I13: 0
A14: Kajaria Ceramics Ltd. | B14: Ceramics | C14: 6397.7 | D14: 0.013 | E14: -0.0011 | F14: 1.89% (Jul 2024) | G14: 1.3% (Jan 2025) | H14: 64.53 L | I14: 0
A15: Techno Electric & Engineering Co. Ltd. | B15: Civil construction | C15: 2350.5 | D15: 0.0048 | E15: -0.0017 | F15: 0.65% (Dec 2024) | G15: 0% (Feb 2024) | H15: 21.81 L | I15: 0
A16: Mphasis Ltd. | B16: Computers - software & consulting | C16: 16719.2 | D16: 0.0341 | E16: 0.0028 | F16: 3.52% (Aug 2024) | G16: 1.04% (May 2024) | H16: 58.30 L | I16: 2.14 k
A17: Persistent Systems Ltd. | B17: Computers - software & consulting | C17: 12939.9 | D17: 0.0264 | E17: -0.0029 | F17: 4.16% (Oct 2024) | G17: 2.64% (Jan 2025) | H17: 21.45 L | I17: -2.62 L
A18: Wipro Ltd. | B18: Computers - software & consulting | C18: 11456.1 | D18: 0.0233 | E18: 0.0035 | F18: 2.33% (Jan 2025) | G18: 0% (Feb 2024) | H18: 3.67 Cr | I18: 18.50 L
A19: Birlasoft Ltd. | B19: Computers - software & consulting | C19: 9590.7 | D19: 0.0195 | E19: 0.0013 | F19: 1.95% (Jan 2025) | G19: 0% (Feb 2024) | H19: 1.79 Cr | I19: 6.92 L
A20: Tech Mahindra Ltd. | B20: Computers - software & consulting | C20: 3634.5 | D20: 0.0074 | E20: 0.0004 | F20: 0.88% (Oct 2024) | G20: 0.57% (May 2024) | H20: 21.71 L | I20: 0
A21: Dixon Technologies (India) Ltd. | B21: Consumer electronics | C21: 11293.7 | D21: 0.0239 | E21: -0.0025 | F21: 2.55% (Dec 2024) | G21: 1.58% (Feb 2024) | H21: 7.54 L | I21: 0
A22: Vishal Mega Mart Ltd. | B22: Diversified retail | C22: 907.7 | D22: 0.0018 | E22: 0.0001 | F22: 0.18% (Jan 2025) | G22: 0% (Feb 2024) | H22: 84.08 L | I22: 0
A23: Zomato Ltd. | B23: E-retail/ e-commerce | C23: 3140.1 | D23: 0.0064 | E23: -0.0011 | F23: 0.77% (Nov 2024) | G23: 0% (Feb 2024) | H23: 1.43 Cr | I23: 0
A24: Solar Industries India Ltd. | B24: Explosives | C24: 11273 | D24: 0.023 | E24: 0.0026 | F24: 4.56% (Mar 2024) | G24: 2.04% (Dec 2024) | H24: 11.06 L | I24: 0
A25: Coromandel International Ltd. | B25: Fertilizers | C25: 13690.3 | D25: 0.0279 | E25: 0.0011 | F25: 2.79% (Jan 2025) | G25: 2.05% (Feb 2024) | H25: 75.66 L | I25: 0
A26: Power Finance Corporation Ltd. | B26: Financial institution | C26: 10013.8 | D26: 0.0204 | E26: 0.0004 | F26: 2.71% (May 2024) | G26: 2% (Oct 2024) | H26: 2.37 Cr | I26: 0
A27: Rural Electrification Corporation Limited | B27: Financial institution | C27: 3230.6 | D27: 0.0066 | E27: -0.0002 | F27: 0.77% (Apr 2024) | G27: 0% (Feb 2024) | H27: 71.81 L | I27: 0
A28: Prudent Corporate Advisory Services Ltd. | B28: Financial products distributor | C28: 3811.5 | D28: 0.0078 | E28: -0.0019 | F28: 1.15% (Oct 2024) | G28: 0% (Feb 2024) | H28: 18.76 L | I28: 0
A29: Metro Brands Ltd. | B29: Footwear | C29: 7556.7 | D29: 0.0154 | E29: 0.0008 | F29: 1.54% (Jan 2025) | G29: 0.47% (Apr 2024) | H29: 63.78 L | I29: 0
A30: Page Industries Ltd. | B30: Garments & apparels | C30: 285.2 | D30: 0.0006 | E30: -0.0052 | F30: 0.58% (Dec 2024) | G30: 0.06% (Jan 2025) | H30: 6.38 k | I30: -0.58 L
A31: ICICI Lombard General Insurance Co Ltd. | B31: General insurance | C31: 7921.1 | D31: 0.0161 | E31: 0.0017 | F31: 1.66% (Aug 2024) | G31: 0% (Feb 2024) | H31: 42.62 L | I31: 0
A32: GE T&D India Ltd. | B32: Heavy electrical equipment | C32: 10400.4 | D32: 0.0212 | E32: 0.004 | F32: 2.12% (Jan 2025) | G32: 0% (Feb 2024) | H32: 58.18 L | I32: 14.23 L
A33: Thermax Ltd. | B33: Heavy electrical equipment | C33: 6486 | D33: 0.0132 | E33: 0.0004 | F33: 2.86% (Apr 2024) | G33: 1.28% (Dec 2024) | H33: 16.79 L | I33: 0
A34: Fortis Healthcare Ltd. | B34: Hospital | C34: 15828.5 | D34: 0.0322 | E34: -0.0013 | F34: 3.35% (Dec 2024) | G34: 0% (Feb 2024) | H34: 2.47 Cr | I34: 0
A35: Global Health Ltd. | B35: Hospital | C35: 7800.4 | D35: 0.0159 | E35: 0.0007 | F35: 1.59% (Jan 2025) | G35: 0% (Feb 2024) | H35: 75.03 L | I35: 0
A36: Max Healthcare Institute Ltd. | B36: Hospital | C36: 1157.6 | D36: 0.0024 | E36: 0.0024 | F36: 0.24% (Jan 2025) | G36: 0% (Feb 2024) | H36: 10.91 L | I36: 10.91 L
A37: Blue Star Ltd. | B37: Household appliances | C37: 9411.5 | D37: 0.0192 | E37: -0.0017 | F37: 2.09% (Dec 2024) | G37: 1.7% (Mar 2024) | H37: 51.78 L | I37: 0
A38: Voltas Limited | B38: Household appliances | C38: 6023 | D38: 0.0123 | E38: -0.0038 | F38: 1.67% (Sep 2024) | G38: 1.23% (Jan 2025) | H38: 47.77 L | I38: 0
A39: Amber Enterprises India Ltd. | B39: Household appliances | C39: 5902.9 | D39: 0.012 | E39: -0.0006 | F39: 1.26% (Dec 2024) | G39: 0.78% (May 2024) | H39: 9.08 L | I39: 0
A40: V-Guard Industries Ltd. | B40: Household appliances | C40: 3971.6 | D40: 0.0081 | E40: -0.0006 | F40: 0.99% (Jul 2024) | G40: 0.81% (Jan 2025) | H40: 1.09 Cr | I40: 0
A41: LIC Housing Finance Ltd. | B41: Housing finance company | C41: 7584.8 | D41: 0.0155 | E41: 0.0012 | F41: 2.06% (Jun 2024) | G41: 1.43% (Dec 2024) | H41: 1.27 Cr | I41: 0
A42: Ratnamani Metals & Tubes Ltd. | B42: Iron & steel products | C42: 5417.4 | D42: 0.011 | E42: -0.0003 | F42: 1.45% (Feb 2024) | G42: 1.1% (Jan 2025) | H42: 18.95 L | I42: 0
A43: APL Apollo Tubes Ltd. | B43: Iron & steel products | C43: 4894.4 | D43: 0.01 | E43: -0.0029 | F43: 1.43% (Feb 2024) | G43: 1% (Jan 2025) | H43: 32.42 L | I43: -0.11 Cr
A44: Max Financial Services Ltd. | B44: Life insurance | C44: 5555.1 | D44: 0.0113 | E44: 0.0009 | F44: 1.26% (Oct 2024) | G44: 0.77% (May 2024) | H44: 49.79 L | I44: 0
A45: Mahindra & Mahindra Financial Services Ltd. | B45: Non banking financial company (nbfc) | C45: 4184.9 | D45: 0.0085 | E45: 0.0012 | F45: 1.05% (Feb 2024) | G45: 0.73% (Dec 2024) | H45: 1.47 Cr | I45: 0
A46: Oil India Ltd. | B46: Oil exploration & production | C46: 6404.5 | D46: 0.013 | E46: 0.0006 | F46: 3.03% (Jul 2024) | G46: 1.24% (Dec 2024) | H46: 1.52 Cr | I46: 0
A47: Au Small Finance Bank Ltd. | B47: Other bank | C47: 2649.6 | D47: 0.0054 | E47: 0.0008 | F47: 1.1% (Apr 2024) | G47: 0.46% (Dec 2024) | H47: 44.09 L | I47: 0
A48: Apar Industries Ltd. | B48: Other electrical equipment | C48: 6627.8 | D48: 0.0135 | E48: 0.0016 | F48: 1.35% (Jan 2025) | G48: 0% (Feb 2024) | H48: 8.85 L | I48: 2.75 L
A49: Emami Ltd. | B49: Personal care | C49: 6837.3 | D49: 0.0139 | E49: 0.0008 | F49: 1.61% (Oct 2024) | G49: 0.77% (Mar 2024) | H49: 1.16 Cr | I49: 0
A50: Pi Industries Ltd. | B50: Pesticides & agrochemicals | C50: 9862.5 | D50: 0.0201 | E50: 0.0004 | F50: 2.62% (Mar 2024) | G50: 1.97% (Dec 2024) | H50: 28.31 L | I50: 0
A51: Ipca Laboratories Ltd. | B51: Pharmaceuticals | C51: 15845.5 | D51: 0.0323 | E51: -0.0022 | F51: 3.45% (Dec 2024) | G51: 2.06% (May 2024) | H51: 1.10 Cr | I51: 1.82 L
A52: J.b. Chemicals & Pharmaceuticals Ltd. | B52: Pharmaceuticals | C52: 6891.2 | D52: 0.014 | E52: 0.0016 | F52: 1.4% (Jan 2025) | G52: 0% (Feb 2024) | H52: 39.07 L | I52: 3.23 L
A53: Torrent Pharmaceuticals Ltd. | B53: Pharmaceuticals | C53: 5166.4 | D53: 0.0105 | E53: 0.0005 | F53: 1.55% (Feb 2024) | G53: 1% (Oct 2024) | H53: 15.80 L | I53: 0
A54: Supreme Industries Ltd. | B54: Plastic products - industrial | C54: 9691.1 | D54: 0.0197 | E54: -0.0032 | F54: 4.31% (Apr 2024) | G54: 1.97% (Jan 2025) | H54: 24.42 L | I54: -1.44 L
A55: NTPC Green Energy Ltd. | B55: Power generation | C55: 4009.9 | D55: 0.0082 | E55: -0.0005 | F55: 1.12% (Nov 2024) | G55: 0% (Feb 2024) | H55: 3.49 Cr | I55: -0.13 Cr
A56: Federal Bank Ltd. | B56: Private sector bank | C56: 6580.3 | D56: 0.0134 | E56: 0.0002 | F56: 1.42% (Nov 2024) | G56: 1.27% (Jun 2024) | H56: 3.51 Cr | I56: 0
A57: Hindustan Petroleum Corporation Ltd. | B57: Refineries & marketing | C57: 8693.1 | D57: 0.0177 | E57: -0.001 | F57: 1.87% (Dec 2024) | G57: 0.55% (Jun 2024) | H57: 2.43 Cr | I57: 0
A58: Oberoi Realty Ltd. | B58: Residential, commercial projects | C58: 14521.1 | D58: 0.0296 | E58: -0.0053 | F58: 3.49% (Dec 2024) | G58: 2.71% (Feb 2024) | H58: 80.11 L | I58: 0
A59: Oracle Financial Services Software Limited | B59: Software products | C59: 13956.2 | D59: 0.0284 | E59: -0.0085 | F59: 3.69% (Dec 2024) | G59: 0% (Feb 2024) | H59: 15.30 L | I59: 0
A60: Deepak Nitrite Ltd. | B60: Specialty chemicals | C60: 9022.8 | D60: 0.0184 | E60: 0.0002 | F60: 2.01% (Nov 2024) | G60: 0% (Feb 2024) | H60: 38.80 L | I60: 0
A61: SRF Ltd. | B61: Specialty chemicals | C61: 6171.7 | D61: 0.0126 | E61: 0.0033 | F61: 1.26% (Jan 2025) | G61: 0.87% (May 2024) | H61: 21.96 L | I61: 0
A62: Atul Ltd. | B62: Specialty chemicals | C62: 1662.2 | D62: 0.0034 | E62: -0.0022 | F62: 1.95% (Feb 2024) | G62: 0.34% (Jan 2025) | H62: 2.64 L | I62: -1.65 L
A63: Edelweiss Securities Pvt. Ltd. | B63: Stockbroking & allied | C63: 4545.4 | D63: 0.0093 | E63: 0.0015 | F63: 0.93% (Jan 2025) | G63: 0% (Feb 2024) | H63: 8.12 L | I63: 2.12 L
A64: Bharti Hexacom Ltd. | B64: Telecom - equipment & accessories | C64: 9873 | D64: 0.0201 | E64: 0.0001 | F64: 2.03% (Oct 2024) | G64: 0% (Feb 2024) | H64: 72.87 L | I64: 0
A65: MRF Ltd. | B65: Tyres & rubber products | C65: 4826.4 | D65: 0.0098 | E65: -0.0006 | F65: 1.45% (Feb 2024) | G65: 0.95% (Nov 2024) | H65: 42.47 k | I65: 109
A66: Apollo Tyres Limited | B66: Tyres & rubber products | C66: 4504.9 | D66: 0.0092 | E66: -0.0005 | F66: 0.97% (Dec 2024) | G66: 0% (Feb 2024) | H66: 1.03 Cr | I66: 5.97 L
A67: Balkrishna Industries Ltd. | B67: Tyres & rubber products | C67: 3506.8 | D67: 0.0071 | E67: 0.0002 | F67: 0.86% (May 2024) | G67: 0.68% (Nov 2024) | H67: 12.65 L | I67: 0
A68: computers - software & consulting | C68: 54340.4 | D68: 0.1107 | E68: 0.0051
A69: Auto components & equipments | C69: 32814.1 | D69: 0.0668 | E69: -0.0048
A70: Pharmaceuticals | C70: 27903.1 | D70: 0.0568 | E70: -0.0001
A71: Household appliances | C71: 25309 | D71: 0.0516 | E71: -0.0067
A72: Hospital | C72: 24786.5 | D72: 0.0505 | E72: 0.0018
A73: Cement & cement products | C73: 18667 | D73: 0.038 | E73: 0.0032
A74: Heavy electrical equipment | C74: 10400.4 | D74: 0.0212 | E74: 0.004
A75: Specialty chemicals | C75: 9022.8 | D75: 0.0184 | E75: 0.0002
A76: Heavy electrical equipment | C76: 6486 | D76: 0.0132 | E76: 0.0004
A77: Specialty chemicals | C77: 7833.9 | D77: 0.016 | E77: 0.0011
A78: Residential, commercial projects | C78: 14521.1 | D78: 0.0296 | E78: -0.0053
A79: Software products | C79: 13956.2 | D79: 0.0284 | E79: -0.0085
... A110: Garments & apparels | C110: 285.2 | D110: 0.0006 | E110: -0.0052

Sheet nippon holdings
A1: Stock Invested in | B1: Sector | C1: Value(Mn) | D1: % of Total Holdings | E1: 1M Change | F1: 1Y Highest Holding | G1: 1Y Lowest Holding | H1: Quantity | I1: 1M Change in Qty
A2: Timken India Ltd. | B2: Abrasives & bearings | C2: 2930 | D2: 0.0058 | E2: 0 | F2: 0.87% (May 2024) | G2: 0.59% (Jan 2025) | H2: 11.84 L | I2: 0
A3: Grindwell Norton Ltd. | B3: Abrasives & bearings | C3: 1917.1 | D3: 0.0038 | E3: 0 | F3: 0.66% (May 2024) | G3: 0.41% (Dec 2024) | H3: 13.33 L | I3: 0
A4: Carborundum Universal Ltd. | B4: Abrasives & bearings | C4: 2715.8 | D4: 0.0053 | E4: 0 | F4: 1.01% (May 2024) | G4: 0.67% (Dec 2024) | H4: 32.66 L | I4: 0
A5: R K Swamy Ltd. | B5: Advertising & media agencies | C5: 450.9 | D5: 0.0009 | E5: 0 | F5: 0.13% (Mar 2024) | G5: 0% (Feb 2024) | H5: 21.15 L | I5: -0.41 k
A6: MTAR Technologies Ltd. | B6: Aerospace & defense | C6: 1192.8 | D6: 0.0023 | E6: 0 | F6: 0.33% (Feb 2024) | G6: 0.25% (Oct 2024) | H6: 9.26 L | I6: 0
A7: Mishra Dhatu Nigam Ltd. | B7: Aerospace & defense | C7: 364.4 | D7: 0.0007 | E7: 0 | F7: 0.13% (Feb 2024) | G7: 0.08% (Oct 2024) | H7: 14.99 L | I7: 0
A8: Hindustan Aeronautics Ltd. | B8: Aerospace & defense | C8: 2665 | D8: 0.0052 | E8: 0 | F8: 1.32% (Feb 2024) | G8: 0.46% (Aug 2024) | H8: 8.63 L | I8: 0
A9: Data Patterns India Ltd. | B9: Aerospace & defense | C9: 731.2 | D9: 0.0014 | E9: 0 | F9: 0.3% (Apr 2024) | G9: 0.19% (Sep 2024) | H9: 5.09 L | I9: 0
A10: Bharat Dynamics Ltd. | B10: Aerospace & defense | C10: 1489 | D10: 0.0029 | E10: 0 | F10: 0.46% (May 2024) | G10: 0.27% (Oct 2024) | H10: 15.26 L | I10: 0
A11: Astra Microwave Products Ltd. | B11: Aerospace & defense | C11: 1335.6 | D11: 0.0026 | E11: 0 | F11: 0.39% (May 2024) | G11: 0.27% (Dec 2024) | H11: 22.00 L | I11: 0
A12: InterGlobe Aviation Ltd. | B12: Airline | C12: 2205.3 | D12: 0.0043 | E12: 0 | F12: 1.28% (Apr 2024) | G12: 0% (Feb 2024) | H12: 4.93 L | I12: 4.71 L
A13: Wonderla Holidays Ltd. | B13: Amusement parks/ other recreation | C13: 400.1 | D13: 0.0008 | E13: 0 | F13: 0.09% (Nov 2024) | G13: 0% (Feb 2024) | H13: 6.26 L | I13: -0.11 L
A14: Godrej Agrovet Ltd. | B14: Animal feed | C14: 1602.6 | D14: 0.0032 | E14: 0 | F14: 0.32% (Jul 2024) | G14: 0.23% (May 2024) | H14: 22.41 L | I14: 0
A15: UTI Asset Management Co. Pvt. Ltd. | B15: Asset management company | C15: 1333.5 | D15: 0.0026 | E15: 0 | F15: 0.44% (Feb 2024) | G15: 0.26% (Jan 2025) | H15: 14.17 L | I15: 0
A16: Aditya Birla Sun Life AMC Ltd. | B16: Asset management company | C16: 1661.9 | D16: 0.0033 | E16: 0 | F16: 0.38% (Nov 2024) | G16: 0% (Feb 2024) | H16: 27.00 L | I16: 0
A17: Sharda Motor Industries Ltd. | B17: Auto ancillaries | C17: 651.6 | D17: 0.0013 | E17: 0 | F17: 0.18% (Aug 2024) | G17: 0% (Feb 2024) | H17: 4.15 L | I17: 0
A18: Tube Investments Of India Ltd. | B18: Auto components & equipments | C18: 6153.5 | D18: 0.0121 | E18: 0 | F18: 2.39% (Mar 2024) | G18: 1.44% (Dec 2024) | H18: 24.99 L | I18: 0
A19: Sundram Fasteners Ltd. | B19: Auto components & equipments | C19: 4391.9 | D19: 0.0086 | E19: 0 | F19: 0.86% (Jan 2025) | G19: 0% (Feb 2024) | H19: 47.03 L | I19: 0
A20: Subros Ltd. | B20: Auto components & equipments | C20: 552.6 | D20: 0.0011 | E20: 0 | F20: 0.13% (Aug 2024) | G20: 0.1% (Oct 2024) | H20: 9.68 L | I20: 0
A21: Schaeffler India Ltd. | B21: Auto components & equipments | C21: 1481.6 | D21: 0.0029 | E21: 0 | F21: 0.29% (Jan 2025) | G21: 0% (Feb 2024) | H21: 4.84 L | I21: 0
A22: Sansera Engineering Ltd. | B22: Auto components & equipments | C22: 863.8 | D22: 0.0017 | E22: 0 | F22: 0.2% (Nov 2024) | G22: 0% (Feb 2024) | H22: 7.72 L | I22: 0
A23: Sandhar Technologies Ltd. | B23: Auto components & equipments | C23: 881.3 | D23: 0.0017 | E23: 0 | F23: 0.29% (Feb 2024) | G23: 0.2% (Jan 2025) | H23: 25.62 L | I23: 0
A24: Rolex Rings Private Ltd. | B24: Auto components & equipments | C24: 279.1 | D24: 0.0005 | E24: 0 | F24: 0.09% (Jun 2024) | G24: 0.06% (Nov 2024) | H24: 1.97 L | I24: 0
A25: Motherson Sumi Systems Ltd. | B25: Auto components & equipments | C25: 2103.5 | D25: 0.0041 | E25: 0 | F25: 0.6% (Sep 2024) | G25: 0% (Feb 2024) | H25: 1.77 Cr | I25: 0
... A30: Divgi Torqtransfer Systems Private Ltd. | B30: Auto components & equipments | C30: 567.8 | D30: 0.0011 | E30: 0 | F30: 0.21% (Feb 2024) | G30: 0.11% (Dec 2024) | H30: 11.53 L | I30: 0
A31: Craftsman Automation Ltd. | B31: Auto components & equipments | C31: 1873 | D31: 0.0037 | E31: 0 | F31: 0.29% (Jan 2025) | G31: 0% (Feb 2024) | H31: 4.16 L | I31: 17.20 k
A32: CIE AUTOMOTIVE INDIA Ltd. | B32: Auto components & equipments | C32: 1867.8 | D32: 0.0037 | E32: 0 | F32: 0.72% (May 2024) | G32: 0% (Feb 2024) | H32: 49.67 L | I32: 0
A33: Automotive Axles Ltd. | B33: Auto components & equipments | C33: 1245.3 | D33: 0.0025 | E33: 0 | F33: 0.31% (Feb 2024) | G33: 0.22% (Nov 2024) | H33: 7.60 L | I33: 0
A34: Asahi India Glass Ltd. | B34: Auto components & equipments | C34: 1611.3 | D34: 0.0032 | E34: 0 | F34: 0.33% (Sep 2024) | G34: 0.27% (Aug 2024) | H34: 26.17 L | I34: 0
A35: Landmark Cars Ltd. | B35: Auto dealer | C35: 673.5 | D35: 0.0013 | E35: 0 | F35: 0.24% (Apr 2024) | G35: 0.13% (Jan 2025) | H35: 15.10 L | I35: 0
A36: Radico Khaitan Ltd. | B36: Breweries & distilleries | C36: 4620.6 | D36: 0.0091 | E36: 0 | F36: 0.94% (Dec 2024) | G36: 0.64% (Jul 2024) | H36: 22.29 L | I36: 0
A37: Allied Blenders and Distillers Ltd. | B37: Breweries & distilleries | C37: 1314.7 | D37: 0.0026 | E37: 0 | F37: 0.4% (Aug 2024) | G37: 0% (Feb 2024) | H37: 42.17 L | I37: 0
A38: eClerx Services Ltd. | B38: Business process outsourcing (bpo)/ knowledge process outsourcing (kpo) | C38: 4994.3 | D38: 0.0098 | E38: 0 | F38: 0.93% (Nov 2024) | G38: 0.65% (Jul 2024) | H38: 17.62 L | I38: 1.21 L
A39: Finolex Cables Ltd. | B39: Cables - electricals | C39: 2384 | D39: 0.0047 | E39: 0 | F39: 0.81% (May 2024) | G39: 0.51% (Jan 2025) | H39: 29.19 L | I39: 0
A40: Orient Cement Ltd. | B40: Cement & cement products | C40: 1120.6 | D40: 0.0022 | E40: 0 | F40: 0.34% (Jul 2024) | G40: 0.23% (May 2024) | H40: 34.00 L | I40: -0.19 Cr
A41: J K Lakshmi Cement Ltd. | B41: Cement & cement products | C41: 714 | D41: 0.0014 | E41: 0 | F41: 0.21% (Feb 2024) | G41: 0.13% (Nov 2024) | H41: 10.63 L | I41: 0
A42: Dalmia Bharat Ltd. | B42: Cement & cement products | C42: 462.8 | D42: 0.0009 | E42: 0.0009 | F42: 0% (Mar 2025) | G42: 0% (Mar 2025) | H42: 2.74 L | I42: 2.74 L
A43: Birla Corporation Ltd. | B43: Cement & cement products | C43: 2735.4 | D43: 0.0054 | E43: 0 | F43: 0.95% (Feb 2024) | G43: 0.54% (Oct 2024) | H43: 28.12 L | I43: 0
A44: Ambuja Cements Ltd. | B44: Cement & cement products | C44: 1255.4 | D44: 0.0025 | E44: 0 | F44: 0.36% (Feb 2024) | G44: 0.23% (Nov 2024) | H44: 27.00 L | I44: 0
A45: RITES Ltd. | B45: Civil construction | C45: 1881.9 | D45: 0.0037 | E45: 0 | F45: 0.78% (Feb 2024) | G45: 0.42% (Jan 2025) | H45: 92.00 L | I45: 0
A46: PNC Infratech Ltd. | B46: Civil construction | C46: 850 | D46: 0.0017 | E46: 0 | F46: 0.33% (May 2024) | G46: 0.16% (Nov 2024) | H46: 32.82 L | I46: 0
A47: Kalpataru Power Transmission Ltd. | B47: Civil construction | C47: 3185 | D47: 0.0063 | E47: 0 | F47: 0.83% (Apr 2024) | G47: 0.63% (Nov 2024) | H47: 36.23 L | I47: 0
A48: ISGEC Heavy Engineering Ltd. | B48: Civil construction | C48: 3892.8 | D48: 0.0077 | E48: 0 | F48: 0.79% (Jul 2024) | G48: 0.55% (Feb 2024) | H48: 41.86 L | I48: 8.33 L
A49: Ion Exchange (India) Ltd. | B49: Civil construction | C49: 3580 | D49: 0.007 | E49: 0 | F49: 0.82% (Jul 2024) | G49: 0.71% (May 2024) | H49: 71.61 L | I49: 0
A50: HG Infra Engineering Ltd. | B50: Civil construction | C50: 2136.1 | D50: 0.0042 | E50: 0 | F50: 0.89% (Jun 2024) | G50: 0.48% (Nov 2024) | H50: 22.15 L | I50: 0
A51: G R Infraprojects Ltd. | B51: Civil construction | C51: 1197.5 | D51: 0.0024 | E51: 0 | F51: 0.37% (Jun 2024) | G51: 0.27% (Jan 2025) | H51: 11.91 L | I51: 0
A52: Ceigall India Ltd. | B52: Civil construction | C52: 357.3 | D52: 0.0007 | E52: 0 | F52: 0.09% (Aug 2024) | G52: 0% (Feb 2024) | H52: 13.86 L | I52: 0
A53: Afcons Infrastructure Ltd. | B53: Civil construction | C53: 414.6 | D53: 0.0008 | E53: 0 | F53: 0.09% (Dec 2024) | G53: 0% (Feb 2024) | H53: 10.04 L | I53: 0
A54: Coal India Ltd. | B54: Coal | C54: 4049.9 | D54: 0.008 | E54: 0 | F54: 0.72% (May 2024) | G54: 0.47% (Dec 2024) | H54: 1.10 Cr | I54: 25.84 L
A55: Navin Flourine International Ltd. | B55: Commodity chemicals | C55: 1239.3 | D55: 0.0024 | E55: 0 | F55: 0.24% (Jan 2025) | G55: 0% (Feb 2024) | H55: 3.29 L | I55: 0
A56: Kirloskar Pneumatic Co. Ltd. | B56: Compressors, pumps & diesel engines | C56: 4100.1 | D56: 0.0081 | E56: 0 | F56: 1.18% (Nov 2024) | G56: 0.63% (Feb 2024) | H56: 41.02 L | I56: 0
A57: Kirloskar Oil Engines Ltd. | B57: Compressors, pumps & diesel engines | C57: 2244 | D57: 0.0044 | E57: 0 | F57: 0.96% (Jun 2024) | G57: 0.62% (Jan 2025) | H57: 38.95 L | I57: 0
A58: Kirloskar Brothers Ltd. | B58: Compressors, pumps & diesel engines | C58: 7138.6 | D58: 0.014 | E58: 0 | F58: 1.77% (Jul 2024) | G58: 0.88% (Feb 2024) | H58: 44.72 L | I58: 0
A59: Zensar Technologies Ltd. | B59: Computers - software & consulting | C59: 1843.6 | D59: 0.0036 | E59: 0 | F59: 0.38% (Jan 2025) | G59: 0.27% (Sep 2024) | H59: 24.97 L | I59: 0
A60: Sonata Software Ltd. | B60: Computers - software & consulting | C60: 985.1 | D60: 0.0019 | E60: 0 | F60: 0.3% (Jul 2024) | G60: 0.21% (Apr 2024) | H60: 27.29 L | I60: 0
A61: Rategain Travel Technologies Ltd. | B61: Computers - software & consulting | C61: 2608.2 | D61: 0.0051 | E61: 0 | F61: 0.99% (Feb 2024) | G61: 0.61% (Nov 2024) | H61: 53.23 L | I61: 0
A62: Persistent Systems Ltd. | B62: Computers - software & consulting | C62: 2917.3 | D62: 0.0057 | E62: 0 | F62: 0.58% (Jan 2025) | G62: 0.2% (Apr 2024) | H62: 5.50 L | I62: 0
A63: KPIT Technologies Ltd. | B63: Computers - software & consulting | C63: 890.2 | D63: 0.0018 | E63: 0 | F63: 1.23% (Feb 2024) | G63: 0.35% (Jan 2025) | H63: 7.43 L | I63: -6.68 L
A64: Birlasoft Ltd. | B64: Computers - software & consulting | C64: 1230.4 | D64: 0.0024 | E64: 0 | F64: 0.47% (Feb 2024) | G64: 0.26% (Oct 2024) | H64: 29.02 L | I64: 0
A65: Netweb Technologies India Ltd. | B65: Computers hardware & equipments | C65: 182.9 | D65: 0.0004 | E65: 0 | F65: 0.13% (Jun 2024) | G65: 0.04% (Jan 2025) | H65: 1.26 L | I65: -0.31 k
A66: PG Electroplast Ltd. | B66: Consumer electronics | C66: 2743.2 | D66: 0.0054 | E66: 0 | F66: 0.55% (Dec 2024) | G66: 0.12% (Mar 2024) | H66: 34.51 L | I66: 0
A67: Orient Electric Ltd. | B67: Consumer electronics | C67: 1977 | D67: 0.0039 | E67: 0 | F67: 0.48% (Jun 2024) | G67: 0.37% (Dec 2024) | H67: 99.74 L | I67: 0
A68: Dixon Technologies (India) Ltd. | B68: Consumer electronics | C68: 6551.9 | D68: 0.0129 | E68: 0 | F68: 1.48% (Dec 2024) | G68: 0.8% (Feb 2024) | H68: 4.70 L | I68: 0
A69: Central Depository Services (India) Ltd. | B69: Depositories, clearing houses and other intermediaries | C69: 4464.5 | D69: 0.0088 | E69: 0 | F69: 1.14% (Dec 2024) | G69: 0.75% (Mar 2024) | H69: 40.30 L | I69: 0
A70: 3M India Ltd. | B70: Diversified | C70: 496.9 | D70: 0.001 | E70: 0 | F70: 0.12% (Jul 2024) | G70: 0% (Feb 2024) | H70: 18.90 k | I70: 0
A71: SIS Ltd. | B71: Diversified commercial services | C71: 747.9 | D71: 0.0015 | E71: 0 | F71: 0.28% (Feb 2024) | G71: 0.14% (Jan 2025) | H71: 24.52 L | I71: 0
A72: Hindustan Unilever Ltd. | B72: Diversified fmcg | C72: 3088.3 | D72: 0.0061 | E72: 0 | F72: 0.61% (Jan 2025) | G72: 0% (Feb 2024) | H72: 14.10 L | I72: 0
A73: Vedanta Ltd. | B73: Diversified metals | C73: 4485.8 | D73: 0.0088 | E73: 0 | F73: 0.94% (Sep 2024) | G73: 0% (Feb 2024) | H73: 1.14 Cr | I73: 0
A74: Vishal Mega Mart Ltd. | B74: Diversified retail | C74: 2844.5 | D74: 0.0056 | E74: 0 | F74: 0.55% (Jan 2025) | G74: 0% (Feb 2024) | H74: 2.84 Cr | I74: -8.76 L
A75: Sudarshan Chemical Industries Ltd. | B75: Dyes and pigments | C75: 838.6 | D75: 0.0016 | E75: 0 | F75: 0.17% (Jan 2025) | G75: 0% (Feb 2024) | H75: 9.69 L | I75: 0
A76: Adani Wilmar Ltd. | B76: Edible oil | C76: 5534.3 | D76: 0.0109 | E76: 0 | F76: 1.04% (Jan 2025) | G76: 0% (Feb 2024) | H76: 2.25 Cr | I76: 1.83 L
A77: NIIT Ltd | B77: Education | C77: 1238.9 | D77: 0.0024 | E77: 0 | F77: 0.4% (Nov 2024) | G77: 0.2% (Jun 2024) | H77: 1.11 Cr | I77: 0
A78: NIIT Learning Systems Ltd. | B78: Education | C78: 5125.2 | D78: 0.0101 | E78: 0 | F78: 1.29% (Feb 2024) | G78: 0.87% (Oct 2024) | H78: 1.22 Cr | I78: 0
A79: Vesuvius India Ltd. | B79: Electrodes & refractories | C79: 1148.5 | D79: 0.0023 | E79: 0 | F79: 0.31% (May 2024) | G79: 0.2% (Feb 2024) | H79: 2.88 L | I79: 0
A80: Orient Refractories Ltd. | B80: Electrodes & refractories | C80: 777.2 | D80: 0.0015 | E80: 0 | F80: 0.27% (May 2024) | G80: 0.16% (Dec 2024) | H80: 19.84 L | I80: 0
A81: FSN E-Commerce Ventures Ltd. | B81: E-retail/ e-commerce | C81: 1110.7 | D81: 0.0022 | E81: 0 | F81: 0.18% (Jan 2025) | G81: 0% (Feb 2024) | H81: 69.94 L | I81: 10.00 L
A82: Multi Commodity Exchange Of India Ltd. | B82: Exchange and data platform | C82: 9239.6 | D82: 0.0182 | E82: 0 | F82: 1.98% (Oct 2024) | G82: 1.29% (Jun 2024) | H82: 18.51 L | I82: 0
A83: Paradeep Phosphates Ltd. | B83: Fertilizers | C83: 2784 | D83: 0.0055 | E83: 0 | F83: 0.58% (Jan 2025) | G83: 0.39% (Sep 2024) | H83: 3.20 Cr | I83: 27.40 L
A84: Chambal Fertilizers & Chemicals Ltd. | B84: Fertilizers | C84: 2165.7 | D84: 0.0043 | E84: 0 | F84: 0.36% (Jan 2025) | G84: 0.3% (Mar 2024) | H84: 40.58 L | I84: 0
A85: PVR Inox Ltd. | B85: Film production, distribution & exhibition | C85: 1776 | D85: 0.0035 | E85: 0 | F85: 0.59% (Feb 2024) | G85: 0.38% (Jan 2025) | H85: 19.65 L | I85: 0
A86: Capital Small Finance Bank Ltd. | B86: Financial services | C86: 400.2 | D86: 0.0008 | E86: 0 | F86: 0.14% (Mar 2024) | G86: 0.07% (Nov 2024) | H86: 14.95 L | I86: 0
A87: Protean eGov Technologies Ltd. | B87: Financial technology (fintech) | C87: 1918.2 | D87: 0.0038 | E87: 0 | F87: 0.52% (Aug 2024) | G87: 0% (Feb 2024) | H87: 14.54 L | I87: 0
A88: KFIN Technologies Ltd. | B88: Financial technology (fintech) | C88: 3341.2 | D88: 0.0066 | E88: 0 | F88: 0.92% (Dec 2024) | G88: 0.45% (Mar 2024) | H88: 38.38 L | I88: 1.25 L
A89: Campus Activewear Ltd. | B89: Footwear | C89: 227.7 | D89: 0.0004 | E89: 0.0004 | F89: 0% (Mar 2025) | G89: 0% (Mar 2025) | H89: 8.74 L | I89: 8.74 L
A90: Stanley Lifestyles Ltd. | B90: Furniture, home furnishing | C90: 695.5 | D90: 0.0014 | E90: 0 | F90: 0.25% (Jul 2024) | G90: 0% (Feb 2024) | H90: 25.27 L | I90: 0
A91: Sheela Foam Ltd. | B91: Furniture, home furnishing | C91: 782.3 | D91: 0.0015 | E91: 0 | F91: 0.26% (Feb 2024) | G91: 0.15% (Nov 2024) | H91: 10.98 L | I91: -1.52 k
A92: Raymond Ltd. | B92: Garments & apparels | C92: 1601.6 | D92: 0.0032 | E92: 0 | F92: 0.64% (Jun 2024) | G92: 0.33% (Nov 2024) | H92: 12.38 L | I92: 0
A93: Raymond Lifestyle Ltd. | B93: Garments & apparels | C93: 1076.5 | D93: 0.0021 | E93: 0 | F93: 0.38% (Sep 2024) | G93: 0% (Feb 2024) | H93: 9.91 L | I93: 0
A94: Gokaldas Exports Ltd. | B94: Garments & apparels | C94: 4388.4 | D94: 0.0086 | E94: 0 | F94: 0.99% (Dec 2024) | G94: 0.63% (Mar 2024) | H94: 53.94 L | I94: 0
A95: P N Gadgil Jewellers Ltd. | B95: Gems, jewellery and watches | C95: 236.7 | D95: 0.0005 | E95: 0 | F95: 0.05% (Nov 2024) | G95: 0% (Feb 2024) | H95: 4.40 L | I95: 0
A96: Pokarna Ltd. | B96: Granites & marbles | C96: 815.7 | D96: 0.0016 | E96: 0 | F96: 0.17% (Jan 2025) | G96: 0.07% (Apr 2024) | H96: 7.39 L | I96: 0
A97: Thyrocare Technologies Ltd. | B97: Healthcare service provider | C97: 1355 | D97: 0.0027 | E97: 0 | F97: 0.32% (Nov 2024) | G97: 0.2% (Jun 2024) | H97: 19.71 L | I97: 0
A98: Metropolis Healthcare Ltd. | B98: Healthcare service provider | C98: 1814.8 | D98: 0.0036 | E98: 0 | F98: 0.42% (May 2024) | G98: 0.36% (Jan 2025) | H98: 11.45 L | I98: 0
A99: DR. LAL PATHLABS Ltd. | B99: Healthcare service provider | C99: 1491.4 | D99: 0.0029 | E99: 0 | F99: 0.32% (Jan 2025) | G99: 0% (Feb 2024) | H99: 6.45 L | I99: 0
A100: Voltamp Transformers Ltd. | B100: Heavy electrical equipment | C100: 4033.5 | D100: 0.0079 | E100: 0 | F100: 1.84% (May 2024) | G100: 0.94% (Jan 2025) | H100: 6.42 L | I100: 0
A101: TD Power Systems Ltd. | B101: Heavy electrical equipment | C101: 3869.7 | D101: 0.0076 | E101: 0 | F101: 0.91% (Dec 2024) | G101: 0.73% (Feb 2024) | H101: 1.25 Cr | I101: -0.29 L
A102: KEC International Ltd. | B102: Heavy electrical equipment | C102: 1188.2 | D102: 0.0023 | E102: 0 | F102: 0.33% (Dec 2024) | G102: 0.25% (May 2024) | H102: 17.31 L | I102: 0
A103: Inox Wind Ltd. | B103: Heavy electrical equipment | C103: 3721 | D103: 0.0073 | E103: 0 | F103: 1.16% (Feb 2024) | G103: 0.62% (Jun 2024) | H103: 2.48 Cr | I103: 0
A104: Bharat Heavy Electricals Ltd. | B104: Heavy electrical equipment | C104: 4927.2 | D104: 0.0097 | E104: 0 | F104: 1.45% (May 2024) | G104: 1% (Jan 2025) | H104: 2.75 Cr | I104: 0
...

Sheet parag holdings
B1: Sector | C1: Value(Mn) | D1: % of Total Holdings | E1: 1M Change | F1: 1Y Highest Holding | G1: 1Y Lowest Holding | H1: Quantity | I1: 1M Change in Qty
A2: HDFC Bank Ltd. | B2: Private sector bank | C2: 74169.4 | D2: 0.0843 | E2: 0 | F2: 8.57% (Jun 2024) | G2: 7.93% (Feb 2024) | H2: 4.28 Cr | I2: 0
A3: ICICI Bank Ltd. | B3: Private sector bank | C3: 42127.5 | D3: 0.0479 | E3: 0 | F3: 5.32% (Oct 2024) | G3: 4.89% (Jan 2025) | H3: 3.50 Cr | I3: 0
A4: Kotak Mahindra Bank Ltd. | B4: Private sector bank | C4: 37589.4 | D4: 0.0427 | E4: 0 | F4: 4.19% (Jan 2025) | G4: 2.23% (Feb 2024) | H4: 1.98 Cr | I4: 0
A5: Axis Bank Ltd. | B5: Private sector bank | C5: 27681.1 | D5: 0.0315 | E5: 0 | F5: 4.32% (Feb 2024) | G5: 3% (Jan 2025) | H5: 2.73 Cr | I5: 0
A6: Facebook | B6: Foreign equity | C6: 34556.4 | D6: 0.0393 | E6: 0 | F6: 4.08% (Feb 2024) | G6: 3.09% (Jul 2024) | H6: 5.91 L | I6: 0
A7: Alphabet Inc | B7: Foreign equity | C7: 28039.1 | D7: 0.0319 | E7: 0 | F7: 4.06% (May 2024) | G7: 3.17% (Nov 2024) | H7: 18.82 L | I7: 0
A8: Microsoft Corp | B8: Foreign equity | C8: 25461.8 | D8: 0.0289 | E8: 0 | F8: 4.27% (Feb 2024) | G8: 2.94% (Jan 2025) | H8: 7.33 L | I8: 0
A9: Amazon.com | B9: Foreign equity | C9: 25460.7 | D9: 0.0289 | E9: 0 | F9: 3.39% (Mar 2024) | G9: 2.59% (Sep 2024) | H9: 13.71 L | I9: 0
A10: Maruti Suzuki India Ltd. | B10: Passenger cars & utility vehicles | C10: 36053.5 | D10: 0.041 | E10: 0 | F10: 5.75% (Mar 2024) | G10: 3.77% (Dec 2024) | H10: 30.18 L | I10: 0
A11: Bajaj Holdings & Investment Ltd. | B11: Holding company | C11: 61563 | D11: 0.07 | E11: 0 | F11: 7.23% (Feb 2024) | G11: 6.03% (May 2024) | H11: 53.19 L | I11: 0
A12: Bajaj Finserv Ltd | B12: Holding company | C12: 114.2 | D12: 0.0001 | E12: 0 | F12: 0.01% (Jan 2025) | G12: 0% (Feb 2024) | H12: 61.00 k | I12: 0
A13: HCL Technologies Limited | B13: Computers - software & consulting | C13: 29464.4 | D13: 0.0335 | E13: 0 | F13: 5.28% (Feb 2024) | G13: 3.6% (Jan 2025) | H13: 1.87 Cr | I13: 0
... A23: Punjab National Bank | B23: Public sector bank | C23: 298.5 | D23: 0.0003 | E23: 0 | F23: 0.04% (Nov 2024) | G23: 0% (Feb 2024) | H23: 34.16 L | I23: 0
A24: Tata Communications Ltd. | B24: Telecom - cellular & fixed line services | C24: 1 | D24: 0 | E24: 0 | F24: 0% (Jan 2025) | G24: 0% (Feb 2024) | H24: 750 | I24: 0
A25: GMR Airports Infrastructure Ltd. | B25: Airport & airport services | C25: 115.7 | D25: 0.0001 | E25: 0 | F25: 0.02% (Nov 2024) | G25: 0% (Feb 2024) | H25: 16.65 L | I25: 0
A26: DLF Ltd. | B26: Residential, commercial projects | C26: 88.1 | D26: 0.0001 | E26: 0 | F26: 0.01% (Jul 2024) | G26: 0% (Feb 2024) | H26: 1.39 L | I26: 0
A27: Swaraj Engines Ltd. | B27: Compressors, pumps & diesel engines | C27: 123.7 | D27: 0.0001 | E27: 0 | F27: 0.02% (Jan 2025) | G27: 0.01% (Feb 2024) | H27: 47.29 k | I27: 0
A28: Tata Steel Ltd. | B28: Iron & steel products | C28: 13.6 | D28: 0 | E28: 0 | F28: 0% (Aug 2024) | G28: 0% (Feb 2024) | H28: 99.00 k | I28: 0
A29: Steel Authority Of India Ltd. | B29: Iron & steel products | C29: 16.4 | D29: 0 | E29: 0 | F29: 0% (Dec 2024) | G29: 0% (Feb 2024) | H29: 1.56 L | I29: 0
A30: Pi Industries Ltd. | B30: Pesticides & agrochemicals | C30: 15.8 | D30: 0 | E30: 0 | F30: 0% (Jul 2024) | G30: 0% (Feb 2024) | H30: 5.25 k | I30: 0
A31: United Spirits Ltd. | B31: Breweries & distilleries | C31: 1.8 | D31: 0 | E31: 0 | F31: 0% (Apr 2024) | G31: 0% (Nov 2024) | H31: 1.40 k | I31: 0
A32: Indus Towers Ltd. | B32: Telecom - infrastructure | C32: 9.4 | D32: 0 | E32: 0 | F32: 0% (Dec 2024) | G32: 0% (Feb 2024) | H32: 28.90 k | I32: 0
A33: Havells India Ltd. | B33: Consumer electronics | C33: 0.7 | D33: 0 | E33: 0 | F33: 0% (Jan 2025) | G33: 0% (Feb 2024) | H33: 500 | I33: 0
A34: Hindustan Copper Ltd. | B34: Copper | C34: 25.2 | D34: 0 | E34: 0 | F34: 0.02% (May 2024) | G34: 0% (Feb 2024) | H34: 1.25 L | I34: 0
A35: HDFC Life Insurance Company Ltd. | B35: Life insurance | C35: 12.1 | D35: 0 | E35: 0 | F35: 0% (Apr 2024) | G35: 0% (Nov 2024) | H35: 19.80 k | I35: 0
A36: InterGlobe Aviation Ltd. | B36: Airline | C36: 2 | D36: 0 | E36: 0 | F36: 0% (Jan 2025) | G36: 0% (Feb 2024) | H36: 450 | I36: 0
A37: Bharat Heavy Electricals Ltd. | B37: Heavy electrical equipment | C37: 40.9 | D37: 0 | E37: 0 | F37: 0.01% (Jul 2024) | G37: 0% (Feb 2024) | H37: 2.28 L | I37: 0
A38: Jindal Steel & Power Ltd. | B38: Iron & steel products | C38: 7.5 | D38: 0 | E38: 0 | F38: 0% (May 2024) | G38: 0% (Feb 2024) | H38: 8.75 k | I38: 0
A39: JSW Steel Ltd. | B39: Iron & steel products | C39: 2.6 | D39: 0 | E39: 0 | F39: 0% (Dec 2024) | G39: 0% (Feb 2024) | H39: 2.70 k | I39: 0
A40: ICRA Ltd. | B40: Ratings | C40: 1527.4 | D40: 0.0017 | E40: 0 | F40: 0.42% (Feb 2024) | G40: 0.21% (Jan 2025) | H40: 2.87 L | I40: -0.10 L
A41: Biocon Ltd. | B41: Pharmaceuticals | C41: 77.9 | D41: 0.0001 | E41: 0 | F41: 0.02% (May 2024) | G41: 0.01% (Nov 2024) | H41: 2.58 L | I41: -0.55 L
A42: Indusind Bank Ltd. | B42: Private sector bank | C42: 200 | D42: 0.0002 | E42: 0 | F42: 0.07% (Feb 2024) | G42: 0.03% (Nov 2024) | H42: 2.02 L | I42: -0.67 L
A43: Multi Commodity Exchange Of India Ltd. | B43: Exchange and data platform | C43: 3981.9 | D43: 0.0045 | E43: 0 | F43: 1.65% (Aug 2024) | G43: 0.56% (Jan 2025) | H43: 7.98 L | I43: -0.84 L
A44: Bharti Airtel Ltd. | B44: Telecom - cellular & fixed line services | C44: 478.8 | D44: 0.0005 | E44: 0 | F44: 0.04% (May 2024) | G44: 0% (Feb 2024) | H44: 3.05 L | I44: 1.06 L
A45: Sun Pharmaceutical Industries Ltd. | B45: Pharmaceuticals | C45: 194.6 | D45: 0.0002 | E45: 0.0002 | F45: 0% (Mar 2025) | G45: 0% (Mar 2025) | H45: 1.22 L | I45: 1.22 L
A46: Larsen & Toubro Ltd. | B46: Civil construction | C46: 484.5 | D46: 0.0006 | E46: 0 | F46: 0.01% (Jan 2025) | G46: 0% (Nov 2024) | H46: 1.53 L | I46: 1.22 L
A47: Bandhan Bank Ltd. | B47: Private sector bank | C47: 116.6 | D47: 0.0001 | E47: 0 | F47: 0.02% (Sep 2024) | G47: 0.01% (Nov 2024) | H47: 8.26 L | I47: 1.48 L
A48: Oil & Natural Gas Corporation Ltd. | B48: Oil exploration & production | C48: 241.5 | D48: 0.0003 | E48: 0 | F48: 0% (Nov 2024) | G48: 0% (Feb 2024) | H48: 10.72 L | I48: 10.43 L
A49: Hero Motocorp Ltd. | B49: 2/3 wheelers | C49: 48.6 | D49: 0.0001 | E49: 0.0001 | F49: 0% (Mar 2025) | G49: 0% (Mar 2025) | H49: 13.20 k | I49: 13.20 k
A50: Cipla Ltd. | B50: Pharmaceuticals | C50: 10915.9 | D50: 0.0124 | E50: 0 | F50: 1.05% (Feb 2024) | G50: 0.76% (Nov 2024) | H50: 77.56 L | I50: 15.32 L
A51: National Thermal Power Corporation Ltd. | B51: Power generation | C51: 125.2 | D51: 0.0001 | E51: 0 | F51: 0.01% (Dec 2024) | G51: 0% (Feb 2024) | H51: 4.02 L | I51: 18.00 k
... A71: Hindustan Unilever Ltd. | B71: Diversified fmcg | C71: 210.9 | D71: 0.0002 | E71: 0 | F71: 0.01% (Mar 2024) | G71: 0% (Nov 2024) | H71: 96.30 k | I71: 93.60 k
A72: Private sector bank | C72: 181884 | D72: 0.2067 | E72: 0
A73: Foreign equity | C73: 113518 | D73: 0.129 | E73: 0
A74: Passenger cars & utility vehicles | C74: 62646.3 | D74: 0.0712 | E74: 0
A75: Holding company | C75: 61677.2 | D75: 0.0701 | E75: 0
A76: Coal | C76: 52682.8 | D76: 0.0599 | E76: 0
A77: Power - transmission | C77: 48539.2 | D77: 0.0552 | E77: 0
A78: Computers - software & consulting | C78: 46240.1 | D78: 0.0525 | E78: 0.0012
A79: Diversified fmcg | C79: 40182.6 | D79: 0.0456 | E79: 0
A80: Pharmaceuticals | C80: 34929.7 | D80: 0.0397 | E80: 0.0002
A81: Tyres & rubber products | C81: 10957.2 | D81: 0.0125 | E81: 0
A82: Exchange and data platform | C82: 10875 | D82: 0.0123 | E82: 0
A83: Refineries & marketing | C83: 7785.1 | D83: 0.0088 | E83: 0
... A115: Iron & steel products | C115: 10.1 | D115: 0 | E115: 0
A116: - indicates change in weight in the portfolio. # indicates a new entry.

Sheet quant holdings
A1: Stock Invested in | B1: Sector | C1: Value(Mn) | D1: % of Total Holdings | E1: 1M Change | F1: 1Y Highest Holding | G1: 1Y Lowest Holding | H1: Quantity | I1: 1M Change in Qty
A2: Aurobindo Pharma Ltd. | B2: Pharmaceuticals | C2: 6995.1 | D2: 0.0813 | E2: -0.0083 | F2: 10% (Aug 2024) | G2: 6.94% (Mar 2024) | H2: 59.69 L | I2: 0
A3: Bharat Forge Ltd. | B3: Castings & forgings | C3: 2926.1 | D3: 0.034 | E3: -0.0009 | F3: 3.77% (Oct 2024) | G3: 0% (Feb 2024) | H3: 23.91 L | I3: 0
A4: Cochin Shipyard Ltd. | B4: Ship building & allied services | C4: 1348.7 | D4: 0.0157 | E4: 0.0005 | F4: 1.57% (Jan 2025) | G4: 0% (Feb 2024) | H4: 8.80 L | I4: 0
A5: Container Corporation Of India Ltd. | B5: Logistics solution provider | C5: 6382.8 | D5: 0.0741 | E5: 0.0016 | F5: 9.17% (Jul 2024) | G5: 1.44% (Feb 2024) | H5: 81.82 L | I5: 0
A6: CRISIL Ltd. | B6: Other financial services | C6: 1633.4 | D6: 0.019 | E6: -0.0035 | F6: 2.44% (Feb 2024) | G6: 1.42% (Jul 2024) | H6: 3.01 L | I6: 0
A7: GAIL (India) Ltd. : Futures Near | B7: Gas transmission/marketing | C7: 315.8 | D7: 0.0037 | E7: -0.0001 | F7: 0.38% (Dec 2024) | G7: 0% (Feb 2024) | H7: 17.74 L | I7: 0.17 Cr
A8: GlaxoSmithKline Pharmaceuticals Ltd. | B8: Pharmaceuticals | C8: 817.5 | D8: 0.0095 | E8: -0.0115 | F8: 2.52% (Oct 2024) | G8: 0.95% (Jan 2025) | H8: 4.13 L | I8: -4.16 L
A9: GMR Airports Infrastructure Ltd. | B9: Airport & airport services | C9: 1751.8 | D9: 0.0204 | E9: -0.0009 | F9: 3.41% (Feb 2024) | G9: 0% (Feb 2024) | H9: 2.41 Cr | I9: 0
A10: Housing & Urban Development Corporation Ltd. | B10: Financial institution | C10: 895.6 | D10: 0.0104 | E10: 0.0001 | F10: 1.04% (Jan 2025) | G10: 0% (Feb 2024) | H10: 38.99 L | I10: 0
A11: Indian Railway Catering and Tourism Corporation Ltd. | B11: Tour, travel related services | C11: 1360.9 | D11: 0.0158 | E11: 0.0012 | F11: 2.48% (Apr 2024) | G11: 0% (Feb 2024) | H11: 16.55 L | I11: 0
A12: Indus Towers Ltd. | B12: Telecom - infrastructure | C12: 1374.9 | D12: 0.016 | E12: 0.0008 | F12: 1.6% (Jan 2025) | G12: 0% (Feb 2024) | H12: 39.60 L | I12: 0
A13: Ipca Laboratories Ltd. | B13: Pharmaceuticals | C13: 1516.9 | D13: 0.0176 | E13: -0.0024 | F13: 2% (Dec 2024) | G13: 0% (Feb 2024) | H13: 10.51 L | I13: 0
A14: IRB Infrastructure Developers Ltd. | B14: Civil construction | C14: 7073 | D14: 0.0822 | E14: 0.0028 | F14: 8.82% (Jul 2024) | G14: 0% (Feb 2024) | H14: 12.34 Cr | I14: 0
A15: ITC Limited | B15: Diversified fmcg | C15: 4379.8 | D15: 0.0509 | E15: -0.0023 | F15: 5.35% (Oct 2024) | G15: 0% (Feb 2024) | H15: 97.87 L | I15: 0
A16: JSW Infrastructure Ltd. | B16: Engineering, designing, construction | C16: 924.4 | D16: 0.0107 | E16: -0.0013 | F16: 1.2% (Dec 2024) | G16: 0% (Feb 2024) | H16: 33.62 L | I16: 0
A17: Larsen & Toubro Ltd. : Futures Near | B17: Civil construction | C17: 845.1 | D17: 0.0098 | E17: 0.0002 | F17: 0.98% (Jan 2025) | G17: 0% (Feb 2024) | H17: 2.36 L | I17: 0.01 Cr
A18: Life Insurance Corporation Of India | B18: Life insurance | C18: 835.6 | D18: 0.0097 | E18: -0.0002 | F18: 1.12% (Aug 2024) | G18: 0% (Feb 2024) | H18: 9.88 L | I18: 0
A19: Linde India Ltd. | B19: Industrial gases | C19: 3000.7 | D19: 0.0349 | E19: 0.0026 | F19: 6.19% (Apr 2024) | G19: 3.23% (Dec 2024) | H19: 4.79 L | I19: 0
A20: Lloyds Metals And Energy Ltd. | B20: Sponge iron | C20: 4548.7 | D20: 0.0528 | E20: 0.0046 | F20: 5.28% (Jan 2025) | G20: 0% (Feb 2024) | H20: 36.71 L | I20: 1.90 L
A21: Marico Ltd. | B21: Personal care | C21: 5370 | D21: 0.0624 | E21: 0.0048 | F21: 6.24% (Jan 2025) | G21: 0% (Feb 2024) | H21: 80.07 L | I21: 0
A22: Mazagon Dock Shipbuilders Ltd. | B22: Ship building & allied services | C22: 2188.2 | D22: 0.0254 | E22: 0.0035 | F22: 2.54% (Jan 2025) | G22: 0% (Feb 2024) | H22: 8.76 L | I22: 0
A23: MRF Ltd. | B23: Tyres & rubber products | C23: 2147.4 | D23: 0.0249 | E23: -0.0029 | F23: 2.9% (Jul 2024) | G23: 0% (Feb 2024) | H23: 18.90 k | I23: 0
A24: NMDC LTD | B24: Industrial minerals | C24: 1235.6 | D24: 0.0144 | E24: 0.0005 | F24: 5.37% (Feb 2024) | G24: 0% (Feb 2024) | H24: 1.87 Cr | I24: 0
A25: Oil India Ltd. | B25: Oil exploration & production | C25: 846.7 | D25: 0.0098 | E25: 0 | F25: 3.07% (Mar 2024) | G25: 0% (Feb 2024) | H25: 20.14 L | I25: 0
A26: Oil India Ltd. : Futures Near | B26: Oil exploration & production | C26: 1412.7 | D26: 0.0164 | E26: 0 | F26: 1.64% (Jan 2025) | G26: 0% (Feb 2024) | H26: 33.46 L | I26: 0.32 Cr
A27: Reliance Industries Ltd. | B27: Refineries & marketing | C27: 8250.6 | D27: 0.0958 | E27: 0.0066 | F27: 10.52% (Jun 2024) | G27: 8.92% (Dec 2024) | H27: 65.22 L | I27: 0
A28: Steel Authority Of India Ltd. | B28: Iron & steel products | C28: 4553.6 | D28: 0.0529 | E28: -0.001 | F28: 8.78% (Jul 2024) | G28: 3.35% (Feb 2024) | H28: 4.24 Cr | I28: 0
A29: Tata Communications Ltd. | B29: Telecom - cellular & fixed line services | C29: 4966.1 | D29: 0.0577 | E29: -0.0006 | F29: 5.97% (Nov 2024) | G29: 2.47% (Aug 2024) | H29: 30.41 L | I29: 0
A30: Tata Communications Ltd. : Futures Near | B30: Telecom - cellular & fixed line services | C30: 692.7 | D30: 0.008 | E30: -0.0002 | F30: 2.15% (Sep 2024) | G30: 0% (Feb 2024) | H30: 4.23 L | I30: 0.03 Cr
A31: Tata Power Co. Ltd. | B31: Integrated power utilities | C31: 1245.2 | D31: 0.0145 | E31: -0.0006 | F31: 2.03% (May 2024) | G31: 0.84% (Apr 2024) | H31: 34.16 L | I31: 0
A32: Aditya Birla Fashion and Retail Ltd. | B32: Speciality retail | C32: 757.1 | D32: 0.0088 | E32: 0.0088 | F32: 0.88% (Jan 2025) | G32: 0% (Feb 2024) | H32: 27.64 L | I32: 27.64 L
A33: ITC Hotels Ltd | B33: Hotels & resorts | C33: 159.5 | D33: 0.0019 | E33: 0.0019 | F33: 0.19% (Jan 2025) | G33: 0% (Feb 2024) | H33: 9.79 L | I33: 9.79 L
A34: Airport & airport services | C34: 1751.8 | D34: 0.0204 | E34: -0.0009
A35: Castings & forgings | C35: 2926.1 | D35: 0.034 | E35: -0.0009
A36: Cement & cement products | C36: 960.4 | D36: 0 | E36: -0.0108
A37: Civil construction | C37: 7918.1 | D37: 0.092 | E37: 0.003
A38: Diversified fmcg | C38: 4379.8 | D38: 0.0509 | E38: -0.0023
A39: Engineering, designing, construction | C39: 924.4 | D39: 0.0107 | E39: -0.0013
A40: Financial institution | C40: 895.6 | D40: 0.0104 | E40: 0.0001
A41: Gas transmission/marketing | C41: 315.8 | D41: 0.0037 | E41: -0.0001
A42: Hotels & resorts | C42: 159.5 | D42: 0.0019 | E42: 0.0019
A43: Industrial gases | C43: 3000.7 | D43: 0.0349 | E43: 0.0026
A44: Industrial minerals | C44: 1235.6 | D44: 0.0144 | E44: 0.0005
A45: Integrated power utilities | C45: 1245.2 | D45: 0.0145 | E45: -0.0006
... A61: Tyres & rubber products | C61: 2147.4 | D61: 0.0249 | E61: -0.0029

Sheet finding common co
A1: NF500 | B1: KOTAK | C1: MATCH DATA | D1: NIPPON | E1: MATCH DATA | F1: PARAG PARIK HOLINGS | G1: MATCH DATA | H1: QUANT | I1: MATCH DATA | J1: common on 2 or more companies
A2: Aavas Financiers Ltd. | B2: Coromandel International Ltd. | C2: =IF(ISNUMBER(MATCH(B2, $A$2:$A$501, 0)), "Present", "Absent") -> Present | D2: Motherson Sumi Systems Ltd. | E2: =IF(ISNUMBER(MATCH(D2, $A$1:$A$501, 0)), "Present", "Absent") -> Absent | F2: GMR Airports Infrastructure Ltd. | G2: =IF(ISNUMBER(MATCH(F2, $A$2:$A$501, 0)), "Present", "Absent") -> Absent | H2: Oil India Ltd. | I2: =IF(ISNUMBER(MATCH(H2, $A$2:$A$501, 0)), "Present","Absent") -> Present | J2: =IF( (COUNTIF($A$2:$A$501, $B$2:$B$67) > 0) + (COUNTIF($D$2:$D$234, $B$2:$B$67) > 0) + (COUNTIF($F$2:$F$204, $B$2:$B$67) > 0) + (COUNTIF($H$2:$H$33, $B$2:$B$67) > 0) >= 2, "Present", "Absent" ) -> Absent
A3: Adani Energy Solutions Ltd. | B3: Dixon Technologies (India) Ltd. | C3: =IF(ISNUMBER(MATCH(B3, $A$2:$A$501, 0)), "Present", "Absent") -> Present | D3: Schaeffler India Ltd. | E3: =IF(ISNUMBER(MATCH(D3, $A$1:$A$501, 0)), "Present", "Absent") -> Present | F3: ITC Hotels Ltd | G3: =IF(ISNUMBER(MATCH(F3, $A$2:$A$501, 0)), "Present", "Absent") -> Absent | H3: Marico Ltd. | I3: =IF(ISNUMBER(MATCH(H3, $A$2:$A$501, 0)), "Present","Absent") -> Present | J3: =IF( (COUNTIF($A$2:$A$501, $B$2:$B$67) > 0) + (COUNTIF($D$2:$D$234, $B$2:$B$67) > 0) + (COUNTIF($F$2:$F$204, $B$2:$B$67) > 0) + (COUNTIF($H$2:$H$33, $B$2:$B$67) > 0) >= 2, "Present", "Absent" ) -> Present
A4: Aditya Birla Capital Ltd. | B4: Mphasis Ltd. | C4: =IF(ISNUMBER(MATCH(B4, $A$2:$A$501, 0)), "Present", "Absent") -> Present | D4: Aditya Birla Sun Life AMC Ltd. | E4: =IF(ISNUMBER(MATCH(D4, $A$1:$A$501, 0)), "Present", "Absent") -> Present | F4: Indian Energy Exchange Ltd. | G4: =IF(ISNUMBER(MATCH(F4, $A$2:$A$501, 0)), "Present", "Absent") -> Present | H4: JSW Infrastructure Ltd. | I4: =IF(ISNUMBER(MATCH(H4, $A$2:$A$501, 0)), "Present","Absent") -> Present | J4: =IF( (COUNTIF($A$2:$A$501, $B$2:$B$67) > 0) + (COUNTIF($D$2:$D$234, $B$2:$B$67) > 0) + (COUNTIF($F$2:$F$204, $B$2:$B$67) > 0) + (COUNTIF($H$2:$H$33, $B$2:$B$67) > 0) >= 2, "Present", "Absent" ) -> Absent
A5: Aegis Logistics Ltd. | B5: The Ramco Cements Ltd. | C5: =IF(ISNUMBER(MATCH(B5, $A$2:$A$501, 0)), "Present", "Absent") -> Present | D5: Wonderla Holidays Ltd. | E5: =IF(ISNUMBER(MATCH(D5, $A$1:$A$501, 0)), "Present", "Absent") -> Absent | F5: HCL Technologies Limited | G5: =IF(ISNUMBER(MATCH(F5, $A$2:$A$501, 0)), "Present", "Absent") -> Absent | H5: Ipca Laboratories Ltd. | I5: =IF(ISNUMBER(MATCH(H5, $A$2:$A$501, 0)), "Present","Absent") -> Present | J5: =IF( (COUNTIF($A$2:$A$501, $B$2:$B$67) > 0) + (COUNTIF($D$2:$D$234, $B$2:$B$67) > 0) + (COUNTIF($F$2:$F$204, $B$2:$B$67) > 0) + (COUNTIF($H$2:$H$33, $B$2:$B$67) > 0) >= 2, "Present", "Absent" ) -> Absent
A6: Balrampur Chini Mills Ltd. | B6: Bharat Electronics Ltd. | C6: =IF(ISNUMBER(MATCH(B6, $A$2:$A$501, 0)), "Present", "Absent") -> Present | D6: Timken India Ltd. | E6: =IF(ISNUMBER(MATCH(D6, $A$1:$A$501, 0)), "Present", "Absent") -> Present | F6: HDFC Bank Ltd. | G6: =IF(ISNUMBER(MATCH(F6, $A$2:$A$501, 0)), "Present", "Absent") -> Present | H6: Aurobindo Pharma Ltd. | I6: =IF(ISNUMBER(MATCH(H6, $A$2:$A$501, 0)), "Present","Absent") -> Present | J6: =IF( (COUNTIF($A$2:$A$501, $B$2:$B$67) > 0) + (COUNTIF($D$2:$D$234, $B$2:$B$67) > 0) + (COUNTIF($F$2:$F$204, $B$2:$B$67) > 0) + (COUNTIF($H$2:$H$33, $B$2:$B$67) > 0) >= 2, "Present", "Absent" ) -> Present
A7: Bata India Ltd. | B7: Vishal Mega Mart Ltd. | C7: =IF(ISNUMBER(MATCH(B7, $A$2:$A$501, 0)), "Present", "Absent") -> Absent | D7: Sansera Engineering Ltd. | E7: =IF(ISNUMBER(MATCH(D7, $A$1:$A$501, 0)), "Present", "Absent") -> Absent | F7: Maharashtra Scooters Ltd. | G7: =IF(ISNUMBER(MATCH(F7, $A$2:$A$501, 0)), "Present", "Absent") -> Absent | H7: Mazagon Dock Shipbuilders Ltd. | I7: =IF(ISNUMBER(MATCH(H7, $A$2:$A$501, 0)), "Present","Absent") -> Present | J7: =IF( (COUNTIF($A$2:$A$501, $B$2:$B$67) > 0) + (COUNTIF($D$2:$D$234, $B$2:$B$67) > 0) + (COUNTIF($F$2:$F$204, $B$2:$B$67) > 0) + (COUNTIF($H$2:$H$33, $B$2:$B$67) > 0) >= 2, "Present", "Absent" ) -> Absent
A8: Krishna Institute of Medical Sciences Ltd. | B8: Sundram Fasteners Ltd. | C8: =IF(ISNUMBER(MATCH(B8, $A$2:$A$501, 0)), "Present", "Absent") -> Present | D8: Mishra Dhatu Nigam Ltd. | E8: =IF(ISNUMBER(MATCH(D8, $A$1:$A$501, 0)), "Present", "Absent") -> Absent | F8: Alphabet Inc | G8: =IF(ISNUMBER(MATCH(F8, $A$2:$A$501, 0)), "Present", "Absent") -> Absent | H8: GAIL (India) Ltd. : Futures Near | I8: =IF(ISNUMBER(MATCH(H8, $A$2:$A$501, 0)), "Present","Absent") -> Absent | J8: =IF( (COUNTIF($A$2:$A$501, $B$2:$B$67) > 0) + (COUNTIF($D$2:$D$234, $B$2:$B$67) > 0) + (COUNTIF($F$2:$F$204, $B$2:$B$67) > 0) + (COUNTIF($H$2:$H$33, $B$2:$B$67) > 0) >= 2, "Present", "Absent" ) -> Present
A9: Bharat Forge Ltd. | B9: GE T&D India Ltd. | C9: =IF(ISNUMBER(MATCH(B9, $A$2:$A$501, 0)), "Present", "Absent") -> Absent | D9: CIE AUTOMOTIVE INDIA Ltd. | E9: =IF(ISNUMBER(MATCH(D9, $A$1:$A$501, 0)), "Present", "Absent") -> Present | F9: Indus Towers Ltd. | G9: =IF(ISNUMBER(MATCH(F9, $A$2:$A$501, 0)), "Present", "Absent") -> Present | H9: Aditya Birla Fashion and Retail Ltd. | I9: =IF(ISNUMBER(MATCH(H9, $A$2:$A$501, 0)), "Present","Absent") -> Present | J9: =IF( (COUNTIF($A$2:$A$501, $B$2:$B$67) > 0) + (COUNTIF($D$2:$D$234, $B$2:$B$67) > 0) + (COUNTIF($F$2:$F$204, $B$2:$B$67) > 0) + (COUNTIF($H$2:$H$33, $B$2:$B$67) > 0) >= 2, "Present", "Absent" ) -> Absent
A10: Sundaram Finance Ltd. | B10: KEI Industries Ltd. | C10: =IF(ISNUMBER(MATCH(B10, $A$2:$A$501, 0)), "Present", "Absent") -> Present | D10: Data Patterns India Ltd. | E10: =IF(ISNUMBER(MATCH(D10, $A$1:$A$501, 0)), "Present", "Absent") -> Absent | F10: Amazon.com | G10: =IF(ISNUMBER(MATCH(F10, $A$2:$A$501, 0)), "Present", "Absent") -> Absent | H10: GMR Airports Infrastructure Ltd. | I10: =IF(ISNUMBER(MATCH(H10, $A$2:$A$501, 0)), "Present","Absent") -> Absent | J10: =IF( (COUNTIF($A$2:$A$501, $B$2:$B$67) > 0) + (COUNTIF($D$2:$D$234, $B$2:$B$67) > 0) + (COUNTIF($F$2:$F$204, $B$2:$B$67) > 0) + (COUNTIF($H$2:$H$33, $B$2:$B$67) > 0) >= 2, "Present", "Absent" ) -> Absent
A11: Jio Financial Services Ltd. | B11: Polycab India Limited | C11: =IF(ISNUMBER(MATCH(B11, $A$2:$A$501, 0)), "Present", "Absent") -> Absent | D11: Bharat Dynamics Ltd. | E11: =IF(ISNUMBER(MATCH(D11, $A$1:$A$501, 0)), "Present", "Absent") -> Present | F11: Maruti Suzuki India Ltd. | G11: =IF(ISNUMBER(MATCH(F11, $A$2:$A$501, 0)), "Present", "Absent") -> Present | H11: Housing & Urban Development Corporation Ltd. | I11: =IF(ISNUMBER(MATCH(H11, $A$2:$A$501, 0)), "Present","Absent") -> Absent | J11: =IF( (COUNTIF($A$2:$A$501, $B$2:$B$67) > 0) + (COUNTIF($D$2:$D$234, $B$2:$B$67) > 0) + (COUNTIF($F$2:$F$204, $B$2:$B$67) > 0) + (COUNTIF($H$2:$H$33, $B$2:$B$67) > 0) >= 2, "Present", "Absent" ) -> Absent
A12: Adani Green Energy Ltd. | B12: Bharat Forge Ltd. | C12: =IF(ISNUMBER(MATCH(B12, $A$2:$A$501, 0)), "Present", "Absent") -> Present | D12: Astra Microwave Products Ltd. | E12: =IF(ISNUMBER(MATCH(D12, $A$1:$A$501, 0)), "Present", "Absent") -> Absent | F12: Bajaj Holdings & Investment Ltd. | G12: =IF(ISNUMBER(MATCH(F12, $A$2:$A$501, 0)), "Present", "Absent") -> Present | H12: Indian Railway Catering and Tourism Corporation Ltd. | I12: =IF(ISNUMBER(MATCH(H12, $A$2:$A$501, 0)), "Present","Absent") -> Absent | J12: =IF( (COUNTIF($A$2:$A$501, $B$2:$B$67) > 0) + (COUNTIF($D$2:$D$234, $B$2:$B$67) > 0) + (COUNTIF($F$2:$F$204, $B$2:$B$67) > 0) + (COUNTIF($H$2:$H$33, $B$2:$B$67) > 0) >= 2, "Present", "Absent" ) -> Present
A13: Brigade Enterprises Ltd. | B13: Metro Brands Ltd. | C13: =IF(ISNUMBER(MATCH(B13, $A$2:$A$501, 0)), "Present", "Absent") -> Present | D13: Gabriel India Ltd. | E13: =IF(ISNUMBER(MATCH(D13, $A$1:$A$501, 0)), "Present", "Absent") -> Absent | F13: Steel Authority Of India Ltd. | G13: =IF(ISNUMBER(MATCH(F13, $A$2:$A$501, 0)), "Present", "Absent") -> Absent | H13: Tata Communications Ltd. | I13: =IF(ISNUMBER(MATCH(H13, $A$2:$A$501, 0)), "Present","Absent") -> Present | J13: =IF( (COUNTIF($A$2:$A$501, $B$2:$B$67) > 0) + (COUNTIF($D$2:$D$234, $B$2:$B$67) > 0) + (COUNTIF($F$2:$F$204, $B$2:$B$67) > 0) + (COUNTIF($H$2:$H$33, $B$2:$B$67) > 0) >= 2, "Present", "Absent" ) -> Absent
... A33: Deepak Fertilisers & Petrochemicals Corporation Ltd. | B33: ICICI Lombard General Insurance Co Ltd. | C33: =IF(ISNUMBER(MATCH(B33, $A$2:$A$501, 0)), "Present", "Absent") -> Absent | D33: Craftsman Automation Ltd. | E33: =IF(ISNUMBER(MATCH(D33, $A$1:$A$501, 0)), "Present", "Absent") -> Present | F33: United Spirits Ltd. | G33: =IF(ISNUMBER(MATCH(F33, $A$2:$A$501, 0)), "Present", "Absent") -> Present | H33: Tata Power Co. Ltd. | I33: =IF(ISNUMBER(MATCH(H33, $A$2:$A$501, 0)), "Present","Absent") -> Absent | J33: =IF( (COUNTIF($A$2:$A$501, $B$2:$B$67) > 0) + (COUNTIF($D$2:$D$234, $B$2:$B$67) > 0) + (COUNTIF($F$2:$F$204, $B$2:$B$67) > 0) + (COUNTIF($H$2:$H$33, $B$2:$B$67) > 0) >= 2, "Present", "Absent" ) -> Absent
A34: Equitas Small Finance Bank Ltd. | B34: Amber Enterprises India Ltd. | C34: =IF(ISNUMBER(MATCH(B34, $A$2:$A$501, 0)), "Present", "Absent") -> Present | D34: Finolex Cables Ltd. | E34: =IF(ISNUMBER(MATCH(D34, $A$1:$A$501, 0)), "Present", "Absent") -> Present | F34: J S W Steel Ltd. | G34: =IF(ISNUMBER(MATCH(F34, $A$2:$A$501, 0)), "Present", "Absent") -> Absent | J34: =IF( (COUNTIF($A$2:$A$501, $B$2:$B$67) > 0) + (COUNTIF($D$2:$D$234, $B$2:$B$67) > 0) + (COUNTIF($F$2:$F$204, $B$2:$B$67) > 0) + (COUNTIF($H$2:$H$33, $B$2:$B$67) > 0) >= 2, "Present", "Absent" ) -> Absent
A35: Multi Commodity Exchange of India Ltd. | B35: Apar Industries Ltd. | C35: =IF(ISNUMBER(MATCH(B35, $A$2:$A$501, 0)), "Present", "Absent") -> Present | D35: ISGEC Heavy Engineering Ltd. | E35: =IF(ISNUMBER(MATCH(D35, $A$1:$A$501, 0)), "Present", "Absent") -> Absent | F35: Oil & Natural Gas Corporation Ltd. | G35: =IF(ISNUMBER(MATCH(F35, $A$2:$A$501, 0)), "Present", "Absent") -> Absent | J35: =IF( (COUNTIF($A$2:$A$501, $B$2:$B$67) > 0) + (COUNTIF($D$2:$D$234, $B$2:$B$67) > 0) + (COUNTIF($F$2:$F$204, $B$2:$B$67) > 0) + (COUNTIF($H$2:$H$33, $B$2:$B$67) > 0) >= 2, "Present", "Absent" ) -> Present
A36: Shyam Metalics and Energy Ltd. | B36: APL Apollo Tubes Ltd. | C36: =IF(ISNUMBER(MATCH(B36, $A$2:$A$501, 0)), "Present", "Absent") -> Present | D36: Birla Corporation Ltd. | E36: =IF(ISNUMBER(MATCH(D36, $A$1:$A$501, 0)), "Present", "Absent") -> Present | F36: Multi Commodity Exchange Of India Ltd. | G36: =IF(ISNUMBER(MATCH(F36, $A$2:$A$501, 0)), "Present", "Absent") -> Present | J36: =IF( (COUNTIF($A$2:$A$501, $B$2:$B$67) > 0) + (COUNTIF($D$2:$D$234, $B$2:$B$67) > 0) + (COUNTIF($F$2:$F$204, $B$2:$B$67) > 0) + (COUNTIF($H$2:$H$33, $B$2:$B$67) > 0) >= 2, "Present", "Absent" ) -> Absent
A37: EIH Ltd. | B37: Apollo Tyres Limited | C37: =IF(ISNUMBER(MATCH(B37, $A$2:$A$501, 0)), "Present", "Absent") -> Absent | D37: PG Electroplast Ltd. | E37: =IF(ISNUMBER(MATCH(D37, $A$1:$A$501, 0)), "Present", "Absent") -> Absent | F37: Tata Motors Ltd. | G37: =IF(ISNUMBER(MATCH(F37, $A$2:$A$501, 0)), "Present", "Absent") -> Present | J37: =IF( (COUNTIF($A$2:$A$501, $B$2:$B$67) > 0) + (COUNTIF($D$2:$D$234, $B$2:$B$67) > 0) + (COUNTIF($F$2:$F$204, $B$2:$B$67) > 0) + (COUNTIF($H$2:$H$33, $B$2:$B$67) > 0) >= 2, "Present", "Absent" ) -> Absent
A38: HDFC Bank Ltd. | B38: Atul Ltd. | C38: =IF(ISNUMBER(MATCH(B38, $A$2:$A$501, 0)), "Present", "Absent") -> Present | D38: Persistent Systems Ltd. | E38: =IF(ISNUMBER(MATCH(D38, $A$1:$A$501, 0)), "Present", "Absent") -> Present | F38: Bharat Electronics Ltd. | G38: =IF(ISNUMBER(MATCH(F38, $A$2:$A$501, 0)), "Present", "Absent") -> Present | J38: =IF( (COUNTIF($A$2:$A$501, $B$2:$B$67) > 0) + (COUNTIF($D$2:$D$234, $B$2:$B$67) > 0) + (COUNTIF($F$2:$F$204, $B$2:$B$67) > 0) + (COUNTIF($H$2:$H$33, $B$2:$B$67) > 0) >= 2, "Present", "Absent" ) -> Absent
A39: JK Lakshmi Cement Ltd. | B39: Au Small Finance Bank Ltd. | C39: =IF(ISNUMBER(MATCH(B39, $A$2:$A$501, 0)), "Present", "Absent") -> Present | D39: Kalpataru Power Transmission Ltd. | E39: =IF(ISNUMBER(MATCH(D39, $A$1:$A$501, 0)), "Present", "Absent") -> Absent | F39: Bandhan Bank Ltd. | G39: =IF(ISNUMBER(MATCH(F39, $A$2:$A$501, 0)), "Present", "Absent") -> Present | J39: =IF( (COUNTIF($A$2:$A$501, $B$2:$B$67) > 0) + (COUNTIF($D$2:$D$234, $B$2:$B$67) > 0) + (COUNTIF($F$2:$F$204, $B$2:$B$67) > 0) + (COUNTIF($H$2:$H$33, $B$2:$B$67) > 0) >= 2, "Present", "Absent" ) -> Absent
A40: Graphite India Ltd. | B40: Balkrishna Industries Ltd. | C40: =IF(ISNUMBER(MATCH(B40, $A$2:$A$501, 0)), "Present", "Absent") -> Present | D40: Orient Electric Ltd. | E40: =IF(ISNUMBER(MATCH(D40, $A$1:$A$501, 0)), "Present", "Absent") -> Absent | F40: Mahindra & Mahindra Ltd. | G40: =IF(ISNUMBER(MATCH(F40, $A$2:$A$501, 0)), "Present", "Absent") -> Present | J40: =IF( (COUNTIF($A$2:$A$501, $B$2:$B$67) > 0) + (COUNTIF($D$2:$D$234, $B$2:$B$67) > 0) + (COUNTIF($F$2:$F$204, $B$2:$B$67) > 0) + (COUNTIF($H$2:$H$33, $B$2:$B$67) > 0) >= 2, "Present", "Absent" ) -> Present
A41: ZF Commercial Vehicle Control Systems India Ltd. | B41: Bharti Hexacom Ltd. | C41: =IF(ISNUMBER(MATCH(B41, $A$2:$A$501, 0)), "Present", "Absent") -> Present | D41: Birlasoft Ltd. | E41: =IF(ISNUMBER(MATCH(D41, $A$1:$A$501, 0)), "Present", "Absent") -> Present | F41: Reliance Industries Ltd. | G41: =IF(ISNUMBER(MATCH(F41, $A$2:$A$501, 0)), "Present", "Absent") -> Present | J41: =IF( (COUNTIF($A$2:$A$501, $B$2:$B$67) > 0) + (COUNTIF($D$2:$D$234, $B$2:$B$67) > 0) + (COUNTIF($F$2:$F$204, $B$2:$B$67) > 0) + (COUNTIF($H$2:$H$33, $B$2:$B$67) > 0) >= 2, "Present", "Absent" ) -> Absent
A42: Divi's Laboratories Ltd. | B42: Blue Star Ltd. | C42: =IF(ISNUMBER(MATCH(B42, $A$2:$A$501, 0)), "Present", "Absent") -> Present | D42: Allied Blenders and Distillers Ltd. | E42: =IF(ISNUMBER(MATCH(D42, $A$1:$A$501, 0)), "Present", "Absent") -> Absent | F42: Bharat Heavy Electricals Ltd. | G42: =IF(ISNUMBER(MATCH(F42, $A$2:$A$501, 0)), "Present", "Absent") -> Present | J42: =IF( (COUNTIF($A$2:$A$501, $B$2:$B$67) > 0) + (COUNTIF($D$2:$D$234, $B$2:$B$67) > 0) + (COUNTIF($F$2:$F$204, $B$2:$B$67) > 0) + (COUNTIF($H$2:$H$33, $B$2:$B$67) > 0) >= 2, "Present", "Absent" ) -> Present
A43: GAIL (India) Ltd. | B43: Deepak Nitrite Ltd. | C43: =IF(ISNUMBER(MATCH(B43, $A$2:$A$501, 0)), "Present", "Absent") -> Present | D43: Sonata Software Ltd. | E43: =IF(ISNUMBER(MATCH(D43, $A$1:$A$501, 0)), "Present", "Absent") -> Present | F43: EID-Parry (India) Ltd. | G43: =IF(ISNUMBER(MATCH(F43, $A$2:$A$501, 0)), "Present", "Absent") -> Absent | J43: =IF( (COUNTIF($A$2:$A$501, $B$2:$B$67) > 0) + (COUNTIF($D$2:$D$234, $B$2:$B$67) > 0) + (COUNTIF($F$2:$F$204, $B$2:$B$67) > 0) + (COUNTIF($H$2:$H$33, $B$2:$B$67) > 0) >= 2, "Present", "Absent" ) -> Present
A44: City Union Bank Ltd. | B44: Edelweiss Securities Pvt. Ltd. | C44: =IF(ISNUMBER(MATCH(B44, $A$2:$A$501, 0)), "Present", "Absent") -> Absent | D44: KPIT Technologies Ltd. | E44: =IF(ISNUMBER(MATCH(D44, $A$1:$A$501, 0)), "Present", "Absent") -> Present | F44: Coal India Ltd. | G44: =IF(ISNUMBER(MATCH(F44, $A$2:$A$501, 0)), "Present", "Absent") -> Present | J44: =IF( (COUNTIF($A$2:$A$501, $B$2:$B$67) > 0) + (COUNTIF($D$2:$D$234, $B$2:$B$67) > 0) + (COUNTIF($F$2:$F$204, $B$2:$B$67) > 0) + (COUNTIF($H$2:$H$33, $B$2:$B$67) > 0) >= 2, "Present", "Absent" ) -> Absent
A45: Akums Drugs & Pharmaceuticals Ltd. | B45: Emami Ltd. | C45: =IF(ISNUMBER(MATCH(B45, $A$2:$A$501, 0)), "Present", "Absent") -> Present | D45: Ion Exchange (india) Ltd. | E45: =IF(ISNUMBER(MATCH(D45, $A$1:$A$501, 0)), "Present", "Absent") -> Absent | F45: Hero Motocorp Ltd. | G45: =IF(ISNUMBER(MATCH(F45, $A$2:$A$501, 0)), "Present", "Absent") -> Present | J45: =IF( (COUNTIF($A$2:$A$501, $B$2:$B$67) > 0) + (COUNTIF($D$2:$D$234, $B$2:$B$67) > 0) + (COUNTIF($F$2:$F$204, $B$2:$B$67) > 0) + (COUNTIF($H$2:$H$33, $B$2:$B$67) > 0) >= 2, "Present", "Absent" ) -> Present
... A67: BEML Ltd. | B67: Voltas Limited | C67: =IF(ISNUMBER(MATCH(B67, $A$2:$A$501, 0)), "Present", "Absent") -> Absent | D67: eClerx Services Ltd. | E67: =IF(ISNUMBER(MATCH(D67, $A$1:$A$501, 0)), "Present", "Absent") -> Present | F67: Jindal Steel & Power Ltd. | G67: =IF(ISNUMBER(MATCH(F67, $A$2:$A$501, 0)), "Present", "Absent") -> Present | J67: =IF( (COUNTIF($A$2:$A$501, $B$2:$B$67) > 0) + (COUNTIF($D$2:$D$234, $B$2:$B$67) > 0) + (COUNTIF($F$2:$F$204, $B$2:$B$67) > 0) + (COUNTIF($H$2:$H$33, $B$2:$B$67) > 0) >= 2, "Present", "Absent" ) -> Absent
A68: Kalyan Jewellers India Ltd. | D68: 3M India Ltd. | E68: =IF(ISNUMBER(MATCH(D68, $A$1:$A$501, 0)), "Present", "Absent") -> Present | F68: Godrej Properties Ltd. | G68: =IF(ISNUMBER(MATCH(F68, $A$2:$A$501, 0)), "Present", "Absent") -> Present | J68: =IF( (COUNTIF($A$2:$A$501, $B$2:$B$67) > 0) + (COUNTIF($D$2:$D$234, $B$2:$B$67) > 0) + (COUNTIF($F$2:$F$204, $B$2:$B$67) > 0) + (COUNTIF($H$2:$H$33, $B$2:$B$67) > 0) >= 2, "Present", "Absent" ) -> Absent
A69: Five-Star Business Finance Ltd. | D69: Aarti Industries Ltd. | E69: =IF(ISNUMBER(MATCH(D69, $A$1:$A$501, 0)), "Present", "Absent") -> Present | F69: Power Grid Corporation of India Ltd. | G69: =IF(ISNUMBER(MATCH(F69, $A$2:$A$501, 0)), "Present", "Absent") -> Present | J69: =IF( (COUNTIF($A$2:$A$501, $B$2:$B$67) > 0) + (COUNTIF($D$2:$D$234, $B$2:$B$67) > 0) + (COUNTIF($F$2:$F$204, $B$2:$B$67) > 0) + (COUNTIF($H$2:$H$33, $B$2:$B$67) > 0) >= 2, "Present", "Absent" ) -> Absent
A70: Bajaj Holdings & Investment Ltd. | D70: Aavas Financiers Ltd. | E70: =IF(ISNUMBER(MATCH(D70, $A$1:$A$501, 0)), "Present", "Absent") -> Present | F70: Indian Hotels Company Limited | G70: =IF(ISNUMBER(MATCH(F70, $A$2:$A$501, 0)), "Present", "Absent") -> Absent | J70: =IF( (COUNTIF($A$2:$A$501, $B$2:$B$67) > 0) + (COUNTIF($D$2:$D$234, $B$2:$B$67) > 0) + (COUNTIF($F$2:$F$204, $B$2:$B$67) > 0) + (COUNTIF($H$2:$H$33, $B$2:$B$67) > 0) >= 2, "Present", "Absent" ) -> Absent
A71: Rail Vikas Nigam Ltd. | D71: ABB Power Products and Systems India Ltd. | E71: =IF(ISNUMBER(MATCH(D71, $A$1:$A$501, 0)), "Present", "Absent") -> Absent | J71: =IF( (COUNTIF($A$2:$A$501, $B$2:$B$67) > 0) + (COUNTIF($D$2:$D$234, $B$2:$B$67) > 0) + (COUNTIF($F$2:$F$204, $B$2:$B$67) > 0) + (COUNTIF($H$2:$H$33, $B$2:$B$67) > 0) >= 2, "Present", "Absent" ) -> Absent
A72: Reliance Industries Ltd. | D72: Acme Solar Holdings Ltd. | E72: =IF(ISNUMBER(MATCH(D72, $A$1:$A$501, 0)), "Present", "Absent") -> Absent | J72: =IF( (COUNTIF($A$2:$A$501, $B$2:$B$67) > 0) + (COUNTIF($D$2:$D$234, $B$2:$B$67) > 0) + (COUNTIF($F$2:$F$204, $B$2:$B$67) > 0) + (COUNTIF($H$2:$H$33, $B$2:$B$67) > 0) >= 2, "Present", "Absent" ) -> Absent
A73: Kirloskar Oil Engines Ltd. | D73: Adani Wilmar Ltd. | E73: =IF(ISNUMBER(MATCH(D73, $A$1:$A$501, 0)), "Present", "Absent") -> Present | J73: =IF( (COUNTIF($A$2:$A$501, $B$2:$B$67) > 0) + (COUNTIF($D$2:$D$234, $B$2:$B$67) > 0) + (COUNTIF($F$2:$F$204, $B$2:$B$67) > 0) + (COUNTIF($H$2:$H$33, $B$2:$B$67) > 0) >= 2, "Present", "Absent" ) -> Absent
A74: Bank of Baroda | D74: Aditya Birla Fashion and Retail Ltd. | E74: =IF(ISNUMBER(MATCH(D74, $A$1:$A$501, 0)), "Present", "Absent") -> Present | J74: =IF( (COUNTIF($A$2:$A$501, $B$2:$B$67) > 0) + (COUNTIF($D$2:$D$234, $B$2:$B$67) > 0) + (COUNTIF($F$2:$F$204, $B$2:$B$67) > 0) + (COUNTIF($H$2:$H$33, $B$2:$B$67) > 0) >= 2, "Present", "Absent" ) -> Absent
A75: ABB India Ltd. | D75: Aditya Birla Real Estate Ltd. | E75: =IF(ISNUMBER(MATCH(D75, $A$1:$A$501, 0)), "Present", "Absent") -> Present | J75: =IF( (COUNTIF($A$2:$A$501, $B$2:$B$67) > 0) + (COUNTIF($D$2:$D$234, $B$2:$B$67) > 0) + (COUNTIF($F$2:$F$204, $B$2:$B$67) > 0) + (COUNTIF($H$2:$H$33, $B$2:$B$67) > 0) >= 2, "Present", "Absent" ) -> Absent
A76: Welspun Corp Ltd. | D76: Aeroflex Industries Ltd. | E76: =IF(ISNUMBER(MATCH(D76, $A$1:$A$501, 0)), "Present", "Absent") -> Absent | J76: =IF( (COUNTIF($A$2:$A$501, $B$2:$B$67) > 0) + (COUNTIF($D$2:$D$234, $B$2:$B$67) > 0) + (COUNTIF($F$2:$F$204, $B$2:$B$67) > 0) + (COUNTIF($H$2:$H$33, $B$2:$B$67) > 0) >= 2, "Present", "Absent" ) -> Absent
A77: Coal India Ltd. | D77: Affle India Ltd. | E77: =IF(ISNUMBER(MATCH(D77, $A$1:$A$501, 0)), "Present", "Absent") -> Absent | J77: =IF( (COUNTIF($A$2:$A$501, $B$2:$B$67) > 0) + (COUNTIF($D$2:$D$234, $B$2:$B$67) > 0) + (COUNTIF($F$2:$F$204, $B$2:$B$67) > 0) + (COUNTIF($H$2:$H$33, $B$2:$B$67) > 0) >= 2, "Present", "Absent" ) -> Absent
A78: Hindustan Zinc Ltd. | D78: Ajanta Pharma Limited | E78: =IF(ISNUMBER(MATCH(D78, $A$1:$A$501, 0)), "Present", "Absent") -> Absent | J78: =IF( (COUNTIF($A$2:$A$501, $B$2:$B$67) > 0) + (COUNTIF($D$2:$D$234, $B$2:$B$67) > 0) + (COUNTIF($F$2:$F$204, $B$2:$B$67) > 0) + (COUNTIF($H$2:$H$33, $B$2:$B$67) > 0) >= 2, "Present", "Absent" ) -> Absent
A79: Container Corporation of India Ltd. | D79: Apar Industries Ltd. | E79: =IF(ISNUMBER(MATCH(D79, $A$1:$A$501, 0)), "Present", "Absent") -> Present | J79: =IF( (COUNTIF($A$2:$A$501, $B$2:$B$67) > 0) + (COUNTIF($D$2:$D$234, $B$2:$B$67) > 0) + (COUNTIF($F$2:$F$204, $B$2:$B$67) > 0) + (COUNTIF($H$2:$H$33, $B$2:$B$67) > 0) >= 2, "Present", "Absent" ) -> Absent
A80: Signatureglobal (India) Ltd. | D80: Apeejay Surrendra Park Hotels Ltd. | E80: =IF(ISNUMBER(MATCH(D80, $A$1:$A$501, 0)), "Present", "Absent") -> Absent | J80: =IF( (COUNTIF($A$2:$A$501, $B$2:$B$67) > 0) + (COUNTIF($D$2:$D$234, $B$2:$B$67) > 0) + (COUNTIF($F$2:$F$204, $B$2:$B$67) > 0) + (COUNTIF($H$2:$H$33, $B$2:$B$67) > 0) >= 2, "Present", "Absent" ) -> Absent
A81: Deepak Nitrite Ltd. | D81: Archean Chemical Industries Ltd. | E81: =IF(ISNUMBER(MATCH(D81, $A$1:$A$501, 0)), "Present", "Absent") -> Present | J81: =IF( (COUNTIF($A$2:$A$501, $B$2:$B$67) > 0) + (COUNTIF($D$2:$D$234, $B$2:$B$67) > 0) + (COUNTIF($F$2:$F$204, $B$2:$B$67) > 0) + (COUNTIF($H$2:$H$33, $B$2:$B$67) > 0) >= 2, "Present", "Absent" ) -> Absent
A82: Newgen Software Technologies Ltd. | D82: Asian Paints (india) Ltd. | E82: =IF(ISNUMBER(MATCH(D82, $A$1:$A$501, 0)), "Present", "Absent") -> Absent | J82: =IF( (COUNTIF($A$2:$A$501, $B$2:$B$67) > 0) + (COUNTIF($D$2:$D$234, $B$2:$B$67) > 0) + (COUNTIF($F$2:$F$204, $B$2:$B$67) > 0) + (COUNTIF($H$2:$H$33, $B$2:$B$67) > 0) >= 2, "Present", "Absent" ) -> Absent
... A203: Bandhan Bank Ltd. | D203: Sheela Foam Ltd. | E203: =IF(ISNUMBER(MATCH(D203, $A$1:$A$501, 0)), "Present", "Absent") -> Absent | J203: =IF( (COUNTIF($A$2:$A$501, $B$2:$B$67) > 0) + (COUNTIF($D$2:$D$234, $B$2:$B$67) > 0) + (COUNTIF($F$2:$F$204, $B$2:$B$67) > 0) + (COUNTIF($H$2:$H$33, $B$2:$B$67) > 0) >= 2, "Present", "Absent" ) -> Absent
A204: KPR Mill Ltd. | D204: SIS Ltd. | E204: =IF(ISNUMBER(MATCH(D204, $A$1:$A$501, 0)), "Present", "Absent") -> Absent | F204: Hindustan Unilever Ltd. | G204: =IF(ISNUMBER(MATCH(F204, $A$2:$A$501, 0)), "Present", "Absent") -> Present | J204: =IF( (COUNTIF($A$2:$A$501, $B$2:$B$67) > 0) + (COUNTIF($D$2:$D$234, $B$2:$B$67) > 0) + (COUNTIF($F$2:$F$204, $B$2:$B$67) > 0) + (COUNTIF($H$2:$H$33, $B$2:$B$67) > 0) >= 2, "Present", "Absent" ) -> Absent
A205: Tata Communications Ltd. | D205: Stanley Lifestyles Ltd. | E205: =IF(ISNUMBER(MATCH(D205, $A$1:$A$501, 0)), "Present", "Absent") -> Absent | J205: =IF( (COUNTIF($A$2:$A$501, $B$2:$B$67) > 0) + (COUNTIF($D$2:$D$234, $B$2:$B$67) > 0) + (COUNTIF($F$2:$F$204, $B$2:$B$67) > 0) + (COUNTIF($H$2:$H$33, $B$2:$B$67) > 0) >= 2, "Present", "Absent" ) -> Absent
A206: Gujarat State Petronet Ltd. | D206: State Bank Of India | E206: =IF(ISNUMBER(MATCH(D206, $A$1:$A$501, 0)), "Present", "Absent") -> Present | J206: =IF( (COUNTIF($A$2:$A$501, $B$2:$B$67) > 0) + (COUNTIF($D$2:$D$234, $B$2:$B$67) > 0) + (COUNTIF($F$2:$F$204, $B$2:$B$67) > 0) + (COUNTIF($H$2:$H$33, $B$2:$B$67) > 0) >= 2, "Present", "Absent" ) -> Absent
A207: Sun Pharmaceutical Industries Ltd. | D207: Sudarshan Chemical Industries Ltd. | E207: =IF(ISNUMBER(MATCH(D207, $A$1:$A$501, 0)), "Present", "Absent") -> Absent | J207: =IF( (COUNTIF($A$2:$A$501, $B$2:$B$67) > 0) + (COUNTIF($D$2:$D$234, $B$2:$B$67) > 0) + (COUNTIF($F$2:$F$204, $B$2:$B$67) > 0) + (COUNTIF($H$2:$H$33, $B$2:$B$67) > 0) >= 2, "Present", "Absent" ) -> Absent
A208: BASF India Ltd. | D208: Sumitomo Chemical India Private Ltd. | E208: =IF(ISNUMBER(MATCH(D208, $A$1:$A$501, 0)), "Present", "Absent") -> Absent | J208: =IF( (COUNTIF($A$2:$A$501, $B$2:$B$67) > 0) + (COUNTIF($D$2:$D$234, $B$2:$B$67) > 0) + (COUNTIF($F$2:$F$204, $B$2:$B$67) > 0) + (COUNTIF($H$2:$H$33, $B$2:$B$67) > 0) >= 2, "Present", "Absent" ) -> Absent
A209: Balkrishna Industries Ltd. | D209: Sundaram Finance Holdings Ltd. | E209: =IF(ISNUMBER(MATCH(D209, $A$1:$A$501, 0)), "Present", "Absent") -> Absent | J209: =IF( (COUNTIF($A$2:$A$501, $B$2:$B$67) > 0) + (COUNTIF($D$2:$D$234, $B$2:$B$67) > 0) + (COUNTIF($F$2:$F$204, $B$2:$B$67) > 0) + (COUNTIF($H$2:$H$33, $B$2:$B$67) > 0) >= 2, "Present", "Absent" ) -> Absent
A210: ICICI Prudential Life Insurance Company Ltd. | D210: Tata Consumer Products Ltd. | E210: =IF(ISNUMBER(MATCH(D210, $A$1:$A$501, 0)), "Present", "Absent") -> Present | J210: =IF( (COUNTIF($A$2:$A$501, $B$2:$B$67) > 0) + (COUNTIF($D$2:$D$234, $B$2:$B$67) > 0) + (COUNTIF($F$2:$F$204, $B$2:$B$67) > 0) + (COUNTIF($H$2:$H$33, $B$2:$B$67) > 0) >= 2, "Present", "Absent" ) -> Absent
A211: Avanti Feeds Ltd. | D211: Tata Power Co. Ltd. | E211: =IF(ISNUMBER(MATCH(D211, $A$1:$A$501, 0)), "Present", "Absent") -> Absent | J211: =IF( (COUNTIF($A$2:$A$501, $B$2:$B$67) > 0) + (COUNTIF($D$2:$D$234, $B$2:$B$67) > 0) + (COUNTIF($F$2:$F$204, $B$2:$B$67) > 0) + (COUNTIF($H$2:$H$33, $B$2:$B$67) > 0) >= 2, "Present", "Absent" ) -> Absent
A212: JBM Auto Ltd. | D212: TBO TEK Ltd. | E212: =IF(ISNUMBER(MATCH(D212, $A$1:$A$501, 0)), "Present", "Absent") -> Present | J212: =IF( (COUNTIF($A$2:$A$501, $B$2:$B$67) > 0) + (COUNTIF($D$2:$D$234, $B$2:$B$67) > 0) + (COUNTIF($F$2:$F$204, $B$2:$B$67) > 0) + (COUNTIF($H$2:$H$33, $B$2:$B$67) > 0) >= 2, "Present", "Absent" ) -> Absent
A213: Kaynes Technology India Ltd. | D213: TD Power Systems Ltd. | E213: =IF(ISNUMBER(MATCH(D213, $A$1:$A$501, 0)), "Present", "Absent") -> Absent | J213: =IF( (COUNTIF($A$2:$A$501, $B$2:$B$67) > 0) + (COUNTIF($D$2:$D$234, $B$2:$B$67) > 0) + (COUNTIF($F$2:$F$204, $B$2:$B$67) > 0) + (COUNTIF($H$2:$H$33, $B$2:$B$67) > 0) >= 2, "Present", "Absent" ) -> Absent
A214: Tata Steel Ltd. | D214: Tejas Networks Ltd. | E214: =IF(ISNUMBER(MATCH(D214, $A$1:$A$501, 0)), "Present", "Absent") -> Present | J214: =IF( (COUNTIF($A$2:$A$501, $B$2:$B$67) > 0) + (COUNTIF($D$2:$D$234, $B$2:$B$67) > 0) + (COUNTIF($F$2:$F$204, $B$2:$B$67) > 0) + (COUNTIF($H$2:$H$33, $B$2:$B$67) > 0) >= 2, "Present", "Absent" ) -> Absent
A215: Eicher Motors Ltd. | D215: Texmaco Rail & Engineering Ltd. | E215: =IF(ISNUMBER(MATCH(D215, $A$1:$A$501, 0)), "Present", "Absent") -> Absent | J215: =IF( (COUNTIF($A$2:$A$501, $B$2:$B$67) > 0) + (COUNTIF($D$2:$D$234, $B$2:$B$67) > 0) + (COUNTIF($F$2:$F$204, $B$2:$B$67) > 0) + (COUNTIF($H$2:$H$33, $B$2:$B$67) > 0) >= 2, "Present", "Absent" ) -> Absent
A216: General Insurance Corporation of India | D216: Thyrocare Technologies Ltd. | E216: =IF(ISNUMBER(MATCH(D216, $A$1:$A$501, 0)), "Present", "Absent") -> Absent | J216: =IF( (COUNTIF($A$2:$A$501, $B$2:$B$67) > 0) + (COUNTIF($D$2:$D$234, $B$2:$B$67) > 0) + (COUNTIF($F$2:$F$204, $B$2:$B$67) > 0) + (COUNTIF($H$2:$H$33, $B$2:$B$67) > 0) >= 2, "Present", "Absent" ) -> Absent
... A234: Hindustan Copper Ltd. | D234: Zydus Wellness Ltd. | E234: =IF(ISNUMBER(MATCH(D234, $A$1:$A$501, 0)), "Present", "Absent") -> Absent | J234: =IF( (COUNTIF($A$2:$A$501, $B$2:$B$67) > 0) + (COUNTIF($D$2:$D$234, $B$2:$B$67) > 0) + (COUNTIF($F$2:$F$204, $B$2:$B$67) > 0) + (COUNTIF($H$2:$H$33, $B$2:$B$67) > 0) >= 2, "Present", "Absent" ) -> Absent
A235: Jammu & Kashmir Bank Ltd. | J235: =IF( (COUNTIF($A$2:$A$501, $B$2:$B$67) > 0) + (COUNTIF($D$2:$D$234, $B$2:$B$67) > 0) + (COUNTIF($F$2:$F$204, $B$2:$B$67) > 0) + (COUNTIF($H$2:$H$33, $B$2:$B$67) > 0) >= 2, "Present", "Absent" ) -> Absent
A236: Affle (India) Ltd. | J236: =IF( (COUNTIF($A$2:$A$501, $B$2:$B$67) > 0) + (COUNTIF($D$2:$D$234, $B$2:$B$67) > 0) + (COUNTIF($F$2:$F$204, $B$2:$B$67) > 0) + (COUNTIF($H$2:$H$33, $B$2:$B$67) > 0) >= 2, "Present", "Absent" ) -> Absent
A237: Honasa Consumer Ltd. | J237: =IF( (COUNTIF($A$2:$A$501, $B$2:$B$67) > 0) + (COUNTIF($D$2:$D$234, $B$2:$B$67) > 0) + (COUNTIF($F$2:$F$204, $B$2:$B$67) > 0) + (COUNTIF($H$2:$H$33, $B$2:$B$67) > 0) >= 2, "Present", "Absent" ) -> Absent
A238: Gujarat State Fertilizer & Chemicals Ltd. | J238: =IF( (COUNTIF($A$2:$A$501, $B$2:$B$67) > 0) + (COUNTIF($D$2:$D$234, $B$2:$B$67) > 0) + (COUNTIF($F$2:$F$204, $B$2:$B$67) > 0) + (COUNTIF($H$2:$H$33, $B$2:$B$67) > 0) >= 2, "Present", "Absent" ) -> Absent
A239: Godrej Agrovet Ltd. | J239: =IF( (COUNTIF($A$2:$A$501, $B$2:$B$67) > 0) + (COUNTIF($D$2:$D$234, $B$2:$B$67) > 0) + (COUNTIF($F$2:$F$204, $B$2:$B$67) > 0) + (COUNTIF($H$2:$H$33, $B$2:$B$67) > 0) >= 2, "Present", "Absent" ) -> Absent
A240: Poonawalla Fincorp Ltd. | J240: =IF( (COUNTIF($A$2:$A$501, $B$2:$B$67) > 0) + (COUNTIF($D$2:$D$234, $B$2:$B$67) > 0) + (COUNTIF($F$2:$F$204, $B$2:$B$67) > 0) + (COUNTIF($H$2:$H$33, $B$2:$B$67) > 0) >= 2, "Present", "Absent" ) -> Absent
A241: Navin Fluorine International Ltd. | J241: =IF( (COUNTIF($A$2:$A$501, $B$2:$B$67) > 0) + (COUNTIF($D$2:$D$234, $B$2:$B$67) > 0) + (COUNTIF($F$2:$F$204, $B$2:$B$67) > 0) + (COUNTIF($H$2:$H$33, $B$2:$B$67) > 0) >= 2, "Present", "Absent" ) -> Absent
A242: Radico Khaitan Ltd. | J242: =IF( (COUNTIF($A$2:$A$501, $B$2:$B$67) > 0) + (COUNTIF($D$2:$D$234, $B$2:$B$67) > 0) + (COUNTIF($F$2:$F$204, $B$2:$B$67) > 0) + (COUNTIF($H$2:$H$33, $B$2:$B$67) > 0) >= 2, "Present", "Absent" ) -> Absent
A243: Adani Enterprises Ltd. | J243: =IF( (COUNTIF($A$2:$A$501, $B$2:$B$67) > 0) + (COUNTIF($D$2:$D$234, $B$2:$B$67) > 0) + (COUNTIF($F$2:$F$204, $B$2:$B$67) > 0) + (COUNTIF($H$2:$H$33, $B$2:$B$67) > 0) >= 2, "Present", "Absent" ) -> Absent
A244: SBI Cards and Payment Services Ltd. | J244: =IF( (COUNTIF($A$2:$A$501, $B$2:$B$67) > 0) + (COUNTIF($D$2:$D$234, $B$2:$B$67) > 0) + (COUNTIF($F$2:$F$204, $B$2:$B$67) > 0) + (COUNTIF($H$2:$H$33, $B$2:$B$67) > 0) >= 2, "Present", "Absent" ) -> Absent
A245: Thermax Ltd. | J245: =IF( (COUNTIF($A$2:$A$501, $B$2:$B$67) > 0) + (COUNTIF($D$2:$D$234, $B$2:$B$67) > 0) + (COUNTIF($F$2:$F$204, $B$2:$B$67) > 0) + (COUNTIF($H$2:$H$33, $B$2:$B$67) > 0) >= 2, "Present", "Absent" ) -> Absent
A246: Himadri Speciality Chemical Ltd. | J246: =IF( (COUNTIF($A$2:$A$501, $B$2:$B$67) > 0) + (COUNTIF($D$2:$D$234, $B$2:$B$67) > 0) + (COUNTIF($F$2:$F$204, $B$2:$B$67) > 0) + (COUNTIF($H$2:$H$33, $B$2:$B$67) > 0) >= 2, "Present", "Absent" ) -> Absent
... A501: Indegene Ltd. | J501: =IF( (COUNTIF($A$2:$A$501, $B$2:$B$67) > 0) + (COUNTIF($D$2:$D$234, $B$2:$B$67) > 0) + (COUNTIF($F$2:$F$204, $B$2:$B$67) > 0) + (COUNTIF($H$2:$H$33, $B$2:$B$67) > 0) >= 2, "Present", "Absent" ) -> Absent
J502: =IF( (COUNTIF($A$2:$A$501, $B$2:$B$67) > 0) + (COUNTIF($D$2:$D$234, $B$2:$B$67) > 0) + (COUNTIF($F$2:$F$204, $B$2:$B$67) > 0) + (COUNTIF($H$2:$H$33, $B$2:$B$67) > 0) >= 2, "Present", "Absent" ) -> Absent
J503: =IF( (COUNTIF($A$2:$A$501, $B$2:$B$67) > 0) + (COUNTIF($D$2:$D$234, $B$2:$B$67) > 0) + (COUNTIF($F$2:$F$204, $B$2:$B$67) > 0) + (COUNTIF($H$2:$H$33, $B$2:$B$67) > 0) >= 2, "Present", "Absent" ) -> Absent
J504: =IF( (COUNTIF($A$2:$A$501, $B$2:$B$67) > 0) + (COUNTIF($D$2:$D$234, $B$2:$B$67) > 0) + (COUNTIF($F$2:$F$204, $B$2:$B$67) > 0) + (COUNTIF($H$2:$H$33, $B$2:$B$67) > 0) >= 2, "Present", "Absent" ) -> Absent
J505: =IF( (COUNTIF($A$2:$A$501, $B$2:$B$67) > 0) + (COUNTIF($D$2:$D$234, $B$2:$B$67) > 0) + (COUNTIF($F$2:$F$204, $B$2:$B$67) > 0) + (COUNTIF($H$2:$H$33, $B$2:$B$67) > 0) >= 2, "Present", "Absent" ) -> Absent
J506: =IF( (COUNTIF($A$2:$A$501, $B$2:$B$67) > 0) + (COUNTIF($D$2:$D$234, $B$2:$B$67) > 0) + (COUNTIF($F$2:$F$204, $B$2:$B$67) > 0) + (COUNTIF($H$2:$H$33, $B$2:$B$67) > 0) >= 2, "Present", "Absent" ) -> Absent

Sheet common co percentage
A1: common co | B1: kotak | C1: nippon | D1: parag | E1: quant | F1: total | K1: =INDEX('[1]common co percentage'!I2:I6, MATCH(SelectedFundCell, '[1]common co percentage'!A2:A6, 0)) -> #NAME?
A2: Dixon Technologies (India) Ltd. | B2: 0.0239 | C2: =VLOOKUP($A2,'nippon holdings'!$A$2:$D$234,4,FALSE) -> 0.0129 | F2: =SUM(B2:E2) -> 0.0368 | G2: =RANK($F2,$F$2:$F$17,1) -> 14 | I2: Dixon Technologies (India) Ltd. | K2: =INDEX(A1:C3, MATCH("kotak", A1:C1, 0), 2) -> 0.0239
A3: Bharat Electronics Ltd. | B3: =VLOOKUP($A3,'kotak holdings'!$A$1:$D$67,4,FALSE) -> 0.0194 | D3: =VLOOKUP($A3,'parag holdings'!$A$1:$D$71,4,FALSE) -> 0.0003 | F3: =SUM(B3:E3) -> 0.0197 | G3: =RANK($F3,$F$2:$F$17,1) -> 3 | I3: Bharat Forge Ltd.
A4: Sundram Fasteners Ltd. | B4: =VLOOKUP($A4,'kotak holdings'!$A$1:$D$67,4,FALSE) -> 0.0059 | C4: =VLOOKUP($A4,'nippon holdings'!$A$2:$D$234,4,FALSE) -> 0.0086 | F4: =SUM(B4:E4) -> 0.0145 | G4: =RANK($F4,$F$2:$F$17,1) -> 1 | I4: Persistent Systems Ltd.
A5: Bharat Forge Ltd. | B5: =VLOOKUP($A5,'kotak holdings'!$A$1:$D$67,4,FALSE) -> 0.0145 | E5: =VLOOKUP($A5,'quant holdings'!$A$1:$D$33,4,FALSE) -> 0.034 | F5: =SUM(B5:E5) -> 0.0485 | G5: =RANK($F5,$F$2:$F$17,1) -> 15 | I5: Ipca Laboratories Ltd.
A6: Persistent Systems Ltd. | B6: =VLOOKUP($A6,'kotak holdings'!$A$1:$D$67,4,FALSE) -> 0.0264 | C6: =VLOOKUP($A6,'nippon holdings'!$A$2:$D$234,4,FALSE) -> 0.0057 | F6: =SUM(B6:E6) -> 0.0321 | G6: =RANK($F6,$F$2:$F$17,1) -> 12 | I6: MRF Ltd.
A7: Schaeffler India Ltd. | B7: =VLOOKUP($A7,'kotak holdings'!$A$1:$D$67,4,FALSE) -> 0.0202 | C7: =VLOOKUP($A7,'nippon holdings'!$A$2:$D$234,4,FALSE) -> 0.0029 | F7: =SUM(B7:E7) -> 0.0231 | G7: =RANK($F7,$F$2:$F$17,1) -> 9
A8: Birlasoft Ltd. | B8: =VLOOKUP($A8,'kotak holdings'!$A$1:$D$67,4,FALSE) -> 0.0195 | C8: =VLOOKUP($A8,'nippon holdings'!$A$2:$D$234,4,FALSE) -> 0.0024 | F8: =SUM(B8:E8) -> 0.0219 | G8: =RANK($F8,$F$2:$F$17,1) -> 5
A9: Apar Industries Ltd. | B9: =VLOOKUP($A9,'kotak holdings'!$A$1:$D$67,4,FALSE) -> 0.0135 | C9: =VLOOKUP($A9,'nippon holdings'!$A$2:$D$234,4,FALSE) -> 0.0103 | F9: =SUM(B9:E9) -> 0.0238 | G9: =RANK($F9,$F$2:$F$17,1) -> 10
A10: Balkrishna Industries Ltd. | B10: =VLOOKUP($A10,'kotak holdings'!$A$1:$D$67,4,FALSE) -> 0.0071 | D10: =VLOOKUP($A10,'parag holdings'!$A$1:$D$71,4,FALSE) -> 0.0125 | F10: =SUM(B10:E10) -> 0.0196 | G10: =RANK($F10,$F$2:$F$17,1) -> 2
A11: Blue Star Ltd. | B11: =VLOOKUP($A11,'kotak holdings'!$A$1:$D$67,4,FALSE) -> 0.0192 | C11: =VLOOKUP($A11,'nippon holdings'!$A$2:$D$234,4,FALSE) -> 0.0076 | F11: =SUM(B11:E11) -> 0.0268 | G11: =RANK($F11,$F$2:$F$17,1) -> 11
A12: Deepak Nitrite Ltd. | B12: =VLOOKUP($A12,'kotak holdings'!$A$1:$D$67,4,FALSE) -> 0.0184 | C12: =VLOOKUP($A12,'nippon holdings'!$A$2:$D$234,4,FALSE) -> 0.004 | F12: =SUM(B12:E12) -> 0.0224 | G12: =RANK($F12,$F$2:$F$17,1) -> 6
A13: Emami Ltd. | B13: =VLOOKUP($A13,'kotak holdings'!$A$1:$D$67,4,FALSE) -> 0.0139 | C13: =VLOOKUP($A13,'nippon holdings'!$A$2:$D$234,4,FALSE) -> 0.0086 | F13: =SUM(B13:E13) -> 0.0225 | G13: =RANK($F13,$F$2:$F$17,1) -> 7
A14: Ipca Laboratories Ltd. | B14: =VLOOKUP($A14,'kotak holdings'!$A$1:$D$67,4,FALSE) -> 0.0323 | D14: =VLOOKUP($A14,'parag holdings'!$A$1:$D$71,4,FALSE) -> 0.003 | E14: =VLOOKUP($A14,'quant holdings'!$A$1:$D$33,4,FALSE) -> 0.0176 | F14: =SUM(B14:E14) -> 0.0529 | G14: =RANK($F14,$F$2:$F$17,1) -> 16
A15: MRF Ltd. | B15: =VLOOKUP($A15,'kotak holdings'!$A$1:$D$67,4,FALSE) -> 0.0098 | E15: =VLOOKUP($A15,'quant holdings'!$A$1:$D$33,4,FALSE) -> 0.0249 | F15: =SUM(B15:E15) -> 0.0347 | G15: =RANK($F15,$F$2:$F$17,1) -> 13
A16: Oil India Ltd. | B16: =VLOOKUP($A16,'kotak holdings'!$A$1:$D$67,4,FALSE) -> 0.013 | E16: =VLOOKUP($A16,'quant holdings'!$A$1:$D$33,4,FALSE) -> 0.0098 | F16: =SUM(B16:E16) -> 0.0228 | G16: =RANK($F16,$F$2:$F$17,1) -> 8
A17: Pi Industries Ltd. | B17: =VLOOKUP($A17,'kotak holdings'!$A$1:$D$67,4,FALSE) -> 0.0201 | D17: =VLOOKUP($A17,'parag holdings'!$A$1:$D$71,4,FALSE) -> 0 | F17: =SUM(B17:E17) -> 0.0201 | G17: =RANK($F17,$F$2:$F$17,1) -> 4
B20: =IF(ISNUMBER(B2), A2, "") -> Dixon Technologies (India) Ltd. | C20: =IF(ISNUMBER(C2), A2, "") -> Dixon Technologies (India) Ltd. | I20: =IF(IsColored(B2), A2, "") -> #NAME?
B21: =IF(ISNUMBER(B3), A3, "") -> Bharat Electronics Ltd. | C21: =IF(ISNUMBER(C3), A3, "")
B22: =IF(ISNUMBER(B4), A4, "") -> Sundram Fasteners Ltd. | C22: =IF(ISNUMBER(C4), A4, "") -> Sundram Fasteners Ltd.
B23: =IF(ISNUMBER(B5), A5, "") -> Bharat Forge Ltd. | C23: =IF(ISNUMBER(C5), A5, "")
B24: =IF(ISNUMBER(B6), A6, "") -> Persistent Systems Ltd. | C24: =IF(ISNUMBER(C6), A6, "") -> Persistent Systems Ltd.
B25: =IF(ISNUMBER(B7), A7, "") -> Schaeffler India Ltd. | C25: =IF(ISNUMBER(C7), A7, "") -> Schaeffler India Ltd.
B26: =IF(ISNUMBER(B8), A8, "") -> Birlasoft Ltd. | C26: =IF(ISNUMBER(C8), A8, "") -> Birlasoft Ltd.
B27: =IF(ISNUMBER(B9), A9, "") -> Apar Industries Ltd. | C27: =IF(ISNUMBER(C9), A9, "") -> Apar Industries Ltd.
B28: =IF(ISNUMBER(B10), A10, "") -> Balkrishna Industries Ltd. | C28: =IF(ISNUMBER(C10), A10, "")
B29: =IF(ISNUMBER(B11), A11, "") -> Blue Star Ltd. | C29: =IF(ISNUMBER(C11), A11, "") -> Blue Star Ltd.
B30: =IF(ISNUMBER(B12), A12, "") -> Deepak Nitrite Ltd. | C30: =IF(ISNUMBER(C12), A12, "") -> Deepak Nitrite Ltd.

Sheet IPCALAB 7-4-23&24,24&25
A1: Date | B1: draw down | C1: peak price so far | D1: close | F1: VOLUME | G1: OPEN | H1: HIGH | I1: LOW | J1: PREV. CLOSE | K1: ltp | M1: vwap | N1: 52W H | O1: 52W L | P1: series | Q1: VALUE | R1: No of trades
A2: 45387 | B2: =(D2 - C2) / C2 -> 0 | C2: =MAX($D$2:D2) -> 1314.55 | D2: 1314.55 | F2: 2753390 | G2: 1289.9 | H2: 1321.6 | I2: 1272.4 | J2: 1276.15 | K2: 1309 | M2: 1305.39 | N2: 1321.6 | O2: 669.8 | P2: EQ | Q2: 3.5942379e+09 | R2: 109506
A3: 45386 | B3: =(D3 - C3) / C3 -> -0.029211517 | C3: =MAX($D$2:D3) -> 1314.55 | D3: 1276.15 | F3: 1879382 | G3: 1230.8 | H3: 1281.95 | I3: 1224 | J3: 1224.35 | K3: 1275 | M3: 1264.12 | N3: 1281.95 | O3: 669.8 | P3: EQ | Q3: 2.375758e+09 | R3: 92164
A4: 45385 | B4: =(D4 - C4) / C4 -> -0.068616637 | C4: =MAX($D$2:D4) -> 1314.55 | D4: 1224.35 | F4: 1653542 | G4: 1240 | H4: 1240 | I4: 1215.85 | J4: 1233.55 | K4: 1225 | M4: 1223.34 | N4: 1263.95 | O4: 669.8 | P4: EQ | Q4: 2.0228469e+09 | R4: 20435
A5: 45384 | B5: =(D5 - C5) / C5 -> -0.061618044 | C5: =MAX($D$2:D5) -> 1314.55 | D5: 1233.55 | F5: 198825 | G5: 1247.6 | H5: 1247.6 | I5: 1225.3 | J5: 1241.05 | K5: 1234.45 | M5: 1236.08 | N5: 1263.95 | O5: 669.8 | P5: EQ | Q5: 2.4576268e+08 | R5: 15880
A6: 45383 | B6: =(D6 - C6) / C6 -> -0.05591267 | C6: =MAX($D$2:D6) -> 1314.55 | D6: 1241.05 | F6: 349243 | G6: 1241 | H6: 1257.45 | I6: 1221.5 | J6: 1237.4 | K6: 1234 | M6: 1240.48 | N6: 1263.95 | O6: 669.8 | P6: EQ | Q6: 4.3322786e+08 | R6: 28323
A7: 45379 | B7: =(D7 - C7) / C7 -> -0.058689285 | C7: =MAX($D$2:D7) -> 1314.55 | D7: 1237.4 | F7: 668011 | G7: 1205.4 | H7: 1245 | I7: 1202.35 | J7: 1205.3 | K7: 1241.1 | M7: 1231.6 | N7: 1263.95 | O7: 669.8 | P7: EQ | Q7: 8.2272351e+08 | R7: 43639
A8: 45378 | B8: =(D8 - C8) / C8 -> -0.083108288 | C8: =MAX($D$2:D8) -> 1314.55 | D8: 1205.3 | F8: 383672 | G8: 1205 | H8: 1220.95 | I8: 1185 | J8: 1200.9 | K8: 1187.6 | M8: 1207.44 | N8: 1263.95 | O8: 669.8 | P8: EQ | Q8: 4.6326236e+08 | R8: 33913
A9: 45377 | B9: =(D9 - C9) / C9 -> -0.086455441 | C9: =MAX($D$2:D9) -> 1314.55 | D9: 1200.9 | F9: 484695 | G9: 1186 | H9: 1219 | I9: 1186 | J9: 1196.05 | K9: 1200.6 | M9: 1208.21 | N9: 1263.95 | O9: 669.8 | P9: EQ | Q9: 5.8561111e+08 | R9: 30473
A10: 45373 | B10: =(D10 - C10) / C10 -> -0.090144917 | C10: =MAX($D$2:D10) -> 1314.55 | D10: 1196.05 | F10: 748972 | G10: 1176.4 | H10: 1209.15 | I10: 1170.2 | J10: 1174.15 | K10: 1194.6 | M10: 1196.82 | N10: 1263.95 | O10: 669.8 | P10: EQ | Q10: 8.9638443e+08 | R10: 44394
A11: 45372 | B11: =(D11 - C11) / C11 -> -0.10680461 | C11: =MAX($D$2:D11) -> 1314.55 | D11: 1174.15 | F11: 309808 | G11: 1172 | H11: 1178.8 | I11: 1140.8 | J11: 1160.95 | K11: 1177.6 | M11: 1162.76 | N11: 1263.95 | O11: 669.8 | P11: EQ | Q11: 3.6023325e+08 | R11: 27551
A12: 45371 | B12: =(D12 - C12) / C12 -> -0.11684607 | C12: =MAX($D$2:D12) -> 1314.55 | D12: 1160.95 | F12: 241592 | G12: 1140.6 | H12: 1167.95 | I12: 1129.15 | J12: 1144.15 | K12: 1156.85 | M12: 1152.56 | N12: 1263.95 | O12: 669.8 | P12: EQ | Q12: 2.7844839e+08 | R12: 18619
A13: 45370 | B13: =(D13 - C13) / C13 -> -0.12962611 | C13: =MAX($D$2:D13) -> 1314.55 | D13: 1144.15 | F13: 191008 | G13: 1161.05 | H13: 1165.05 | I13: 1135.75 | J13: 1165.05 | K13: 1138.05 | M13: 1146.9 | N13: 1263.95 | O13: 669.8 | P13: EQ | Q13: 2.1906697e+08 | R13: 17635
... A249: 45026 | B249: =(D249 - C249) / C249 -> -0.36609486 | C249: =MAX($D$2:D249) -> 1314.55 | D249: 833.3 | F249: 203531 | G249: 830.3 | H249: 843.7 | I249: 825.8 | J249: 830.4 | K249: 834 | M249: 835.46 | N249: 1053.5 | O249: 767.5 | P249: EQ | Q249: 1.7004227e+08 | R249: 17809
A251: Date | D251: close | E251: series | F251: VOLUME | G251: OPEN | H251: HIGH | I251: LOW | J251: PREV. CLOSE | K251: ltp | M251: vwap | N251: 52W H | O251: 52W L | Q251: VALUE | R251: No of trades
A252: 45751 | D252: 1399.25 | E252: EQ | F252: 945827 | G252: 1481 | H252: 1491.75 | I252: 1358.5 | J252: 1497.6 | K252: 1407.55 | M252: 1395.21 | N252: 1755.9 | O252: 1052 | Q252: 1.3196293e+09 | R252: 76133
A253: 45750 | D253: 1497.6 | E253: EQ | F253: 547719 | G253: 1430.95 | H253: 1515.15 | I253: 1430.95 | J253: 1415.95 | K253: 1480.95 | M253: 1481.56 | N253: 1755.9 | O253: 1052 | Q253: 8.114791e+08 | R253: 43073
A254: 45749 | D254: 1415.95 | E254: EQ | F254: 162222 | G254: 1405.95 | H254: 1435.55 | I254: 1386.9 | J254: 1390.85 | K254: 1409 | M254: 1413.68 | N254: 1755.9 | O254: 1052 | Q254: 2.2932978e+08 | R254: 21359
A255: 45748 | D255: 1390.85 | E255: EQ | F255: 424983 | G255: 1493.65 | H255: 1493.95 | I255: 1383.5 | J255: 1501.9 | K255: 1402 | M255: 1410.24 | N255: 1755.9 | O255: 1052 | Q255: 5.9932848e+08 | R255: 45664
A256: 45744 | D256: 1501.9 | E256: EQ | F256: 325369 | G256: 1461.25 | H256: 1510.7 | I256: 1420.5 | J256: 1470.05 | K256: 1508.55 | M256: 1472.52 | N256: 1755.9 | O256: 1052 | Q256: 4.7911168e+08 | R256: 45904
A257: 45743 | D257: 1470.05 | E257: EQ | F257: 169854 | G257: 1404.25 | H257: 1493.95 | I257: 1399.3 | J257: 1433.25 | K257: 1425.25 | M257: 1445.66 | N257: 1755.9 | O257: 1052 | Q257: 2.4555131e+08 | R257: 26806
A258: 45742 | D258: 1433.25 | E258: EQ | F258: 153103 | G258: 1460 | H258: 1464.7 | I258: 1415 | J258: 1446.75 | K258: 1418.65 | M258: 1438.42 | N258: 1755.9 | O258: 1052 | Q258: 2.202261e+08 | R258: 18032
A259: 45741 | D259: 1446.75 | E259: EQ | F259: 227617 | G259: 1464 | H259: 1464 | I259: 1397.2 | J259: 1453 | K259: 1460 | M259: 1426.21 | N259: 1755.9 | O259: 1052 | Q259: 3.2462986e+08 | R259: 32858
A260: 45740 | D260: 1453 | E260: EQ | F260: 164425 | G260: 1420.55 | H260: 1478.9 | I260: 1411 | J260: 1407.05 | K260: 1448.05 | M260: 1444.55 | N260: 1755.9 | O260: 1052 | Q260: 2.3751991e+08 | R260: 25317
A261: 45737 | D261: 1407.05 | E261: EQ | F261: 314521 | G261: 1414 | H261: 1434.3 | I261: 1390.55 | J261: 1402.2 | K261: 1418.8 | M261: 1408.4 | N261: 1755.9 | O261: 1052 | Q261: 4.4297061e+08 | R261: 51685
A262: 45736 | D262: 1402.2 | E262: EQ | F262: 217469 | G262: 1367.05 | H262: 1414.85 | I262: 1357.15 | J262: 1359.3 | K262: 1400.2 | M262: 1397.01 | N262: 1755.9 | O262: 1052 | Q262: 3.038064e+08 | R262: 32391
A263: 45735 | D263: 1359.3 | E263: EQ | F263: 215189 | G263: 1347.05 | H263: 1369 | I263: 1341.95 | J263: 1347.05 | K263: 1350.15 | M263: 1353.74 | N263: 1755.9 | O263: 1052 | Q263: 2.9131088e+08 | R263: 36228
... A499: 45390 | D499: 1294.5 | E499: EQ | F499: 1531611 | G499: 1319.9 | H499: 1338 | I499: 1285 | J499: 1314.55 | K499: 1300 | M499: 1309.49 | N499: 1338 | O499: 669.8 | Q499: 2.0056236e+09 | R499: 41864

Sheet analysis on IPCALAB
A1: IPCA LABORITARIES CO LTD ANALYSIS.
A2: Date | B2: close | C2: OPEN | D2: HIGH | E2: LOW | F2: 20 day sma | G2: percentail | H2: daily return % | I2: Date | J2: close
A3: 45387 | B3: 1314.55 | C3: 1289.9 | D3: 1321.6 | E3: 1272.4 | F3: =SUM(B3:B22)/20 -> 1200.44 | G3: =_xlfn.PERCENTILE.INC(H3:H250,0.05) -> -0.019868891 | H3: =('IPCALAB 7-4-23&24,24&25'!D2-'IPCALAB 7-4-23&24,24&25'!J2)/'IPCALAB 7-4-23&24,24&25'!J2 -> 0.030090507 | I3: 45751 | J3: 1399.25
A4: 45386 | B4: 1276.15 | C4: 1230.8 | D4: 1281.95 | E4: 1224 | F4: =SUM(B4:B23)/20 -> 1194.1975 | G4: =_xlfn.PERCENTILE.INC(H4:H251,0.05) -> -0.01992022 | H4: =('IPCALAB 7-4-23&24,24&25'!D3-'IPCALAB 7-4-23&24,24&25'!J3)/'IPCALAB 7-4-23&24,24&25'!J3 -> 0.042308164 | I4: 45750 | J4: 1497.6
A5: 45385 | B5: 1224.35 | C5: 1240 | D5: 1240 | E5: 1215.85 | F5: =SUM(B5:B24)/20 -> 1190.48 | G5: =_xlfn.PERCENTILE.INC(H5:H252,0.05) -> -0.019971548 | H5: =('IPCALAB 7-4-23&24,24&25'!D4-'IPCALAB 7-4-23&24,24&25'!J4)/'IPCALAB 7-4-23&24,24&25'!J4 -> -0.0074581492 | I5: 45749 | J5: 1415.95
A6: 45384 | B6: 1233.55 | C6: 1247.6 | D6: 1247.6 | E6: 1225.3 | F6: =SUM(B6:B25)/20 -> 1189.21 | G6: =_xlfn.PERCENTILE.INC(H6:H253,0.05) -> -0.020022877 | H6: =('IPCALAB 7-4-23&24,24&25'!D5-'IPCALAB 7-4-23&24,24&25'!J5)/'IPCALAB 7-4-23&24,24&25'!J5 -> -0.0060432698 | I6: 45748 | J6: 1390.85
A7: 45383 | B7: 1241.05 | C7: 1241 | D7: 1257.45 | E7: 1221.5 | F7: =SUM(B7:B26)/20 -> 1187.185 | G7: =_xlfn.PERCENTILE.INC(H7:H254,0.05) -> -0.020074206 | H7: =('IPCALAB 7-4-23&24,24&25'!D6-'IPCALAB 7-4-23&24,24&25'!J6)/'IPCALAB 7-4-23&24,24&25'!J6 -> 0.0029497333 | I7: 45744 | J7: 1501.9
A8: 45379 | B8: 1237.4 | C8: 1205.4 | D8: 1245 | E8: 1202.35 | F8: =SUM(B8:B27)/20 -> 1184.795 | G8: =_xlfn.PERCENTILE.INC(H8:H255,0.05) -> -0.020125535 | H8: =('IPCALAB 7-4-23&24,24&25'!D7-'IPCALAB 7-4-23&24,24&25'!J7)/'IPCALAB 7-4-23&24,24&25'!J7 -> 0.026632374 | I8: 45743 | J8: 1470.05
A9: 45378 | B9: 1205.3 | C9: 1205 | D9: 1220.95 | E9: 1185 | F9: =SUM(B9:B28)/20 -> 1182.34 | G9: =_xlfn.PERCENTILE.INC(H9:H256,0.05) -> -0.020176863 | H9: =('IPCALAB 7-4-23&24,24&25'!D8-'IPCALAB 7-4-23&24,24&25'!J8)/'IPCALAB 7-4-23&24,24&25'!J8 -> 0.0036639187 | I9: 45742 | J9: 1433.25
A10: 45377 | B10: 1200.9 | C10: 1186 | D10: 1219 | E10: 1186 | F10: =SUM(B10:B29)/20 -> 1181.8175 | G10: =_xlfn.PERCENTILE.INC(H10:H257,0.05) -> -0.020228192 | H10: =('IPCALAB 7-4-23&24,24&25'!D9-'IPCALAB 7-4-23&24,24&25'!J9)/'IPCALAB 7-4-23&24,24&25'!J9 -> 0.0040550144 | I10: 45741 | J10: 1446.75
A11: 45373 | B11: 1196.05 | C11: 1176.4 | D11: 1209.15 | E11: 1170.2 | F11: =SUM(B11:B30)/20 -> 1182.4975 | G11: =_xlfn.PERCENTILE.INC(H11:H258,0.05) -> -0.020275808 | H11: =('IPCALAB 7-4-23&24,24&25'!D10-'IPCALAB 7-4-23&24,24&25'!J10)/'IPCALAB 7-4-23&24,24&25'!J10 -> 0.018651791 | I11: 45740 | J11: 1453
A12: 45372 | B12: 1174.15 | C12: 1172 | D12: 1178.8 | E12: 1140.8 | F12: =SUM(B12:B31)/20 -> 1183.58 | G12: =_xlfn.PERCENTILE.INC(H12:H259,0.05) -> -0.020323425 | H12: =('IPCALAB 7-4-23&24,24&25'!D11-'IPCALAB 7-4-23&24,24&25'!J11)/'IPCALAB 7-4-23&24,24&25'!J11 -> 0.011369999 | I12: 45737 | J12: 1407.05
A13: 45371 | B13: 1160.95 | C13: 1140.6 | D13: 1167.95 | E13: 1129.15 | F13: =SUM(B13:B32)/20 -> 1186.4075 | G13: =_xlfn.PERCENTILE.INC(H13:H260,0.05) -> -0.020371041 | H13: =('IPCALAB 7-4-23&24,24&25'!D12-'IPCALAB 7-4-23&24,24&25'!J12)/'IPCALAB 7-4-23&24,24&25'!J12 -> 0.014683389 | I13: 45736 | J13: 1402.2
A14: 45370 | B14: 1144.15 | C14: 1161.05 | D14: 1165.05 | E14: 1135.75 | F14: =SUM(B14:B33)/20 -> 1189.3775 | G14: =_xlfn.PERCENTILE.INC(H14:H261,0.05) -> -0.020418657 | H14: =('IPCALAB 7-4-23&24,24&25'!D13-'IPCALAB 7-4-23&24,24&25'!J13)/'IPCALAB 7-4-23&24,24&25'!J13 -> -0.017939144 | I14: 45735 | J14: 1359.3
... A32: 45344 | B32: 1230.7 | C32: 1225 | D32: 1236 | E32: 1213.35 | F32: =SUM(B32:B51)/20 -> 1173.265 | G32: =_xlfn.PERCENTILE.INC(H32:H279,0.05) -> -0.020323425 | H32: =('IPCALAB 7-4-23&24,24&25'!D31-'IPCALAB 7-4-23&24,24&25'!J31)/'IPCALAB 7-4-23&24,24&25'!J31 -> 0.0084811734 | I32: 45707 | J32: 1467.85
A33: 45343 | B33: 1220.35 | C33: 1240 | D33: 1246.85 | E33: 1213.3 | F33: =SUM(B33:B52)/20 -> 1166.6525 | G33: =_xlfn.PERCENTILE.INC(H33:H280,0.05) -> -0.020371041 | H33: =('IPCALAB 7-4-23&24,24&25'!D32-'IPCALAB 7-4-23&24,24&25'!J32)/'IPCALAB 7-4-23&24,24&25'!J32 -> -0.012182289 | I33: 45706 | J33: 1473.05 | T33: gains and losses are almost equal so less risk.
A34: 45342 | B34: 1235.4 | C34: 1241.45 | D34: 1249.35 | E34: 1208.2 | F34: =SUM(B34:B53)/20 -> 1159.735 | G34: =_xlfn.PERCENTILE.INC(H34:H281,0.05) -> -0.020418657 | H34: =('IPCALAB 7-4-23&24,24&25'!D33-'IPCALAB 7-4-23&24,24&25'!J33)/'IPCALAB 7-4-23&24,24&25'!J33 -> -0.00044500182 | I34: 45705 | J34: 1476.75
A35: 45341 | B35: 1235.95 | C35: 1248.05 | D35: 1260.55 | E35: 1225.4 | F35: =SUM(B35:B54)/20 -> 1151.85 | G35: =_xlfn.PERCENTILE.INC(H35:H282,0.05) -> -0.020466274 | H35: =('IPCALAB 7-4-23&24,24&25'!D34-'IPCALAB 7-4-23&24,24&25'!J34)/'IPCALAB 7-4-23&24,24&25'!J34 -> -0.0044303033 | I35: 45702 | J35: 1463.9
A36: 45338 | B36: 1241.45 | C36: 1155.8 | D36: 1247.55 | E36: 1155 | F36: =SUM(B36:B55)/20 -> 1145.05 | G36: =_xlfn.PERCENTILE.INC(H36:H283,0.05) -> -0.02051389 | H36: =('IPCALAB 7-4-23&24,24&25'!D35-'IPCALAB 7-4-23&24,24&25'!J35)/'IPCALAB 7-4-23&24,24&25'!J35 -> 0.077320259 | I36: 45701 | J36: 1490.9
A37: 45337 | B37: 1152.35 | C37: 1164.5 | D37: 1192 | E37: 1145 | F37: =SUM(B37:B56)/20 -> 1137.0475 | G37: =_xlfn.PERCENTILE.INC(H37:H284,0.05) -> -0.020561506 | H37: =('IPCALAB 7-4-23&24,24&25'!D36-'IPCALAB 7-4-23&24,24&25'!J36)/'IPCALAB 7-4-23&24,24&25'!J36 -> -0.0020351606 | I37: 45700 | J37: 1419.8
A38: 45336 | B38: 1154.7 | C38: 1144 | D38: 1207.5 | E38: 1134.05 | F38: =SUM(B38:B57)/20 -> 1135.605 | G38: =_xlfn.PERCENTILE.INC(H38:H285,0.05) -> -0.020609123 | H38: =('IPCALAB 7-4-23&24,24&25'!D37-'IPCALAB 7-4-23&24,24&25'!J37)/'IPCALAB 7-4-23&24,24&25'!J37 -> -0.0051264378 | I38: 45699 | J38: 1419.9
A39: 45335 | B39: 1160.65 | C39: 1182.35 | D39: 1182.35 | E39: 1146.85 | F39: =SUM(B39:B58)/20 -> 1134.5975 | G39: =_xlfn.PERCENTILE.INC(H39:H286,0.05) -> -0.020656739 | H39: =('IPCALAB 7-4-23&24,24&25'!D38-'IPCALAB 7-4-23&24,24&25'!J38)/'IPCALAB 7-4-23&24,24&25'!J38 -> -0.0064629344 | I39: 45698 | J39: 1447.95
A40: 45334 | B40: 1168.2 | C40: 1198.9 | D40: 1201.9 | E40: 1151.35 | F40: =SUM(B40:B59)/20 -> 1133.5425 | G40: =_xlfn.PERCENTILE.INC(H40:H287,0.05) -> -0.020704355 | H40: =('IPCALAB 7-4-23&24,24&25'!D39-'IPCALAB 7-4-23&24,24&25'!J39)/'IPCALAB 7-4-23&24,24&25'!J39 -> -0.022917364 | I40: 45695 | J40: 1507.25
A41: 45331 | B41: 1195.6 | C41: 1219.8 | D41: 1224 | E41: 1190 | F41: =SUM(B41:B60)/20 -> 1131.9 | G41: =_xlfn.PERCENTILE.INC(H41:H288,0.05) -> -0.019766233 | H41: =('IPCALAB 7-4-23&24,24&25'!D40-'IPCALAB 7-4-23&24,24&25'!J40)/'IPCALAB 7-4-23&24,24&25'!J40 -> -0.016574131 | I41: 45694 | J41: 1514.9
A42: 45330 | B42: 1215.75 | C42: 1230 | D42: 1263.95 | E42: 1210 | F42: =SUM(B42:B61)/20 -> 1129.3375 | G42: =_xlfn.PERCENTILE.INC(H42:H289,0.05) -> -0.019817562 | H42: =('IPCALAB 7-4-23&24,24&25'!D41-'IPCALAB 7-4-23&24,24&25'!J41)/'IPCALAB 7-4-23&24,24&25'!J41 -> -0.0079559364 | I42: 45693 | J42: 1491.45
A43: 45329 | B43: 1225.5 | C43: 1204 | D43: 1232.35 | E43: 1192.85 | F43: =SUM(B43:B62)/20 -> 1124.3625 | G43: =_xlfn.PERCENTILE.INC(H43:H290,0.05) -> -0.019868891 | H43: =('IPCALAB 7-4-23&24,24&25'!D42-'IPCALAB 7-4-23&24,24&25'!J42)/'IPCALAB 7-4-23&24,24&25'!J42 -> 0.021973898 | I43: 45692 | J43: 1468.05
A44: 45328 | B44: 1199.15 | C44: 1134.35 | D44: 1203.95 | E44: 1134.35 | F44: =SUM(B44:B63)/20 -> 1118.24 | G44: =_xlfn.PERCENTILE.INC(H44:H291,0.05) -> -0.01992022 | H44: =('IPCALAB 7-4-23&24,24&25'!D43-'IPCALAB 7-4-23&24,24&25'!J43)/'IPCALAB 7-4-23&24,24&25'!J43 -> 0.057125226 | I44: 45691 | J44: 1428.6
A45: 45327 | B45: 1134.35 | C45: 1110 | D45: 1146.5 | E45: 1103.2 | F45: =SUM(B45:B64)/20 -> 1112.6875 | G45: =_xlfn.PERCENTILE.INC(H45:H292,0.05) -> -0.019971548 | H45: =('IPCALAB 7-4-23&24,24&25'!D44-'IPCALAB 7-4-23&24,24&25'!J44)/'IPCALAB 7-4-23&24,24&25'!J44 -> 0.023089064 | I45: 45689 | J45: 1417.35
... A48: 45322 | B48: 1120.25 | C48: 1103.5 | D48: 1129.2 | E48: 1102.9 | F48: =SUM(B48:B67)/20 -> 1111.485 | G48: =_xlfn.PERCENTILE.INC(H48:H295,0.05) -> -0.020125535 | H48: =('IPCALAB 7-4-23&24,24&25'!D47-'IPCALAB 7-4-23&24,24&25'!J47)/'IPCALAB 7-4-23&24,24&25'!J47 -> 0.014995017 | I48: 45686 | J48: 1443.3
A49: 45321 | B49: 1103.7 | C49: 1134.9 | D49: 1141 | E49: 1098.1 | F49: =SUM(B49:B68)/20 -> 1111.14 | G49: =_xlfn.PERCENTILE.INC(H49:H296,0.05) -> -0.020176863 | H49: =('IPCALAB 7-4-23&24,24&25'!D48-'IPCALAB 7-4-23&24,24&25'!J48)/'IPCALAB 7-4-23&24,24&25'!J48 -> -0.025516511 | I49: 45685 | J49: 1382.75 | T49: here lower volume the price is increasing so low trend must be cautious of investment.
A50: 45320 | B50: 1132.6 | C50: 1116.25 | D50: 1135.05 | E50: 1111 | F50: =SUM(B50:B69)/20 -> 1111.9225 | G50: =_xlfn.PERCENTILE.INC(H50:H297,0.05) -> -0.019201617 | H50: =('IPCALAB 7-4-23&24,24&25'!D49-'IPCALAB 7-4-23&24,24&25'!J49)/'IPCALAB 7-4-23&24,24&25'!J49 -> 0.015374961 | I50: 45684 | J50: 1442.55
A51: 45316 | B51: 1115.45 | C51: 1093 | D51: 1120.85 | E51: 1079.2 | F51: =SUM(B51:B70)/20 -> 1110.95 | G51: =_xlfn.PERCENTILE.INC(H51:H298,0.05) -> -0.019252946 | H51: =('IPCALAB 7-4-23&24,24&25'!D50-'IPCALAB 7-4-23&24,24&25'!J50)/'IPCALAB 7-4-23&24,24&25'!J50 -> 0.015476353 | I51: 45681 | J51: 1515.85
A52: 45315 | B52: 1098.45 | C52: 1065 | D52: 1109 | E52: 1062.15 | F52: =SUM(B52:B71)/20 -> 1110.165 | G52: =_xlfn.PERCENTILE.INC(H52:H299,0.05) -> -0.019304274 | H52: =('IPCALAB 7-4-23&24,24&25'!D51-'IPCALAB 7-4-23&24,24&25'!J51)/'IPCALAB 7-4-23&24,24&25'!J51 -> 0.015203327 | I52: 45680 | J52: 1583.55
A53: 45314 | B53: 1082 | C53: 1075 | D53: 1093.25 | E53: 1061.05 | F53: =SUM(B53:B72)/20 -> 1108.195 | G53: =_xlfn.PERCENTILE.INC(H53:H300,0.05) -> -0.019355603 | H53: =('IPCALAB 7-4-23&24,24&25'!D52-'IPCALAB 7-4-23&24,24&25'!J52)/'IPCALAB 7-4-23&24,24&25'!J52 -> 0.0039899787 | I53: 45679 | J53: 1559.25
A54: 45311 | B54: 1077.7 | C54: 1100 | D54: 1107.5 | E54: 1072 | F54: =SUM(B54:B73)/20 -> 1107.025 | G54: =_xlfn.PERCENTILE.INC(H54:H301,0.05) -> -0.019406932 | H54: =('IPCALAB 7-4-23&24,24&25'!D53-'IPCALAB 7-4-23&24,24&25'!J53)/'IPCALAB 7-4-23&24,24&25'!J53 -> -0.020228192 | I54: 45678 | J54: 1545.8
A55: 45310 | B55: 1099.95 | C55: 1080.8 | D55: 1105 | E55: 1075.9 | F55: =SUM(B55:B74)/20 -> 1106.2725 | G55: =_xlfn.PERCENTILE.INC(H55:H302,0.05) -> -0.018883934 | H55: =('IPCALAB 7-4-23&24,24&25'!D54-'IPCALAB 7-4-23&24,24&25'!J54)/'IPCALAB 7-4-23&24,24&25'!J54 -> 0.01715369 | I55: 45677 | J55: 1547.1
A56: 45309 | B56: 1081.4 | C56: 1120 | D56: 1123.5 | E56: 1062.4 | F56: =SUM(B56:B75)/20 -> 1104.4925 | G56: =_xlfn.PERCENTILE.INC(H56:H303,0.05) -> -0.018905113 | H56: =('IPCALAB 7-4-23&24,24&25'!D55-'IPCALAB 7-4-23&24,24&25'!J55)/'IPCALAB 7-4-23&24,24&25'!J55 -> -0.037472185 | I56: 45674 | J56: 1543.25
A57: 45308 | B57: 1123.5 | C57: 1130 | D57: 1136.25 | E57: 1112.2 | F57: =SUM(B57:B76)/20 -> 1103.4975 | G57: =_xlfn.PERCENTILE.INC(H57:H304,0.05) -> -0.018400299 | H57: =('IPCALAB 7-4-23&24,24&25'!D56-'IPCALAB 7-4-23&24,24&25'!J56)/'IPCALAB 7-4-23&24,24&25'!J56 -> -0.0097395443 | I57: 45673 | J57: 1550.3
A58: 45307 | B58: 1134.55 | C58: 1140 | D58: 1140.95 | E58: 1121.8 | F58: =SUM(B58:B77)/20 -> 1102.705 | G58: =_xlfn.PERCENTILE.INC(H58:H305,0.05) -> -0.018429356 | H58: =('IPCALAB 7-4-23&24,24&25'!D57-'IPCALAB 7-4-23&24,24&25'!J57)/'IPCALAB 7-4-23&24,24&25'!J57 -> -0.0043876969 | I58: 45672 | J58: 1565.55
A59: 45306 | B59: 1139.55 | C59: 1138.75 | D59: 1147.55 | E59: 1133 | F59: =SUM(B59:B78)/20 -> 1102.205 | G59: =_xlfn.PERCENTILE.INC(H59:H306,0.05) -> -0.018458413 | H59: =('IPCALAB 7-4-23&24,24&25'!D58-'IPCALAB 7-4-23&24,24&25'!J58)/'IPCALAB 7-4-23&24,24&25'!J58 -> 0.0036992998 | I59: 45671 | J59: 1588.15
A60: 45303 | B60: 1135.35 | C60: 1156 | D60: 1156 | E60: 1128.45 | F60: =SUM(B60:B79)/20 -> 1100.945 | G60: =_xlfn.PERCENTILE.INC(H60:H307,0.05) -> -0.01848747 | H60: =('IPCALAB 7-4-23&24,24&25'!D59-'IPCALAB 7-4-23&24,24&25'!J59)/'IPCALAB 7-4-23&24,24&25'!J59 -> -0.0078647267 | I60: 45670 | J60: 1579.65
A61: 45302 | B61: 1144.35 | C61: 1125 | D61: 1148.8 | E61: 1119.1 | F61: =SUM(B61:B80)/20 -> 1099.3975 | G61: =_xlfn.PERCENTILE.INC(H61:H308,0.05) -> -0.018516527 | H61: =('IPCALAB 7-4-23&24,24&25'!D60-'IPCALAB 7-4-23&24,24&25'!J60)/'IPCALAB 7-4-23&24,24&25'!J60 -> 0.025173572 | I61: 45667 | J61: 1632.35
... A250: 45026 | B250: 833.3 | C250: 830.3 | D250: 843.7 | E250: 825.8 | F250: =SUM(B250:B269)/20 -> 41.665 | G250: =_xlfn.PERCENTILE.INC(H250:H497,0.05) -> 0.0034922929 | H250: =('IPCALAB 7-4-23&24,24&25'!D249-'IPCALAB 7-4-23&24,24&25'!J249)/'IPCALAB 7-4-23&24,24&25'!J249 -> 0.0034922929 | I250: 45390 | J250: 1294.5

Sheet BHARATFOR 7424-25&23-24
A1: Date | B1: close | C1: OPEN | D1: HIGH | E1: LOW | F1: PREV. CLOSE | G1: ltp | I1: vwap | J1: 52W H | K1: 52W L | L1: VOLUME | M1: VALUE | N1: No of trades
A2: 45387 | B2: 1145.65 | C2: 1149.95 | D2: 1154.9 | E2: 1136 | F2: 1151.35 | G2: 1146.8 | I2: 1143.54 | J2: 1330 | K2: 743.55 | L2: 838396 | M2: 9.5873553e+08 | N2: 40711
A3: 45386 | B3: 1151.35 | C3: 1152.5 | D3: 1172.5 | E3: 1139.25 | F3: 1141.75 | G3: 1155 | I3: 1154.95 | J3: 1330 | K3: 743.55 | L3: 2867983 | M3: 3.3123655e+09 | N3: 72390
A4: 45385 | B4: 1141.75 | C4: 1125 | D4: 1144.1 | E4: 1105.3 | F4: 1155.35 | G4: 1143.95 | I4: 1136.99 | J4: 1330 | K4: 743.55 | L4: 1586014 | M4: 1.8032755e+09 | N4: 59377
A5: 45384 | B5: 1155.35 | C5: 1159.9 | D5: 1159.9 | E5: 1135.15 | F5: 1148.6 | G5: 1156.5 | I5: 1151.76 | J5: 1330 | K5: 743.55 | L5: 713289 | M5: 821536171 | N5: 38521
A6: 45383 | B6: 1148.6 | C6: 1132.2 | D6: 1153.4 | E6: 1121 | F6: 1129.6 | G6: 1147.95 | I6: 1145.02 | J6: 1330 | K6: 743.55 | L6: 1247843 | M6: 1.4288052e+09 | N6: 57433
A7: 45379 | B7: 1129.6 | C7: 1114.95 | D7: 1135.2 | E7: 1103.5 | F7: 1111.2 | G7: 1129.5 | I7: 1121.52 | J7: 1330 | K7: 743.55 | L7: 1391471 | M7: 1.5605557e+09 | N7: 68011
A8: 45378 | B8: 1111.2 | C8: 1132.4 | D8: 1143.05 | E8: 1107.25 | F8: 1130.15 | G8: 1112.4 | I8: 1124.95 | J8: 1330 | K8: 743.55 | L8: 1811541 | M8: 2.0379008e+09 | N8: 79901
A9: 45377 | B9: 1130.15 | C9: 1131.9 | D9: 1140.95 | E9: 1127 | F9: 1128.95 | G9: 1132.5 | I9: 1132.69 | J9: 1330 | K9: 743.55 | L9: 728614 | M9: 8.2529221e+08 | N9: 32778
A10: 45373 | B10: 1128.95 | C10: 1102 | D10: 1133.6 | E10: 1101.3 | F10: 1102 | G10: 1131.75 | I10: 1123.52 | J10: 1330 | K10: 743.55 | L10: 1129996 | M10: 1.2695699e+09 | N10: 67472
A11: 45372 | B11: 1102 | C11: 1097.8 | D11: 1122 | E11: 1094 | F11: 1092.7 | G11: 1100.2 | I11: 1102.92 | J11: 1330 | K11: 743.55 | L11: 2400850 | M11: 2.6479484e+09 | N11: 71231
A12: 45371 | B12: 1092.7 | C12: 1110 | D12: 1118.6 | E12: 1088 | F12: 1112.7 | G12: 1093 | I12: 1098.58 | J12: 1330 | K12: 743.55 | L12: 1044847 | M12: 1.1478515e+09 | N12: 45692
A13: 45370 | B13: 1112.7 | C13: 1111.75 | D13: 1133 | E13: 1093.6 | F13: 1114.4 | G13: 1116 | I13: 1109.84 | J13: 1330 | K13: 743.55 | L13: 830859 | M13: 9.2211839e+08 | N13: 29848
... A18: 45363 | B18: 1155.85 | C18: 1160.05 | D18: 1170.9 | E18: 1139 | F18: 1159.85 | G18: 1154.6 | I18: 1149.83 | J18: 1330 | K18: 743.55 | L18: 942567 | M18: 1.0837896e+09 | N18: 39226
A19: 45362 | B19: 1159.85 | C19: 1170.05 | D19: 1190.6 | E19: 1143.4 | F19: 1178.85 | G19: 1156.75 | I19: 1162.02 | J19: 1330 | K19: 743.55 | L19: 2315091 | M19: 2.6901847e+09 | N19: 128283 | P19: =INDEX(#REF!, 2, 3) -> #REF!
A20: 45358 | B20: 1178.85 | C20: 1181.65 | D20: 1193.6 | E20: 1170.35 | F20: 1181.75 | G20: 1170.9 | I20: 1182.45 | J20: 1330 | K20: 743.55 | L20: 557070 | M20: 6.5870525e+08 | N20: 40303
A21: 45357 | B21: 1181.75 | C21: 1189 | D21: 1190.75 | E21: 1150.1 | F21: 1185.8 | G21: 1183 | I21: 1170.79 | J21: 1330 | K21: 743.55 | L21: 674420 | M21: 7.8960188e+08 | N21: 32962
A22: 45356 | B22: 1185.8 | C22: 1190 | D22: 1211 | E22: 1179.95 | F22: 1189.15 | G22: 1187 | I22: 1195.71 | J22: 1330 | K22: 743.55 | L22: 1251169 | M22: 1.496032e+09 | N22: 46896
A23: 45355 | B23: 1189.15 | C23: 1182 | D23: 1193.7 | E23: 1170 | F23: 1179.65 | G23: 1191 | I23: 1184.6 | J23: 1330 | K23: 743.55 | L23: 1806324 | M23: 2.1397669e+09 | N23: 83790
A24: 45353 | B24: 1179.65 | C24: 1186.55 | D24: 1194.9 | E24: 1171.05 | F24: 1184.25 | G24: 1182 | I24: 1178.65 | J24: 1330 | K24: 743.55 | L24: 60824 | M24: 71690181 | N24: 4177
A25: 45352 | B25: 1184.25 | C25: 1150.05 | D25: 1187.9 | E25: 1150.05 | F25: 1151 | G25: 1185 | I25: 1171.33 | J25: 1330 | K25: 743.55 | L25: 740159 | M25: 8.6697247e+08 | N25: 40351
A26: 45351 | B26: 1151 | C26: 1145 | D26: 1158 | E26: 1135.8 | F26: 1152.25 | G26: 1148.4 | I26: 1147.47 | J26: 1330 | K26: 743.55 | L26: 1187019 | M26: 1362069416 | N26: 43754
A27: 45350 | B27: 1152.25 | C27: 1175.75 | D27: 1181.55 | E27: 1141.15 | F27: 1177.95 | G27: 1150 | I27: 1157.31 | J27: 1330 | K27: 743.55 | L27: 770303 | M27: 8.914801e+08 | N27: 34062
A28: 45349 | B28: 1177.95 | C28: 1173.9 | D28: 1195.2 | E28: 1169.8 | F28: 1175.6 | G28: 1179 | I28: 1182.79 | J28: 1330 | K28: 743.55 | L28: 1178342 | M28: 1.3937307e+09 | N28: 67566
A29: 45348 | B29: 1175.6 | C29: 1132.1 | D29: 1181.85 | E29: 1119.4 | F29: 1132.1 | G29: 1172 | I29: 1154.59 | J29: 1330 | K29: 743.55 | L29: 3694478 | M29: 4.2656106e+09 | N29: 150064
A30: 45345 | B30: 1132.1 | C30: 1133.05 | D30: 1145.55 | E30: 1125 | F30: 1133.05 | G30: 1130 | I30: 1136.79 | J30: 1330 | K30: 743.55 | L30: 443601 | M30: 5.042831e+08 | N30: 24652
A31: 45344 | B31: 1133.05 | C31: 1123.4 | D31: 1135.5 | E31: 1109.4 | F31: 1123.3 | G31: 1130.85 | I31: 1125.49 | J31: 1330 | K31: 743.55 | L31: 508795 | M31: 5.7264331e+08 | N31: 29893
... A249: 45026 | B249: 756.45 | C249: 762.9 | D249: 762.9 | E249: 743.55 | F249: 762.4 | G249: 756.65 | I249: 752.06 | J249: 919.45 | K249: 597 | L249: 1153620 | M249: 8.6759666e+08 | N249: 41721
A251: Date | B251: close | C251: OPEN | D251: HIGH | E251: LOW | F251: PREV. CLOSE | G251: ltp | I251: vwap | J251: 52W H | K251: 52W L | L251: VOLUME | M251: VALUE | N251: No of trades
A252: 45754 | B252: 951.6 | C252: 925 | D252: 959.85 | E252: 919.1 | F252: 1026.05 | G252: 958.75 | I252: 937.18 | J252: 1804.5 | K252: 919.1 | L252: 3849870 | M252: 3.6080173e+09 | N252: 123195
A253: 45751 | B253: 1026.05 | C253: 1097 | D253: 1100 | E253: 1014 | F253: 1117.1 | G253: 1029 | I253: 1036.61 | J253: 1804.5 | K253: 1002.15 | L253: 4793116 | M253: 4.9686022e+09 | N253: 135692
A254: 45750 | B254: 1117.1 | C254: 1130 | D254: 1135.8 | E254: 1082.55 | F254: 1152.95 | G254: 1115.1 | I254: 1120.6 | J254: 1804.5 | K254: 1002.15 | L254: 2078500 | M254: 2.3291729e+09 | N254: 62214
A255: 45749 | B255: 1152.95 | C255: 1154 | D255: 1167.4 | E255: 1138.5 | F255: 1148.65 | G255: 1154 | I255: 1158.24 | J255: 1804.5 | K255: 1002.15 | L255: 1275536 | M255: 1.4773777e+09 | N255: 35361
A256: 45748 | B256: 1148.65 | C256: 1160 | D256: 1179 | E256: 1144.05 | F256: 1169.15 | G256: 1149.95 | I256: 1160.53 | J256: 1804.5 | K256: 1002.15 | L256: 900487 | M256: 1.045038e+09 | N256: 37797
A257: 45744 | B257: 1169.15 | C257: 1174.45 | D257: 1181.55 | E257: 1154 | F257: 1159.15 | G257: 1159.45 | I257: 1170.44 | J257: 1804.5 | K257: 1002.15 | L257: 2164434 | M257: 2.5333444e+09 | N257: 70073
A258: 45743 | B258: 1159.15 | C258: 1182 | D258: 1199 | E258: 1129.85 | F258: 1182.9 | G258: 1155.4 | I258: 1163.6 | J258: 1804.5 | K258: 1002.15 | L258: 5362970 | M258: 6.2403389e+09 | N258: 137342
A259: 45742 | B259: 1182.9 | C259: 1186.25 | D259: 1202.2 | E259: 1178 | F259: 1186.25 | G259: 1183 | I259: 1186.92 | J259: 1804.5 | K259: 1002.15 | L259: 812349 | M259: 9.6419437e+08 | N259: 37575
A260: 45741 | B260: 1186.25 | C260: 1207 | D260: 1210 | E260: 1170.55 | F260: 1201.4 | G260: 1183.6 | I260: 1186.3 | J260: 1804.5 | K260: 1002.15 | L260: 1298776 | M260: 1540742090 | N260: 47413
A261: 45740 | B261: 1201.4 | C261: 1185 | D261: 1206.6 | E261: 1185 | F261: 1181.3 | G261: 1199.1 | I261: 1201.07 | J261: 1804.5 | K261: 1002.15 | L261: 1330920 | M261: 1.5985238e+09 | N261: 56317
A262: 45737 | B262: 1181.3 | C262: 1207 | D262: 1207.3 | E262: 1169.2 | F262: 1194.3 | G262: 1182 | I262: 1181.39 | J262: 1804.5 | K262: 1002.15 | L262: 2395430 | M262: 2.8299345e+09 | N262: 81183
A263: 45736 | B263: 1194.3 | C263: 1147 | D263: 1202 | E263: 1147 | F263: 1136 | G263: 1191.5 | I263: 1181.98 | J263: 1804.5 | K263: 1002.15 | L263: 2766980 | M263: 3.2705239e+09 | N263: 79114
... A500: 45390 | B500: 1173.9 | C500: 1152.95 | D500: 1180 | E500: 1136 | F500: 1145.65 | G500: 1175.05 | I500: 1165.79 | J500: 1330 | K500: 743.55 | L500: 2521920 | M500: 2.9400223e+09 | N500: 96463

Sheet DIXON7423-24&24-25
A1: Date | B1: series | C1: OPEN | D1: HIGH | E1: LOW | F1: PREV. CLOSE | G1: ltp | H1: close | I1: vwap | J1: 52W H | K1: 52W L | L1: VOLUME | M1: VALUE | N1: No of trades
A2: 45387 | B2: EQ | C2: 7650 | D2: 7755 | E2: 7619.4 | F2: 7628.25 | G2: 7690 | H2: 7660.5 | I2: 7683.63 | J2: 7950 | K2: 2820 | L2: 322191 | M2: 2.4755976e+09 | N2: 52366
A3: 45386 | B3: EQ | C3: 7700 | D3: 7746.8 | E3: 7599.3 | F3: 7699.45 | G3: 7635 | H3: 7628.25 | I3: 7651.16 | J3: 7950 | K3: 2820 | L3: 253626 | M3: 1.9405327e+09 | N3: 30103
A4: 45385 | B4: EQ | C4: 7920 | D4: 7922.5 | E4: 7680.35 | F4: 7915.5 | G4: 7700 | H4: 7699.45 | I4: 7769.8 | J4: 7950 | K4: 2820 | L4: 412950 | M4: 3.2085385e+09 | N4: 55958
A5: 45384 | B5: EQ | C5: 7579.9 | D5: 7950 | E5: 7554.15 | F5: 7592.05 | G5: 7920 | H5: 7915.5 | I5: 7798.54 | J5: 7950 | K5: 2820 | L5: 482981 | M5: 3.7665452e+09 | N5: 52008
A6: 45383 | B6: EQ | C6: 7520 | D6: 7626.9 | E6: 7480.05 | F6: 7479.25 | G6: 7592.55 | H6: 7592.05 | I6: 7576.82 | J6: 7626.9 | K6: 2820 | L6: 256567 | M6: 1.9439616e+09 | N6: 36222
A7: 45379 | B7: EQ | C7: 7486.35 | D7: 7580 | E7: 7431.45 | F7: 7424.2 | G7: 7474 | H7: 7479.25 | I7: 7489.32 | J7: 7580 | K7: 2754.05 | L7: 251091 | M7: 1.8805009e+09 | N7: 34737
A8: 45378 | B8: EQ | C8: 7255 | D8: 7470 | E8: 7255 | F8: 7245.65 | G8: 7430 | H8: 7424.2 | I8: 7385.16 | J8: 7470 | K8: 2754.05 | L8: 340520 | M8: 2.5147953e+09 | N8: 41677
A9: 45377 | B9: EQ | C9: 7157 | D9: 7286.35 | E9: 7108.7 | F9: 7165.15 | G9: 7251 | H9: 7245.65 | I9: 7211.46 | J9: 7286.35 | K9: 2754.05 | L9: 181186 | M9: 1.3066147e+09 | N9: 24241
A10: 45373 | B10: EQ | C10: 7040 | D10: 7189.85 | E10: 7027 | F10: 7067.75 | G10: 7158 | H10: 7165.15 | I10: 7119.63 | J10: 7236 | K10: 2754.05 | L10: 227094 | M10: 1.6168259e+09 | N10: 28959
A11: 45372 | B11: EQ | C11: 7049.95 | D11: 7079 | E11: 6932.9 | F11: 6952.3 | G11: 7070 | H11: 7067.75 | I11: 7020.31 | J11: 7236 | K11: 2754.05 | L11: 225768 | M11: 1.5849611e+09 | N11: 27499
A12: 45371 | B12: EQ | C12: 6954 | D12: 7008.95 | E12: 6839.1 | F12: 6946.65 | G12: 6962 | H12: 6952.3 | I12: 6925.29 | J12: 7236 | K12: 2754.05 | L12: 199618 | M12: 1.3824127e+09 | N12: 30958
A13: 45370 | B13: EQ | C13: 7045.95 | D13: 7060 | E13: 6920 | F13: 7022.05 | G13: 6950 | H13: 6946.65 | I13: 6967.78 | J13: 7236 | K13: 2754.05 | L13: 193387 | M13: 1.3474772e+09 | N13: 24965
... A249: 45026 | B249: EQ | C249: 2885.2 | D249: 2990 | E249: 2870.05 | F249: 2887.45 | G249: 2980 | H249: 2977.05 | I249: 2947.1 | J249: 4670 | K249: 2553 | L249: 321718 | M249: 9.4813373e+08 | N249: 22617
A251: Date | B251: series | C251: OPEN | D251: HIGH | E251: LOW | F251: PREV. CLOSE | G251: ltp | H251: close | I251: vwap | J251: 52W H | K251: 52W L | L251: VOLUME | M251: VALUE | N251: No of trades
A252: 45754 | B252: EQ | C252: 12202.2 | D252: 12897 | E252: 12202.2 | F252: 13137.55 | G252: 12635 | H252: 12556.05 | I252: 12579.76 | J252: 19148.9 | K252: 7198.35 | L252: 466181 | M252: 5.8644459e+09 | N252: 96321
A253: 45751 | B253: EQ | C253: 13450.05 | D253: 13472.75 | E253: 13038 | F253: 13487.95 | G253: 13153.95 | H253: 13137.55 | I253: 13172.77 | J253: 19148.9 | K253: 7198.35 | L253: 279276 | M253: 3.6788381e+09 | N253: 54693
A254: 45750 | B254: EQ | C254: 13303.2 | D254: 13567.45 | E254: 13095 | F254: 13450.7 | G254: 13470 | H254: 13487.95 | I254: 13353.3 | J254: 19148.9 | K254: 7198.35 | L254: 343363 | M254: 4585028763 | N254: 68070
A255: 45749 | B255: EQ | C255: 12950 | D255: 13485 | E255: 12899.75 | F255: 12923.9 | G255: 13435 | H255: 13450.7 | I255: 13249.28 | J255: 19148.9 | K255: 7198.35 | L255: 390817 | M255: 5.1780423e+09 | N255: 76492
A256: 45748 | B256: EQ | C256: 13199 | D256: 13450 | E256: 12880 | F256: 13179.5 | G256: 12924.8 | H256: 12923.9 | I256: 13117.53 | J256: 19148.9 | K256: 7198.35 | L256: 305230 | M256: 4.0038634e+09 | N256: 70073
A257: 45744 | B257: EQ | C257: 13516 | D257: 13680.8 | E257: 13009.4 | F257: 13510.8 | G257: 13175 | H257: 13179.5 | I257: 13306.85 | J257: 19148.9 | K257: 7108.7 | L257: 430635 | M257: 5730394296 | N257: 80778
A258: 45743 | B258: EQ | C258: 13300 | D258: 13673.95 | E258: 13100 | F258: 13260.4 | G258: 13470 | H258: 13510.8 | I258: 13491.3 | J258: 19148.9 | K258: 7108.7 | L258: 538219 | M258: 7.2612755e+09 | N258: 80751
A259: 45742 | B259: EQ | C259: 13651.05 | D259: 13691.05 | E259: 13216 | F259: 13624.5 | G259: 13260.05 | H259: 13260.4 | I259: 13416.86 | J259: 19148.9 | K259: 7108.7 | L259: 452537 | M259: 6.0716236e+09 | N259: 90096
A260: 45741 | B260: EQ | C260: 14676.65 | D260: 14740 | E260: 13495 | F260: 14608.35 | G260: 13568 | H260: 13624.5 | I260: 13906.69 | J260: 19148.9 | K260: 7108.7 | L260: 835339 | M260: 1.1616802e+10 | N260: 125845
A261: 45740 | B261: EQ | C261: 14122 | D261: 14720 | E261: 14121 | F261: 14056.8 | G261: 14600 | H261: 14608.35 | I261: 14503.97 | J261: 19148.9 | K261: 7108.7 | L261: 284541 | M261: 4.1269742e+09 | N261: 59137
A262: 45737 | B262: EQ | C262: 13880 | D262: 14122.95 | E262: 13834.45 | F262: 13905.7 | G262: 14025.4 | H262: 14056.8 | I262: 14040.01 | J262: 19148.9 | K262: 6839.1 | L262: 256973 | M262: 3.6079023e+09 | N262: 48887
A263: 45736 | B263: EQ | C263: 13875.6 | D263: 14085 | E263: 13754.3 | F263: 13875.6 | G263: 13880 | H263: 13905.7 | I263: 13927.12 | J263: 19148.9 | K263: 6839.1 | L263: 211223 | M263: 2.9417279e+09 | N263: 46187
... A500: 45390 | B500: EQ | C500: 7682.05 | D500: 7749.95 | E500: 7615.1 | F500: 7660.5 | G500: 7640 | H500: 7635.3 | I500: 7670.03 | J500: 7950 | K500: 2820 | L500: 216902 | M500: 1.6636455e+09 | N500: 26462

Sheet -MRF-7423-24&24-25
A1: Date | B1: series | C1: OPEN | D1: HIGH | E1: LOW | F1: PREV. CLOSE | G1: ltp | H1: close | I1: vwap | J1: 52W H | K1: 52W L | L1: VOLUME | M1: VALUE | N1: No of trades
A2: 45387 | B2: EQ | C2: 135690 | D2: 136100 | E2: 134500 | F2: 135360.95 | G2: 135627.65 | H2: 135464.6 | I2: 135369.18 | J2: 151445 | K2: 83325.75 | L2: 6537 | M2: 8.8490836e+08 | N2: 4681
A3: 45386 | B3: EQ | C3: 136398 | D3: 137117.25 | E3: 135101 | F3: 136190.7 | G3: 135400 | H3: 135360.95 | I3: 136081.96 | J3: 151445 | K3: 83325.75 | L3: 5388 | M3: 7.332096e+08 | N3: 4169
A4: 45385 | B4: EQ | C4: 137199 | D4: 137554.95 | E4: 136000 | F4: 137092.8 | G4: 136010 | H4: 136190.7 | I4: 136662.47 | J4: 151445 | K4: 83325.75 | L4: 6928 | M4: 9.4679761e+08 | N4: 4894
A5: 45384 | B5: EQ | C5: 136300 | D5: 137489.95 | E5: 134906.7 | F5: 135719.35 | G5: 137199.95 | H5: 137092.8 | I5: 136199.53 | J5: 151445 | K5: 83325.75 | L5: 7756 | M5: 1.0563635e+09 | N5: 5633
A6: 45383 | B6: EQ | C6: 135995 | D6: 136989.9 | E6: 134555.05 | F6: 133387.35 | G6: 135800 | H6: 135719.35 | I6: 135517.4 | J6: 151445 | K6: 83325.75 | L6: 12671 | M6: 1.7171409e+09 | N6: 9800
A7: 45379 | B7: EQ | C7: 132889 | D7: 134000 | E7: 132000.5 | F7: 131809.4 | G7: 133923 | H7: 133387.35 | I7: 133098.61 | J7: 151445 | K7: 81786.5 | L7: 10442 | M7: 1.3898157e+09 | N7: 7062
A8: 45378 | B8: EQ | C8: 132000 | D8: 133843.9 | E8: 131264 | F8: 131645.4 | G8: 131500 | H8: 131809.4 | I8: 132418.47 | J8: 151445 | K8: 81786.5 | L8: 7985 | M8: 1.0573615e+09 | N8: 5549
A9: 45377 | B9: EQ | C9: 131995 | D9: 132317.35 | E9: 130700.05 | F9: 131302.95 | G9: 131600 | H9: 131645.4 | I9: 131567.23 | J9: 151445 | K9: 81786.5 | L9: 7707 | M9: 1.0139887e+09 | N9: 5393
A10: 45373 | B10: EQ | C10: 131700 | D10: 132749.9 | E10: 130500 | F10: 131583.6 | G10: 131400 | H10: 131302.95 | I10: 131251.68 | J10: 151445 | K10: 81786.5 | L10: 11040 | M10: 1.4490185e+09 | N10: 7831
A11: 45372 | B11: EQ | C11: 132022 | D11: 132969.9 | E11: 131045.55 | F11: 131512.65 | G11: 131700 | H11: 131583.6 | I11: 131907.72 | J11: 151445 | K11: 81786.5 | L11: 10316 | M11: 1.3607601e+09 | N11: 6945
A12: 45371 | B12: EQ | C12: 132680.05 | D12: 134039.05 | E12: 129614.6 | F12: 132679.75 | G12: 131230.9 | H12: 131512.65 | I12: 131786.09 | J12: 151445 | K12: 81786.5 | L12: 14354 | M12: 1.8916575e+09 | N12: 10981
A13: 45370 | B13: EQ | C13: 136990 | D13: 136990 | E13: 132150.15 | F13: 137012.75 | G13: 132469 | H13: 132679.75 | I13: 133950.73 | J13: 151445 | K13: 81786.5 | L13: 13171 | M13: 1.764265e+09 | N13: 8598
... A249: 45026 | B249: EQ | C249: 83750 | D249: 84780 | E249: 83750 | F249: 84005.55 | G249: 84537.25 | H249: 84398.45 | I249: 84338.48 | J249: 96000 | K249: 65800 | L249: 3582 | M249: 3.0210043e+08 | N249: 2123
A251: Date | B251: series | C251: OPEN | D251: HIGH | E251: LOW | F251: PREV. CLOSE | G251: ltp | H251: close | I251: vwap | J251: 52W H | K251: 52W L | L251: VOLUME | M251: VALUE | N251: No of trades
A252: 45754 | B252: EQ | C252: 110000 | D252: 110821.5 | E252: 108001 | F252: 113236.95 | G252: 110665.95 | H252: 110385.5 | I252: 109833.24 | J252: 143849.9 | K252: 102124.05 | L252: 7098 | M252: 7.7959635e+08 | N252: 5043
A253: 45751 | B253: EQ | C253: 115000 | D253: 115000 | E253: 112800 | F253: 114870.45 | G253: 113280.25 | H253: 113236.95 | I253: 113408.39 | J253: 143849.9 | K253: 102124.05 | L253: 4440 | M253: 5.0353323e+08 | N253: 3260
A254: 45750 | B254: EQ | C254: 114500 | D254: 115000 | E254: 113800 | F254: 115137.35 | G254: 114877.7 | H254: 114870.45 | I254: 114499.88 | J254: 143849.9 | K254: 102124.05 | L254: 3272 | M254: 374643593 | N254: 2613
A255: 45749 | B255: EQ | C255: 113400.05 | D255: 115275.8 | E255: 112774.3 | F255: 113037.05 | G255: 114919 | H255: 115137.35 | I255: 114379.13 | J255: 143849.9 | K255: 102124.05 | L255: 5030 | M255: 5.75327e+08 | N255: 3815
A256: 45748 | B256: EQ | C256: 112500 | D256: 114411.65 | E256: 111900 | F256: 112677.75 | G256: 113077.75 | H256: 113037.05 | I256: 113253.04 | J256: 143849.9 | K256: 102124.05 | L256: 3593 | M256: 4.0691816e+08 | N256: 2862
A257: 45744 | B257: EQ | C257: 113800 | D257: 114397 | E257: 112084.35 | F257: 113264.05 | G257: 112500.25 | H257: 112677.75 | I257: 112937.96 | J257: 143849.9 | K257: 102124.05 | L257: 7320 | M257: 8.2670587e+08 | N257: 5233
A258: 45743 | B258: EQ | C258: 114003 | D258: 114200 | E258: 112445 | F258: 114321.2 | G258: 113939.7 | H258: 113264.05 | I258: 113188.28 | J258: 143849.9 | K258: 102124.05 | L258: 10576 | M258: 1.1970793e+09 | N258: 7707
A259: 45742 | B259: EQ | C259: 114126.5 | D259: 115500 | E259: 113900.1 | F259: 114264.5 | G259: 114008.7 | H259: 114321.2 | I259: 114844.44 | J259: 143849.9 | K259: 102124.05 | L259: 5979 | M259: 6.8665489e+08 | N259: 4284
A260: 45741 | B260: EQ | C260: 115925 | D260: 116000 | E260: 113509.85 | F260: 114020.8 | G260: 114115 | H260: 114264.5 | I260: 114610.7 | J260: 143849.9 | K260: 102124.05 | L260: 8037 | M260: 9.2112621e+08 | N260: 5495
A261: 45740 | B261: EQ | C261: 112990 | D261: 114300 | E261: 112651.3 | F261: 112050.15 | G261: 114150 | H261: 114020.8 | I261: 113907.54 | J261: 143849.9 | K261: 102124.05 | L261: 5731 | M261: 6.5280409e+08 | N261: 4028
A262: 45737 | B262: EQ | C262: 111440 | D262: 112799.95 | E262: 111042.45 | F262: 111107.9 | G262: 112100 | H262: 112050.15 | I262: 112131.46 | J262: 143849.9 | K262: 102124.05 | L262: 8367 | M262: 9.3820389e+08 | N262: 5828
A263: 45736 | B263: EQ | C263: 110500 | D263: 111450 | E263: 110161.15 | F263: 109922.8 | G263: 111230 | H263: 111107.9 | I263: 110951.56 | J263: 143849.9 | K263: 102124.05 | L263: 5687 | M263: 6.3098151e+08 | N263: 3631
... A500: 45390 | B500: EQ | C500: 134807 | D500: 135799 | E500: 130775.25 | F500: 135464.6 | G500: 132920 | H500: 132708.45 | I500: 133115.83 | J500: 151445 | K500: 83750 | L500: 15744 | M500: 2095775688 | N500: 10443

Sheet PERSISTENT 23-24&24-25
A1: Date | B1: series | C1: OPEN | D1: HIGH | E1: LOW | F1: PREV. CLOSE | G1: ltp | H1: close | I1: vwap | J1: 52W H | K1: 52W L | L1: VOLUME | M1: VALUE | N1: No of trades
A2: 45387 | B2: EQ | C2: 4045 | D2: 4046 | E2: 3970 | F2: 4029.5 | G2: 3993.75 | H2: 3996.75 | I2: 3991.84 | J2: 8900 | K2: 3931.25 | L2: 324838 | M2: 1.2967016e+09 | N2: 43603
A3: 45386 | B3: EQ | C3: 4028 | D3: 4085.05 | E3: 3977.4 | F3: 3972.9 | G3: 4035 | H3: 4029.5 | I3: 4026.34 | J3: 8900 | K3: 3931.25 | L3: 856395 | M3: 3.4481364e+09 | N3: 57162
A4: 45385 | B4: EQ | C4: 3970.2 | D4: 3994.85 | E4: 3931.25 | F4: 3970.25 | G4: 3962 | H4: 3972.9 | I4: 3973.76 | J4: 8900 | K4: 3931.25 | L4: 610324 | M4: 2.4252783e+09 | N4: 47940
A5: 45384 | B5: EQ | C5: 3989 | D5: 3989 | E5: 3951.1 | F5: 3996.65 | G5: 3962.7 | H5: 3970.25 | I5: 3970.05 | J5: 8900 | K5: 3932 | L5: 296000 | M5: 1.1751342e+09 | N5: 43939
A6: 45383 | B6: EQ | C6: 4069.9 | D6: 4076.4 | E6: 3932 | F6: 3984.55 | G6: 3990.05 | H6: 3996.65 | I6: 3984.54 | J6: 8900 | K6: 3932 | L6: 841783 | M6: 3.3541169e+09 | N6: 74448
A7: 45379 | B7: EQ | C7: 4069 | D7: 4096.65 | E7: 3947.45 | F7: 8099.65 | G7: 3985 | H7: 3984.55 | I7: 4009.79 | J7: 8900 | K7: 3947.45 | L7: 747068 | M7: 2.9955887e+09 | N7: 79802
A8: 45378 | B8: EQ | C8: 8100 | D8: 8128 | E8: 8020 | F8: 8074.8 | G8: 8092 | H8: 8099.65 | I8: 8093.7 | J8: 8900 | K8: 3962.05 | L8: 222658 | M8: 1.802127e+09 | N8: 28720
A9: 45377 | B9: EQ | C9: 7995 | D9: 8128.85 | E9: 7955.3 | F9: 7971.4 | G9: 8070 | H9: 8074.8 | I9: 8075.43 | J9: 8900 | K9: 3962.05 | L9: 300936 | M9: 2.4301879e+09 | N9: 34919
A10: 45373 | B10: EQ | C10: 7979.95 | D10: 8085 | E10: 7862 | F10: 8204.85 | G10: 7995 | H10: 7971.4 | I10: 7978.25 | J10: 8900 | K10: 3962.05 | L10: 516790 | M10: 4.1230797e+09 | N10: 62626
A11: 45372 | B11: EQ | C11: 8054.95 | D11: 8248.7 | E11: 8054.95 | F11: 8002.45 | G11: 8200.5 | H11: 8204.85 | I11: 8169.1 | J11: 8900 | K11: 3962.05 | L11: 273190 | M11: 2.2317169e+09 | N11: 40658
A12: 45371 | B12: EQ | C12: 7982.95 | D12: 8052 | E12: 7911 | F12: 7979.45 | G12: 8000 | H12: 8002.45 | I12: 7999.52 | J12: 8900 | K12: 3962.05 | L12: 176468 | M12: 1.4116599e+09 | N12: 30179
A13: 45370 | B13: EQ | C13: 8140 | D13: 8140 | E13: 7945 | F13: 8179.35 | G13: 7973.25 | H13: 7979.45 | I13: 8010.78 | J13: 8900 | K13: 3962.05 | L13: 281428 | M13: 2.2544586e+09 | N13: 38838
... A249: 45026 | B249: EQ | C249: 4548 | D249: 4583.5 | E249: 4491 | F249: 4547.3 | G249: 4568 | H249: 4569.75 | I249: 4542.26 | J249: 5135 | K249: 3092.05 | L249: 132523 | M249: 6.0195393e+08 | N249: 18994
A251: Date | B251: series | C251: OPEN | D251: HIGH | E251: LOW | F251: PREV. CLOSE | G251: ltp | H251: close | I251: vwap | J251: 52W H | K251: 52W L | L251: VOLUME | M251: VALUE | N251: No of trades
A252: 45754 | B252: EQ | C252: 4148.95 | D252: 4630 | E252: 4148.95 | F252: 4609.95 | G252: 4623 | H252: 4573.55 | I252: 4440.73 | J252: 6788.9 | K252: 3232.05 | L252: 1802134 | M252: 8.0027823e+09 | N252: 207401
A253: 45751 | B253: EQ | C253: 4750 | D253: 4772.35 | E253: 4498.6 | F253: 4793.35 | G253: 4667.5 | H253: 4609.95 | I253: 4594.32 | J253: 6788.9 | K253: 3232.05 | L253: 2694235 | M253: 1.2378173e+10 | N253: 195005
A254: 45750 | B254: EQ | C254: 5120.4 | D254: 5145 | E254: 4771.55 | F254: 5317.5 | G254: 4799 | H254: 4793.35 | I254: 4849.86 | J254: 6788.9 | K254: 3232.05 | L254: 2581937 | M254: 1.2522037e+10 | N254: 259723
A255: 45749 | B255: EQ | C255: 5253.65 | D255: 5411.95 | E255: 5218.75 | F255: 5211.55 | G255: 5324 | H255: 5317.5 | I255: 5303.08 | J255: 6788.9 | K255: 3232.05 | L255: 525175 | M255: 2.7850438e+09 | N255: 76247
A256: 45748 | B256: EQ | C256: 5494 | D256: 5509.65 | E256: 5189.8 | F256: 5513.75 | G256: 5237.95 | H256: 5211.55 | I256: 5290.55 | J256: 6788.9 | K256: 3232.05 | L256: 453706 | M256: 2.4003544e+09 | N256: 68118
A257: 45744 | B257: EQ | C257: 5665 | D257: 5700.45 | E257: 5466.5 | F257: 5641.45 | G257: 5483.85 | H257: 5513.75 | I257: 5580.54 | J257: 8128.85 | K257: 3232.05 | L257: 317428 | M257: 1.7714182e+09 | N257: 38497
A258: 45743 | B258: EQ | C258: 5440.6 | D258: 5669 | E258: 5440.6 | F258: 5517 | G258: 5657.7 | H258: 5641.45 | I258: 5613.18 | J258: 8128.85 | K258: 3232.05 | L258: 593246 | M258: 3.3299989e+09 | N258: 80649
A259: 45742 | B259: EQ | C259: 5574 | D259: 5623.6 | E259: 5477.8 | F259: 5558.3 | G259: 5490 | H259: 5517 | I259: 5562.05 | J259: 8128.85 | K259: 3232.05 | L259: 416614 | M259: 2.3172298e+09 | N259: 71064
A260: 45741 | B260: EQ | C260: 5499 | D260: 5633 | E260: 5435.15 | F260: 5421.3 | G260: 5561.6 | H260: 5558.3 | I260: 5539.59 | J260: 8128.85 | K260: 3232.05 | L260: 827076 | M260: 4.5816616e+09 | N260: 109832
A261: 45740 | B261: EQ | C261: 5306 | D261: 5508.4 | E261: 5232.25 | F261: 5275.55 | G261: 5418.15 | H261: 5421.3 | I261: 5407.23 | J261: 8128.85 | K261: 3232.05 | L261: 569197 | M261: 3.0777782e+09 | N261: 63024
A262: 45737 | B262: EQ | C262: 5104.65 | D262: 5323 | E262: 5028.2 | F262: 5194.05 | G262: 5278.15 | H262: 5275.55 | I262: 5246.62 | J262: 8422.4 | K262: 3232.05 | L262: 789021 | M262: 4.139694e+09 | N262: 75847
A263: 45736 | B263: EQ | C263: 5340 | D263: 5385 | E263: 5184.6 | F263: 5280.6 | G263: 5188 | H263: 5194.05 | I263: 5269.61 | J263: 8422.4 | K263: 3232.05 | L263: 621056 | M263: 3.2727242e+09 | N263: 63681
... A500: 45390 | B500: EQ | C500: 4005.95 | D500: 4010.8 | E500: 3731.65 | F500: 3996.75 | G500: 3875 | H500: 3903.8 | I500: 3913.45 | J500: 8900 | K500: 3731.65 | L500: 764262 | M500: 2.9909038e+09 | N500: 72246

Sheet data sheet
B1: ='dash board'!H5 -> Ipca Laboratories Ltd.
A2: date | B2: close | C2: HIGH | D2: LOW | E2: OPEN | F2: volume
A3: 45387 | B3: =IF('dash board'!$H$5="Dixon Technologies (India) Ltd.",'DIXON7423-24&24-25'!H2,IF('dash board'!$H$5="Bharat Forge Ltd.",'BHARATFOR 7424-25&23-24'!B2,IF('dash board'!$H$5="Persistent Systems Ltd.",'PERSISTENT 23-24&24-25'!H2,IF('dash board'!$H$5="Ipca Laboratories Ltd.",'IPCALAB 7-4-23&24,24&25'!D2,IF('dash board'!$H$5="MRF Ltd.",'-MRF-7423-24&24-25'!H2,""))))) -> 1314.55 | C3: =IF('dash board'!$H$5="Dixon Technologies (India) Ltd.",'DIXON7423-24&24-25'!D2,IF('dash board'!$H$5="Bharat Forge Ltd.",'BHARATFOR 7424-25&23-24'!D2,IF('dash board'!$H$5="Persistent Systems Ltd.",'PERSISTENT 23-24&24-25'!D2,IF('dash board'!$H$5="Ipca Laboratories Ltd.",'IPCALAB 7-4-23&24,24&25'!H2,IF('dash board'!$H$5="MRF Ltd.",'-MRF-7423-24&24-25'!D2,""))))) -> 1321.6 | D3: =IF('dash board'!$H$5="Dixon Technologies (India) Ltd.",'DIXON7423-24&24-25'!E2,IF('dash board'!$H$5="Bharat Forge Ltd.",'BHARATFOR 7424-25&23-24'!E2,IF('dash board'!$H$5="Persistent Systems Ltd.",'PERSISTENT 23-24&24-25'!E2,IF('dash board'!$H$5="Ipca Laboratories Ltd.",'IPCALAB 7-4-23&24,24&25'!I2,IF('dash board'!$H$5="MRF Ltd.",'-MRF-7423-24&24-25'!E2,""))))) -> 1272.4 | E3: =IF('dash board'!$H$5="Dixon Technologies (India) Ltd.",'DIXON7423-24&24-25'!C2,IF('dash board'!$H$5="Bharat Forge Ltd.",'BHARATFOR 7424-25&23-24'!C2,IF('dash board'!$H$5="Persistent Systems Ltd.",'PERSISTENT 23-24&24-25'!C2,IF('dash board'!$H$5="Ipca Laboratories Ltd.",'IPCALAB 7-4-23&24,24&25'!G2,IF('dash board'!$H$5="MRF Ltd.",'-MRF-7423-24&24-25'!C2,""))))) -> 1289.9 | F3: =IF('dash board'!$H$5="Dixon Technologies (India) Ltd.",'DIXON7423-24&24-25'!L2,IF('dash board'!$H$5="Bharat Forge Ltd.",'BHARATFOR 7424-25&23-24'!L2,IF('dash board'!$H$5="Persistent Systems Ltd.",'PERSISTENT 23-24&24-25'!L2,IF('dash board'!$H$5="Ipca Laboratories Ltd.",'IPCALAB 7-4-23&24,24&25'!F2,IF('dash board'!$H$5="MRF Ltd.",'-MRF-7423-24&24-25'!L2,""))))) -> 2753390
A4: 45386 | B4: =IF('dash board'!$H$5="Dixon Technologies (India) Ltd.",'DIXON7423-24&24-25'!H3,IF('dash board'!$H$5="Bharat Forge Ltd.",'BHARATFOR 7424-25&23-24'!B3,IF('dash board'!$H$5="Persistent Systems Ltd.",'PERSISTENT 23-24&24-25'!H3,IF('dash board'!$H$5="Ipca Laboratories Ltd.",'IPCALAB 7-4-23&24,24&25'!D3,IF('dash board'!$H$5="MRF Ltd.",'-MRF-7423-24&24-25'!H3,""))))) -> 1276.15 | C4: =IF('dash board'!$H$5="Dixon Technologies (India) Ltd.",'DIXON7423-24&24-25'!D3,IF('dash board'!$H$5="Bharat Forge Ltd.",'BHARATFOR 7424-25&23-24'!D3,IF('dash board'!$H$5="Persistent Systems Ltd.",'PERSISTENT 23-24&24-25'!D3,IF('dash board'!$H$5="Ipca Laboratories Ltd.",'IPCALAB 7-4-23&24,24&25'!H3,IF('dash board'!$H$5="MRF Ltd.",'-MRF-7423-24&24-25'!D3,""))))) -> 1281.95 | D4: =IF('dash board'!$H$5="Dixon Technologies (India) Ltd.",'DIXON7423-24&24-25'!E3,IF('dash board'!$H$5="Bharat Forge Ltd.",'BHARATFOR 7424-25&23-24'!E3,IF('dash board'!$H$5="Persistent Systems Ltd.",'PERSISTENT 23-24&24-25'!E3,IF('dash board'!$H$5="Ipca Laboratories Ltd.",'IPCALAB 7-4-23&24,24&25'!I3,IF('dash board'!$H$5="MRF Ltd.",'-MRF-7423-24&24-25'!E3,""))))) -> 1224 | E4: =IF('dash board'!$H$5="Dixon Technologies (India) Ltd.",'DIXON7423-24&24-25'!C3,IF('dash board'!$H$5="Bharat Forge Ltd.",'BHARATFOR 7424-25&23-24'!C3,IF('dash board'!$H$5="Persistent Systems Ltd.",'PERSISTENT 23-24&24-25'!C3,IF('dash board'!$H$5="Ipca Laboratories Ltd.",'IPCALAB 7-4-23&24,24&25'!G3,IF('dash board'!$H$5="MRF Ltd.",'-MRF-7423-24&24-25'!C3,""))))) -> 1230.8 | F4: =IF('dash board'!$H$5="Dixon Technologies (India) Ltd.",'DIXON7423-24&24-25'!L3,IF('dash board'!$H$5="Bharat Forge Ltd.",'BHARATFOR 7424-25&23-24'!L3,IF('dash board'!$H$5="Persistent Systems Ltd.",'PERSISTENT 23-24&24-25'!L3,IF('dash board'!$H$5="Ipca Laboratories Ltd.",'IPCALAB 7-4-23&24,24&25'!F3,IF('dash board'!$H$5="MRF Ltd.",'-MRF-7423-24&24-25'!L3,""))))) -> 1879382
A5: 45385 | B5: =IF('dash board'!$H$5="Dixon Technologies (India) Ltd.",'DIXON7423-24&24-25'!H4,IF('dash board'!$H$5="Bharat Forge Ltd.",'BHARATFOR 7424-25&23-24'!B4,IF('dash board'!$H$5="Persistent Systems Ltd.",'PERSISTENT 23-24&24-25'!H4,IF('dash board'!$H$5="Ipca Laboratories Ltd.",'IPCALAB 7-4-23&24,24&25'!D4,IF('dash board'!$H$5="MRF Ltd.",'-MRF-7423-24&24-25'!H4,""))))) -> 1224.35 | C5: =IF('dash board'!$H$5="Dixon Technologies (India) Ltd.",'DIXON7423-24&24-25'!D4,IF('dash board'!$H$5="Bharat Forge Ltd.",'BHARATFOR 7424-25&23-24'!D4,IF('dash board'!$H$5="Persistent Systems Ltd.",'PERSISTENT 23-24&24-25'!D4,IF('dash board'!$H$5="Ipca Laboratories Ltd.",'IPCALAB 7-4-23&24,24&25'!H4,IF('dash board'!$H$5="MRF Ltd.",'-MRF-7423-24&24-25'!D4,""))))) -> 1240 | D5: =IF('dash board'!$H$5="Dixon Technologies (India) Ltd.",'DIXON7423-24&24-25'!E4,IF('dash board'!$H$5="Bharat Forge Ltd.",'BHARATFOR 7424-25&23-24'!E4,IF('dash board'!$H$5="Persistent Systems Ltd.",'PERSISTENT 23-24&24-25'!E4,IF('dash board'!$H$5="Ipca Laboratories Ltd.",'IPCALAB 7-4-23&24,24&25'!I4,IF('dash board'!$H$5="MRF Ltd.",'-MRF-7423-24&24-25'!E4,""))))) -> 1215.85 | E5: =IF('dash board'!$H$5="Dixon Technologies (India) Ltd.",'DIXON7423-24&24-25'!C4,IF('dash board'!$H$5="Bharat Forge Ltd.",'BHARATFOR 7424-25&23-24'!C4,IF('dash board'!$H$5="Persistent Systems Ltd.",'PERSISTENT 23-24&24-25'!C4,IF('dash board'!$H$5="Ipca Laboratories Ltd.",'IPCALAB 7-4-23&24,24&25'!G4,IF('dash board'!$H$5="MRF Ltd.",'-MRF-7423-24&24-25'!C4,""))))) -> 1240 | F5: =IF('dash board'!$H$5="Dixon Technologies (India) Ltd.",'DIXON7423-24&24-25'!L4,IF('dash board'!$H$5="Bharat Forge Ltd.",'BHARATFOR 7424-25&23-24'!L4,IF('dash board'!$H$5="Persistent Systems Ltd.",'PERSISTENT 23-24&24-25'!L4,IF('dash board'!$H$5="Ipca Laboratories Ltd.",'IPCALAB 7-4-23&24,24&25'!F4,IF('dash board'!$H$5="MRF Ltd.",'-MRF-7423-24&24-25'!L4,""))))) -> 1653542
A6: 45384 | B6: =IF('dash board'!$H$5="Dixon Technologies (India) Ltd.",'DIXON7423-24&24-25'!H5,IF('dash board'!$H$5="Bharat Forge Ltd.",'BHARATFOR 7424-25&23-24'!B5,IF('dash board'!$H$5="Persistent Systems Ltd.",'PERSISTENT 23-24&24-25'!H5,IF('dash board'!$H$5="Ipca Laboratories Ltd.",'IPCALAB 7-4-23&24,24&25'!D5,IF('dash board'!$H$5="MRF Ltd.",'-MRF-7423-24&24-25'!H5,""))))) -> 1233.55 | C6: =IF('dash board'!$H$5="Dixon Technologies (India) Ltd.",'DIXON7423-24&24-25'!D5,IF('dash board'!$H$5="Bharat Forge Ltd.",'BHARATFOR 7424-25&23-24'!D5,IF('dash board'!$H$5="Persistent Systems Ltd.",'PERSISTENT 23-24&24-25'!D5,IF('dash board'!$H$5="Ipca Laboratories Ltd.",'IPCALAB 7-4-23&24,24&25'!H5,IF('dash board'!$H$5="MRF Ltd.",'-MRF-7423-24&24-25'!D5,""))))) -> 1247.6 | D6: =IF('dash board'!$H$5="Dixon Technologies (India) Ltd.",'DIXON7423-24&24-25'!E5,IF('dash board'!$H$5="Bharat Forge Ltd.",'BHARATFOR 7424-25&23-24'!E5,IF('dash board'!$H$5="Persistent Systems Ltd.",'PERSISTENT 23-24&24-25'!E5,IF('dash board'!$H$5="Ipca Laboratories Ltd.",'IPCALAB 7-4-23&24,24&25'!I5,IF('dash board'!$H$5="MRF Ltd.",'-MRF-7423-24&24-25'!E5,""))))) -> 1225.3 | E6: =IF('dash board'!$H$5="Dixon Technologies (India) Ltd.",'DIXON7423-24&24-25'!C5,IF('dash board'!$H$5="Bharat Forge Ltd.",'BHARATFOR 7424-25&23-24'!C5,IF('dash board'!$H$5="Persistent Systems Ltd.",'PERSISTENT 23-24&24-25'!C5,IF('dash board'!$H$5="Ipca Laboratories Ltd.",'IPCALAB 7-4-23&24,24&25'!G5,IF('dash board'!$H$5="MRF Ltd.",'-MRF-7423-24&24-25'!C5,""))))) -> 1247.6 | F6: =IF('dash board'!$H$5="Dixon Technologies (India) Ltd.",'DIXON7423-24&24-25'!L5,IF('dash board'!$H$5="Bharat Forge Ltd.",'BHARATFOR 7424-25&23-24'!L5,IF('dash board'!$H$5="Persistent Systems Ltd.",'PERSISTENT 23-24&24-25'!L5,IF('dash board'!$H$5="Ipca Laboratories Ltd.",'IPCALAB 7-4-23&24,24&25'!F5,IF('dash board'!$H$5="MRF Ltd.",'-MRF-7423-24&24-25'!L5,""))))) -> 198825
A7: 45383 | B7: =IF('dash board'!$H$5="Dixon Technologies (India) Ltd.",'DIXON7423-24&24-25'!H6,IF('dash board'!$H$5="Bharat Forge Ltd.",'BHARATFOR 7424-25&23-24'!B6,IF('dash board'!$H$5="Persistent Systems Ltd.",'PERSISTENT 23-24&24-25'!H6,IF('dash board'!$H$5="Ipca Laboratories Ltd.",'IPCALAB 7-4-23&24,24&25'!D6,IF('dash board'!$H$5="MRF Ltd.",'-MRF-7423-24&24-25'!H6,""))))) -> 1241.05 | C7: =IF('dash board'!$H$5="Dixon Technologies (India) Ltd.",'DIXON7423-24&24-25'!D6,IF('dash board'!$H$5="Bharat Forge Ltd.",'BHARATFOR 7424-25&23-24'!D6,IF('dash board'!$H$5="Persistent Systems Ltd.",'PERSISTENT 23-24&24-25'!D6,IF('dash board'!$H$5="Ipca Laboratories Ltd.",'IPCALAB 7-4-23&24,24&25'!H6,IF('dash board'!$H$5="MRF Ltd.",'-MRF-7423-24&24-25'!D6,""))))) -> 1257.45 | D7: =IF('dash board'!$H$5="Dixon Technologies (India) Ltd.",'DIXON7423-24&24-25'!E6,IF('dash board'!$H$5="Bharat Forge Ltd.",'BHARATFOR 7424-25&23-24'!E6,IF('dash board'!$H$5="Persistent Systems Ltd.",'PERSISTENT 23-24&24-25'!E6,IF('dash board'!$H$5="Ipca Laboratories Ltd.",'IPCALAB 7-4-23&24,24&25'!I6,IF('dash board'!$H$5="MRF Ltd.",'-MRF-7423-24&24-25'!E6,""))))) -> 1221.5 | E7: =IF('dash board'!$H$5="Dixon Technologies (India) Ltd.",'DIXON7423-24&24-25'!C6,IF('dash board'!$H$5="Bharat Forge Ltd.",'BHARATFOR 7424-25&23-24'!C6,IF('dash board'!$H$5="Persistent Systems Ltd.",'PERSISTENT 23-24&24-25'!C6,IF('dash board'!$H$5="Ipca Laboratories Ltd.",'IPCALAB 7-4-23&24,24&25'!G6,IF('dash board'!$H$5="MRF Ltd.",'-MRF-7423-24&24-25'!C6,""))))) -> 1241 | F7: =IF('dash board'!$H$5="Dixon Technologies (India) Ltd.",'DIXON7423-24&24-25'!L6,IF('dash board'!$H$5="Bharat Forge Ltd.",'BHARATFOR 7424-25&23-24'!L6,IF('dash board'!$H$5="Persistent Systems Ltd.",'PERSISTENT 23-24&24-25'!L6,IF('dash board'!$H$5="Ipca Laboratories Ltd.",'IPCALAB 7-4-23&24,24&25'!F6,IF('dash board'!$H$5="MRF Ltd.",'-MRF-7423-24&24-25'!L6,""))))) -> 349243
A8: 45379 | B8: =IF('dash board'!$H$5="Dixon Technologies (India) Ltd.",'DIXON7423-24&24-25'!H7,IF('dash board'!$H$5="Bharat Forge Ltd.",'BHARATFOR 7424-25&23-24'!B7,IF('dash board'!$H$5="Persistent Systems Ltd.",'PERSISTENT 23-24&24-25'!H7,IF('dash board'!$H$5="Ipca Laboratories Ltd.",'IPCALAB 7-4-23&24,24&25'!D7,IF('dash board'!$H$5="MRF Ltd.",'-MRF-7423-24&24-25'!H7,""))))) -> 1237.4 | C8: =IF('dash board'!$H$5="Dixon Technologies (India) Ltd.",'DIXON7423-24&24-25'!D7,IF('dash board'!$H$5="Bharat Forge Ltd.",'BHARATFOR 7424-25&23-24'!D7,IF('dash board'!$H$5="Persistent Systems Ltd.",'PERSISTENT 23-24&24-25'!D7,IF('dash board'!$H$5="Ipca Laboratories Ltd.",'IPCALAB 7-4-23&24,24&25'!H7,IF('dash board'!$H$5="MRF Ltd.",'-MRF-7423-24&24-25'!D7,""))))) -> 1245 | D8: =IF('dash board'!$H$5="Dixon Technologies (India) Ltd.",'DIXON7423-24&24-25'!E7,IF('dash board'!$H$5="Bharat Forge Ltd.",'BHARATFOR 7424-25&23-24'!E7,IF('dash board'!$H$5="Persistent Systems Ltd.",'PERSISTENT 23-24&24-25'!E7,IF('dash board'!$H$5="Ipca Laboratories Ltd.",'IPCALAB 7-4-23&24,24&25'!I7,IF('dash board'!$H$5="MRF Ltd.",'-MRF-7423-24&24-25'!E7,""))))) -> 1202.35 | E8: =IF('dash board'!$H$5="Dixon Technologies (India) Ltd.",'DIXON7423-24&24-25'!C7,IF('dash board'!$H$5="Bharat Forge Ltd.",'BHARATFOR 7424-25&23-24'!C7,IF('dash board'!$H$5="Persistent Systems Ltd.",'PERSISTENT 23-24&24-25'!C7,IF('dash board'!$H$5="Ipca Laboratories Ltd.",'IPCALAB 7-4-23&24,24&25'!G7,IF('dash board'!$H$5="MRF Ltd.",'-MRF-7423-24&24-25'!C7,""))))) -> 1205.4 | F8: =IF('dash board'!$H$5="Dixon Technologies (India) Ltd.",'DIXON7423-24&24-25'!L7,IF('dash board'!$H$5="Bharat Forge Ltd.",'BHARATFOR 7424-25&23-24'!L7,IF('dash board'!$H$5="Persistent Systems Ltd.",'PERSISTENT 23-24&24-25'!L7,IF('dash board'!$H$5="Ipca Laboratories Ltd.",'IPCALAB 7-4-23&24,24&25'!F7,IF('dash board'!$H$5="MRF Ltd.",'-MRF-7423-24&24-25'!L7,""))))) -> 668011
A9: 45378 | B9: =IF('dash board'!$H$5="Dixon Technologies (India) Ltd.",'DIXON7423-24&24-25'!H8,IF('dash board'!$H$5="Bharat Forge Ltd.",'BHARATFOR 7424-25&23-24'!B8,IF('dash board'!$H$5="Persistent Systems Ltd.",'PERSISTENT 23-24&24-25'!H8,IF('dash board'!$H$5="Ipca Laboratories Ltd.",'IPCALAB 7-4-23&24,24&25'!D8,IF('dash board'!$H$5="MRF Ltd.",'-MRF-7423-24&24-25'!H8,""))))) -> 1205.3 | C9: =IF('dash board'!$H$5="Dixon Technologies (India) Ltd.",'DIXON7423-24&24-25'!D8,IF('dash board'!$H$5="Bharat Forge Ltd.",'BHARATFOR 7424-25&23-24'!D8,IF('dash board'!$H$5="Persistent Systems Ltd.",'PERSISTENT 23-24&24-25'!D8,IF('dash board'!$H$5="Ipca Laboratories Ltd.",'IPCALAB 7-4-23&24,24&25'!H8,IF('dash board'!$H$5="MRF Ltd.",'-MRF-7423-24&24-25'!D8,""))))) -> 1220.95 | D9: =IF('dash board'!$H$5="Dixon Technologies (India) Ltd.",'DIXON7423-24&24-25'!E8,IF('dash board'!$H$5="Bharat Forge Ltd.",'BHARATFOR 7424-25&23-24'!E8,IF('dash board'!$H$5="Persistent Systems Ltd.",'PERSISTENT 23-24&24-25'!E8,IF('dash board'!$H$5="Ipca Laboratories Ltd.",'IPCALAB 7-4-23&24,24&25'!I8,IF('dash board'!$H$5="MRF Ltd.",'-MRF-7423-24&24-25'!E8,""))))) -> 1185 | E9: =IF('dash board'!$H$5="Dixon Technologies (India) Ltd.",'DIXON7423-24&24-25'!C8,IF('dash board'!$H$5="Bharat Forge Ltd.",'BHARATFOR 7424-25&23-24'!C8,IF('dash board'!$H$5="Persistent Systems Ltd.",'PERSISTENT 23-24&24-25'!C8,IF('dash board'!$H$5="Ipca Laboratories Ltd.",'IPCALAB 7-4-23&24,24&25'!G8,IF('dash board'!$H$5="MRF Ltd.",'-MRF-7423-24&24-25'!C8,""))))) -> 1205 | F9: =IF('dash board'!$H$5="Dixon Technologies (India) Ltd.",'DIXON7423-24&24-25'!L8,IF('dash board'!$H$5="Bharat Forge Ltd.",'BHARATFOR 7424-25&23-24'!L8,IF('dash board'!$H$5="Persistent Systems Ltd.",'PERSISTENT 23-24&24-25'!L8,IF('dash board'!$H$5="Ipca Laboratories Ltd.",'IPCALAB 7-4-23&24,24&25'!F8,IF('dash board'!$H$5="MRF Ltd.",'-MRF-7423-24&24-25'!L8,""))))) -> 383672
A10: 45377 | B10: =IF('dash board'!$H$5="Dixon Technologies (India) Ltd.",'DIXON7423-24&24-25'!H9,IF('dash board'!$H$5="Bharat Forge Ltd.",'BHARATFOR 7424-25&23-24'!B9,IF('dash board'!$H$5="Persistent Systems Ltd.",'PERSISTENT 23-24&24-25'!H9,IF('dash board'!$H$5="Ipca Laboratories Ltd.",'IPCALAB 7-4-23&24,24&25'!D9,IF('dash board'!$H$5="MRF Ltd.",'-MRF-7423-24&24-25'!H9,""))))) -> 1200.9 | C10: =IF('dash board'!$H$5="Dixon Technologies (India) Ltd.",'DIXON7423-24&24-25'!D9,IF('dash board'!$H$5="Bharat Forge Ltd.",'BHARATFOR 7424-25&23-24'!D9,IF('dash board'!$H$5="Persistent Systems Ltd.",'PERSISTENT 23-24&24-25'!D9,IF('dash board'!$H$5="Ipca Laboratories Ltd.",'IPCALAB 7-4-23&24,24&25'!H9,IF('dash board'!$H$5="MRF Ltd.",'-MRF-7423-24&24-25'!D9,""))))) -> 1219 | D10: =IF('dash board'!$H$5="Dixon Technologies (India) Ltd.",'DIXON7423-24&24-25'!E9,IF('dash board'!$H$5="Bharat Forge Ltd.",'BHARATFOR 7424-25&23-24'!E9,IF('dash board'!$H$5="Persistent Systems Ltd.",'PERSISTENT 23-24&24-25'!E9,IF('dash board'!$H$5="Ipca Laboratories Ltd.",'IPCALAB 7-4-23&24,24&25'!I9,IF('dash board'!$H$5="MRF Ltd.",'-MRF-7423-24&24-25'!E9,""))))) -> 1186 | E10: =IF('dash board'!$H$5="Dixon Technologies (India) Ltd.",'DIXON7423-24&24-25'!C9,IF('dash board'!$H$5="Bharat Forge Ltd.",'BHARATFOR 7424-25&23-24'!C9,IF('dash board'!$H$5="Persistent Systems Ltd.",'PERSISTENT 23-24&24-25'!C9,IF('dash board'!$H$5="Ipca Laboratories Ltd.",'IPCALAB 7-4-23&24,24&25'!G9,IF('dash board'!$H$5="MRF Ltd.",'-MRF-7423-24&24-25'!C9,""))))) -> 1186 | F10: =IF('dash board'!$H$5="Dixon Technologies (India) Ltd.",'DIXON7423-24&24-25'!L9,IF('dash board'!$H$5="Bharat Forge Ltd.",'BHARATFOR 7424-25&23-24'!L9,IF('dash board'!$H$5="Persistent Systems Ltd.",'PERSISTENT 23-24&24-25'!L9,IF('dash board'!$H$5="Ipca Laboratories Ltd.",'IPCALAB 7-4-23&24,24&25'!F9,IF('dash board'!$H$5="MRF Ltd.",'-MRF-7423-24&24-25'!L9,""))))) -> 484695
A11: 45373 | B11: =IF('dash board'!$H$5="Dixon Technologies (India) Ltd.",'DIXON7423-24&24-25'!H10,IF('dash board'!$H$5="Bharat Forge Ltd.",'BHARATFOR 7424-25&23-24'!B10,IF('dash board'!$H$5="Persistent Systems Ltd.",'PERSISTENT 23-24&24-25'!H10,IF('dash board'!$H$5="Ipca Laboratories Ltd.",'IPCALAB 7-4-23&24,24&25'!D10,IF('dash board'!$H$5="MRF Ltd.",'-MRF-7423-24&24-25'!H10,""))))) -> 1196.05 | C11: =IF('dash board'!$H$5="Dixon Technologies (India) Ltd.",'DIXON7423-24&24-25'!D10,IF('dash board'!$H$5="Bharat Forge Ltd.",'BHARATFOR 7424-25&23-24'!D10,IF('dash board'!$H$5="Persistent Systems Ltd.",'PERSISTENT 23-24&24-25'!D10,IF('dash board'!$H$5="Ipca Laboratories Ltd.",'IPCALAB 7-4-23&24,24&25'!H10,IF('dash board'!$H$5="MRF Ltd.",'-MRF-7423-24&24-25'!D10,""))))) -> 1209.15 | D11: =IF('dash board'!$H$5="Dixon Technologies (India) Ltd.",'DIXON7423-24&24-25'!E10,IF('dash board'!$H$5="Bharat Forge Ltd.",'BHARATFOR 7424-25&23-24'!E10,IF('dash board'!$H$5="Persistent Systems Ltd.",'PERSISTENT 23-24&24-25'!E10,IF('dash board'!$H$5="Ipca Laboratories Ltd.",'IPCALAB 7-4-23&24,24&25'!I10,IF('dash board'!$H$5="MRF Ltd.",'-MRF-7423-24&24-25'!E10,""))))) -> 1170.2 | E11: =IF('dash board'!$H$5="Dixon Technologies (India) Ltd.",'DIXON7423-24&24-25'!C10,IF('dash board'!$H$5="Bharat Forge Ltd.",'BHARATFOR 7424-25&23-24'!C10,IF('dash board'!$H$5="Persistent Systems Ltd.",'PERSISTENT 23-24&24-25'!C10,IF('dash board'!$H$5="Ipca Laboratories Ltd.",'IPCALAB 7-4-23&24,24&25'!G10,IF('dash board'!$H$5="MRF Ltd.",'-MRF-7423-24&24-25'!C10,""))))) -> 1176.4 | F11: =IF('dash board'!$H$5="Dixon Technologies (India) Ltd.",'DIXON7423-24&24-25'!L10,IF('dash board'!$H$5="Bharat Forge Ltd.",'BHARATFOR 7424-25&23-24'!L10,IF('dash board'!$H$5="Persistent Systems Ltd.",'PERSISTENT 23-24&24-25'!L10,IF('dash board'!$H$5="Ipca Laboratories Ltd.",'IPCALAB 7-4-23&24,24&25'!F10,IF('dash board'!$H$5="MRF Ltd.",'-MRF-7423-24&24-25'!L10,""))))) -> 748972
A12: 45372 | B12: =IF('dash board'!$H$5="Dixon Technologies (India) Ltd.",'DIXON7423-24&24-25'!H11,IF('dash board'!$H$5="Bharat Forge Ltd.",'BHARATFOR 7424-25&23-24'!B11,IF('dash board'!$H$5="Persistent Systems Ltd.",'PERSISTENT 23-24&24-25'!H11,IF('dash board'!$H$5="Ipca Laboratories Ltd.",'IPCALAB 7-4-23&24,24&25'!D11,IF('dash board'!$H$5="MRF Ltd.",'-MRF-7423-24&24-25'!H11,""))))) -> 1174.15 | C12: =IF('dash board'!$H$5="Dixon Technologies (India) Ltd.",'DIXON7423-24&24-25'!D11,IF('dash board'!$H$5="Bharat Forge Ltd.",'BHARATFOR 7424-25&23-24'!D11,IF('dash board'!$H$5="Persistent Systems Ltd.",'PERSISTENT 23-24&24-25'!D11,IF('dash board'!$H$5="Ipca Laboratories Ltd.",'IPCALAB 7-4-23&24,24&25'!H11,IF('dash board'!$H$5="MRF Ltd.",'-MRF-7423-24&24-25'!D11,""))))) -> 1178.8 | D12: =IF('dash board'!$H$5="Dixon Technologies (India) Ltd.",'DIXON7423-24&24-25'!E11,IF('dash board'!$H$5="Bharat Forge Ltd.",'BHARATFOR 7424-25&23-24'!E11,IF('dash board'!$H$5="Persistent Systems Ltd.",'PERSISTENT 23-24&24-25'!E11,IF('dash board'!$H$5="Ipca Laboratories Ltd.",'IPCALAB 7-4-23&24,24&25'!I11,IF('dash board'!$H$5="MRF Ltd.",'-MRF-7423-24&24-25'!E11,""))))) -> 1140.8 | E12: =IF('dash board'!$H$5="Dixon Technologies (India) Ltd.",'DIXON7423-24&24-25'!C11,IF('dash board'!$H$5="Bharat Forge Ltd.",'BHARATFOR 7424-25&23-24'!C11,IF('dash board'!$H$5="Persistent Systems Ltd.",'PERSISTENT 23-24&24-25'!C11,IF('dash board'!$H$5="Ipca Laboratories Ltd.",'IPCALAB 7-4-23&24,24&25'!G11,IF('dash board'!$H$5="MRF Ltd.",'-MRF-7423-24&24-25'!C11,""))))) -> 1172 | F12: =IF('dash board'!$H$5="Dixon Technologies (India) Ltd.",'DIXON7423-24&24-25'!L11,IF('dash board'!$H$5="Bharat Forge Ltd.",'BHARATFOR 7424-25&23-24'!L11,IF('dash board'!$H$5="Persistent Systems Ltd.",'PERSISTENT 23-24&24-25'!L11,IF('dash board'!$H$5="Ipca Laboratories Ltd.",'IPCALAB 7-4-23&24,24&25'!F11,IF('dash board'!$H$5="MRF Ltd.",'-MRF-7423-24&24-25'!L11,""))))) -> 309808
A13: 45371 | B13: =IF('dash board'!$H$5="Dixon Technologies (India) Ltd.",'DIXON7423-24&24-25'!H12,IF('dash board'!$H$5="Bharat Forge Ltd.",'BHARATFOR 7424-25&23-24'!B12,IF('dash board'!$H$5="Persistent Systems Ltd.",'PERSISTENT 23-24&24-25'!H12,IF('dash board'!$H$5="Ipca Laboratories Ltd.",'IPCALAB 7-4-23&24,24&25'!D12,IF('dash board'!$H$5="MRF Ltd.",'-MRF-7423-24&24-25'!H12,""))))) -> 1160.95 | C13: =IF('dash board'!$H$5="Dixon Technologies (India) Ltd.",'DIXON7423-24&24-25'!D12,IF('dash board'!$H$5="Bharat Forge Ltd.",'BHARATFOR 7424-25&23-24'!D12,IF('dash board'!$H$5="Persistent Systems Ltd.",'PERSISTENT 23-24&24-25'!D12,IF('dash board'!$H$5="Ipca Laboratories Ltd.",'IPCALAB 7-4-23&24,24&25'!H12,IF('dash board'!$H$5="MRF Ltd.",'-MRF-7423-24&24-25'!D12,""))))) -> 1167.95 | D13: =IF('dash board'!$H$5="Dixon Technologies (India) Ltd.",'DIXON7423-24&24-25'!E12,IF('dash board'!$H$5="Bharat Forge Ltd.",'BHARATFOR 7424-25&23-24'!E12,IF('dash board'!$H$5="Persistent Systems Ltd.",'PERSISTENT 23-24&24-25'!E12,IF('dash board'!$H$5="Ipca Laboratories Ltd.",'IPCALAB 7-4-23&24,24&25'!I12,IF('dash board'!$H$5="MRF Ltd.",'-MRF-7423-24&24-25'!E12,""))))) -> 1129.15 | E13: =IF('dash board'!$H$5="Dixon Technologies (India) Ltd.",'DIXON7423-24&24-25'!C12,IF('dash board'!$H$5="Bharat Forge Ltd.",'BHARATFOR 7424-25&23-24'!C12,IF('dash board'!$H$5="Persistent Systems Ltd.",'PERSISTENT 23-24&24-25'!C12,IF('dash board'!$H$5="Ipca Laboratories Ltd.",'IPCALAB 7-4-23&24,24&25'!G12,IF('dash board'!$H$5="MRF Ltd.",'-MRF-7423-24&24-25'!C12,""))))) -> 1140.6 | F13: =IF('dash board'!$H$5="Dixon Technologies (India) Ltd.",'DIXON7423-24&24-25'!L12,IF('dash board'!$H$5="Bharat Forge Ltd.",'BHARATFOR 7424-25&23-24'!L12,IF('dash board'!$H$5="Persistent Systems Ltd.",'PERSISTENT 23-24&24-25'!L12,IF('dash board'!$H$5="Ipca Laboratories Ltd.",'IPCALAB 7-4-23&24,24&25'!F12,IF('dash board'!$H$5="MRF Ltd.",'-MRF-7423-24&24-25'!L12,""))))) -> 241592
A14: 45370 | B14: =IF('dash board'!$H$5="Dixon Technologies (India) Ltd.",'DIXON7423-24&24-25'!H13,IF('dash board'!$H$5="Bharat Forge Ltd.",'BHARATFOR 7424-25&23-24'!B13,IF('dash board'!$H$5="Persistent Systems Ltd.",'PERSISTENT 23-24&24-25'!H13,IF('dash board'!$H$5="Ipca Laboratories Ltd.",'IPCALAB 7-4-23&24,24&25'!D13,IF('dash board'!$H$5="MRF Ltd.",'-MRF-7423-24&24-25'!H13,""))))) -> 1144.15 | C14: =IF('dash board'!$H$5="Dixon Technologies (India) Ltd.",'DIXON7423-24&24-25'!D13,IF('dash board'!$H$5="Bharat Forge Ltd.",'BHARATFOR 7424-25&23-24'!D13,IF('dash board'!$H$5="Persistent Systems Ltd.",'PERSISTENT 23-24&24-25'!D13,IF('dash board'!$H$5="Ipca Laboratories Ltd.",'IPCALAB 7-4-23&24,24&25'!H13,IF('dash board'!$H$5="MRF Ltd.",'-MRF-7423-24&24-25'!D13,""))))) -> 1165.05 | D14: =IF('dash board'!$H$5="Dixon Technologies (India) Ltd.",'DIXON7423-24&24-25'!E13,IF('dash board'!$H$5="Bharat Forge Ltd.",'BHARATFOR 7424-25&23-24'!E13,IF('dash board'!$H$5="Persistent Systems Ltd.",'PERSISTENT 23-24&24-25'!E13,IF('dash board'!$H$5="Ipca Laboratories Ltd.",'IPCALAB 7-4-23&24,24&25'!I13,IF('dash board'!$H$5="MRF Ltd.",'-MRF-7423-24&24-25'!E13,""))))) -> 1135.75 | E14: =IF('dash board'!$H$5="Dixon Technologies (India) Ltd.",'DIXON7423-24&24-25'!C13,IF('dash board'!$H$5="Bharat Forge Ltd.",'BHARATFOR 7424-25&23-24'!C13,IF('dash board'!$H$5="Persistent Systems Ltd.",'PERSISTENT 23-24&24-25'!C13,IF('dash board'!$H$5="Ipca Laboratories Ltd.",'IPCALAB 7-4-23&24,24&25'!G13,IF('dash board'!$H$5="MRF Ltd.",'-MRF-7423-24&24-25'!C13,""))))) -> 1161.05 | F14: =IF('dash board'!$H$5="Dixon Technologies (India) Ltd.",'DIXON7423-24&24-25'!L13,IF('dash board'!$H$5="Bharat Forge Ltd.",'BHARATFOR 7424-25&23-24'!L13,IF('dash board'!$H$5="Persistent Systems Ltd.",'PERSISTENT 23-24&24-25'!L13,IF('dash board'!$H$5="Ipca Laboratories Ltd.",'IPCALAB 7-4-23&24,24&25'!F13,IF('dash board'!$H$5="MRF Ltd.",'-MRF-7423-24&24-25'!L13,""))))) -> 191008
... A499: 45390 | B499: =IF('dash board'!$H$5="Dixon Technologies (India) Ltd.",'DIXON7423-24&24-25'!H498,IF('dash board'!$H$5="Bharat Forge Ltd.",'BHARATFOR 7424-25&23-24'!B498,IF('dash board'!$H$5="Persistent Systems Ltd.",'PERSISTENT 23-24&24-25'!H498,IF('dash board'!$H$5="Ipca Laboratories Ltd.",'IPCALAB 7-4-23&24,24&25'!D498,IF('dash board'!$H$5="MRF Ltd.",'-MRF-7423-24&24-25'!H498,""))))) -> 1322.15 | C499: =IF('dash board'!$H$5="Dixon Technologies (India) Ltd.",'DIXON7423-24&24-25'!D498,IF('dash board'!$H$5="Bharat Forge Ltd.",'BHARATFOR 7424-25&23-24'!D498,IF('dash board'!$H$5="Persistent Systems Ltd.",'PERSISTENT 23-24&24-25'!D498,IF('dash board'!$H$5="Ipca Laboratories Ltd.",'IPCALAB 7-4-23&24,24&25'!H498,IF('dash board'!$H$5="MRF Ltd.",'-MRF-7423-24&24-25'!D498,""))))) -> 1336.9 | D499: =IF('dash board'!$H$5="Dixon Technologies (India) Ltd.",'DIXON7423-24&24-25'!E498,IF('dash board'!$H$5="Bharat Forge Ltd.",'BHARATFOR 7424-25&23-24'!E498,IF('dash board'!$H$5="Persistent Systems Ltd.",'PERSISTENT 23-24&24-25'!E498,IF('dash board'!$H$5="Ipca Laboratories Ltd.",'IPCALAB 7-4-23&24,24&25'!I498,IF('dash board'!$H$5="MRF Ltd.",'-MRF-7423-24&24-25'!E498,""))))) -> 1286.5 | E499: =IF('dash board'!$H$5="Dixon Technologies (India) Ltd.",'DIXON7423-24&24-25'!C498,IF('dash board'!$H$5="Bharat Forge Ltd.",'BHARATFOR 7424-25&23-24'!C498,IF('dash board'!$H$5="Persistent Systems Ltd.",'PERSISTENT 23-24&24-25'!C498,IF('dash board'!$H$5="Ipca Laboratories Ltd.",'IPCALAB 7-4-23&24,24&25'!G498,IF('dash board'!$H$5="MRF Ltd.",'-MRF-7423-24&24-25'!C498,""))))) -> 1306.5 | F499: =IF('dash board'!$H$5="Dixon Technologies (India) Ltd.",'DIXON7423-24&24-25'!L498,IF('dash board'!$H$5="Bharat Forge Ltd.",'BHARATFOR 7424-25&23-24'!L498,IF('dash board'!$H$5="Persistent Systems Ltd.",'PERSISTENT 23-24&24-25'!L498,IF('dash board'!$H$5="Ipca Laboratories Ltd.",'IPCALAB 7-4-23&24,24&25'!F498,IF('dash board'!$H$5="MRF Ltd.",'-MRF-7423-24&24-25'!L498,""))))) -> 1078562

Sheet dash board
E1: PORTFOLIO DASH BOARD
E4: PERFORMANCE ANALYSIS | G4: fund | H4: quant returns
G5: company | H5: Ipca Laboratories Ltd.
E6: LATEST CLOSE PRICE | F6: =IF(H5='data sheet'!B1,'data sheet'!C253,FALSE) -> 1491.75
E7: 5DAY-%CHANGE | F7: =('data sheet'!B257-'data sheet'!B253)/'data sheet'!B253 -> 0.073360729
E8: HIGHEST VOLUME DAY | F8: =INDEX('data sheet'!A3:A499, MATCH(MAX('data sheet'!F3:F499),'data sheet'!F3:F499, 0)) -> 45041
